Workbook

Sheet Cover
A1: Farm financial model — structure (Stage 1)
A2: Generated 2026-10-19 by scripts/build_financial_model.py
A4: Status | B4: STRUCTURE AND PLACEHOLDERS. Inputs labelled A or U are placeholders, not findings. Do not quote outputs as forecasts.
A5: Purpose | B5: Tests whether each farm model fits the founder's capital, when cash turns positive, and which assumptions matter most.
A6: Terms | B6: Real terms (constant 2026 RWF, no inflation). Month 1 = first month of spending. A farm year = 12 model months.
A7: How to use | B7: Pick a scenario and a farm model on Control. Edit only blue cells. Results are on Metrics; detail on Annual and CashFlow.
A8: Legend: blue | B8: Input you may edit (Control, Assumptions, Models, Curves, Sensitivity).
A9: Legend: black | B9: Formula. Do not overwrite.
A10: Legend: green | B10: Direct link to another sheet.
A11: Legend: yellow fill | B11: Key inputs to confirm with the founder.
A12: Labels | B12: V verified (source ID) · E estimate (method shown) · A assumption · U unknown. See CLAUDE.md.
A13: Structural constants | B13: Sale age 9 months · first-birth lag 6 months · receivable lag 1 month. Change them in the script and rebuild.
A14: Not modelled yet | B14: Loans and interest, inflation, tax losses carried forward, terminal value of orchards, value-added processing, agritourism.
A15: Sheets | B15: Control · Assumptions · Models · Curves · Sensitivity · Land · Trees · Livestock · Feed · CapEx · CashFlow · Annual · Metrics

Sheet Control
A1: Control
A2: The two switches and the founder's key inputs. Blue cells only.
A4: Key | B4: Input | C4: Value | D4: Unit | E4: Note
A5: scenario | B5: Scenario (1 downside · 2 base · 3 upside) | C5: 2 | D5: index | E5: Drives every Assumptions row
A6: model | B6: Farm model (1 M1 · 2 M2 · 3 M3) | C6: 1 | D6: index | E6: Drives every Models row
A7: area | B7: Total farm area | C7: 5 | D7: ha | E7: [A] founder: 2–10 ha; base 5 ha until surveyed
A8: capital | B8: Capital available, years 1–2 | C8: 35000000 | D8: RWF | E8: [A] founder: under USD 25k
A9: start_year | B9: Model start year | C9: 2026 | D9: year | E9: Month 1 = first month of spending
A10: start_month | B10: Model start month (1–12) | C10: 11 | D10: month | E10: 11 = November
A11: plant_m | B11: Tree planting month (model month #) | C11: 5 | D11: month # | E11: [A] 5 = March 2027, Season B onset
A12: past_m | B12: Pasture/fodder planting month (model month #) | C12: 5 | D12: month # | E12: [A] same rains as trees
B14: Selected scenario | C14: =CHOOSE(Control!$C$5,"Downside","Base","Upside")
B15: Selected farm model | C15: =CHOOSE(Control!$C$6,"M1 Conservative mixed","M2 Diversified commercial","M3 Tech-enabled integrated")
B16: Capital available in USD (at the Assumptions rate) | C16: =Control!$C$8/Assumptions!$H$6

Sheet Assumptions
A1: Assumptions
A2: Uncertain inputs with downside / base / upside values. Selected = the value for the scenario chosen on Control.
A4: ID | B4: Group | C4: Parameter | D4: Unit | E4: Downside | F4: Base | G4: Upside | H4: Selected | I4: Label | J4: Source | K4: Notes
B5: General
A6: FX | B6: General | C6: Exchange rate | D6: RWF per USD | E6: 1470 | F6: 1470 | G6: 1470 | H6: =CHOOSE(Control!$C$5,E6,F6,G6) | I6: A | J6: placeholder — pending Stage 1 research | K6: Verify against the BNR reference rate
A7: DR | B7: General | C7: Real discount rate | D7: per year | E7: 0.14 | F7: 0.12 | G7: 0.1 | H7: =CHOOSE(Control!$C$5,E7,F7,G7) | I7: A | J7: judgement | K7: Real terms: the model is in constant 2026 RWF
A8: TAX | B8: General | C8: Income tax rate on profit | D8: share | E8: 0.28 | F8: 0.28 | G8: 0.28 | H8: =CHOOSE(Control!$C$5,E8,F8,G8) | I8: U | J8: placeholder — pending Stage 1 research | K8: Confirm agricultural income treatment with RRA
A9: CREDIT | B9: General | C9: Share of sales on credit | D9: share | E9: 0.6 | F9: 0.5 | G9: 0.3 | H9: =CHOOSE(Control!$C$5,E9,F9,G9) | I9: A | J9: judgement | K9: Collected 1 month later
A10: CONT | B10: General | C10: Capex contingency | D10: share of capex | E10: 0.15 | F10: 0.1 | G10: 0.08 | H10: =CHOOSE(Control!$C$5,E10,F10,G10) | I10: A | J10: judgement
A11: MKTG | B11: General | C11: Marketing and sales cost | D11: share of sales | E11: 0.03 | F11: 0.02 | G11: 0.02 | H11: =CHOOSE(Control!$C$5,E11,F11,G11) | I11: A | J11: judgement
A12: RM | B12: General | C12: Repairs and maintenance | D12: share of capex per yr | E12: 0.05 | F12: 0.04 | G12: 0.03 | H12: =CHOOSE(Control!$C$5,E12,F12,G12) | I12: A | J12: judgement
B13: Labour
A14: WAGE | B14: Labour | C14: Permanent worker wage | D14: RWF per month | E14: 60000 | F14: 50000 | G14: 45000 | H14: =CHOOSE(Control!$C$5,E14,F14,G14) | I14: A | J14: placeholder — pending Stage 1 research
A15: DAYWAGE | B15: Labour | C15: Casual labour wage | D15: RWF per day | E15: 2500 | F15: 2000 | G15: 1800 | H15: =CHOOSE(Control!$C$5,E15,F15,G15) | I15: A | J15: placeholder — pending Stage 1 research
A16: DAYS_HA | B16: Labour | C16: Casual labour in orchard | D16: days per ha per yr | E16: 120 | F16: 100 | G16: 80 | H16: =CHOOSE(Control!$C$5,E16,F16,G16) | I16: A | J16: placeholder — pending Stage 1 research
B17: Capital costs
A18: FENCE | B18: Capital costs | C18: Perimeter fence | D18: RWF per m | E18: 6000 | F18: 5000 | G18: 4000 | H18: =CHOOSE(Control!$C$5,E18,F18,G18) | I18: A | J18: placeholder — pending Stage 1 research
A19: IFENCE | B19: Capital costs | C19: Internal paddock fence | D19: RWF per m | E19: 3500 | F19: 3000 | G19: 2500 | H19: =CHOOSE(Control!$C$5,E19,F19,G19) | I19: A | J19: placeholder — pending Stage 1 research
A20: GATE | B20: Capital costs | C20: Gate | D20: RWF each | E20: 250000 | F20: 200000 | G20: 150000 | H20: =CHOOSE(Control!$C$5,E20,F20,G20) | I20: A | J20: placeholder — pending Stage 1 research
A21: TANK | B21: Capital costs | C21: Water storage | D21: RWF per m3 | E21: 120000 | F21: 100000 | G21: 90000 | H21: =CHOOSE(Control!$C$5,E21,F21,G21) | I21: A | J21: placeholder — pending Stage 1 research
A22: GUTTER | B22: Capital costs | C22: Rainwater harvesting fittings | D22: RWF lump | E22: 400000 | F22: 300000 | G22: 250000 | H22: =CHOOSE(Control!$C$5,E22,F22,G22) | I22: A | J22: placeholder — pending Stage 1 research
A23: BORE | B23: Capital costs | C23: Borehole (if legal and viable) | D23: RWF lump | E23: 12000000 | F23: 9000000 | G23: 7000000 | H23: =CHOOSE(Control!$C$5,E23,F23,G23) | I23: U | J23: placeholder — pending Stage 1 research | K23: Hydrogeology and permit unknown
A24: PUMP | B24: Capital costs | C24: Solar pump system | D24: RWF lump | E24: 4500000 | F24: 3500000 | G24: 3000000 | H24: =CHOOSE(Control!$C$5,E24,F24,G24) | I24: A | J24: placeholder — pending Stage 1 research
A25: DRIP | B25: Capital costs | C25: Drip irrigation | D25: RWF per ha | E25: 4500000 | F25: 3500000 | G25: 3000000 | H25: =CHOOSE(Control!$C$5,E25,F25,G25) | I25: A | J25: placeholder — pending Stage 1 research
A26: PAST_EST | B26: Capital costs | C26: Pasture establishment | D26: RWF per ha | E26: 600000 | F26: 450000 | G26: 350000 | H26: =CHOOSE(Control!$C$5,E26,F26,G26) | I26: A | J26: placeholder — pending Stage 1 research
A27: FOD_EST | B27: Capital costs | C27: Fodder bank establishment | D27: RWF per ha | E27: 900000 | F27: 700000 | G27: 550000 | H27: =CHOOSE(Control!$C$5,E27,F27,G27) | I27: A | J27: placeholder — pending Stage 1 research
A28: HOUSE | B28: Capital costs | C28: Animal house | D28: RWF per m2 | E28: 60000 | F28: 45000 | G28: 35000 | H28: =CHOOSE(Control!$C$5,E28,F28,G28) | I28: A | J28: placeholder — pending Stage 1 research
A29: M2HEAD | B29: Capital costs | C29: House floor area per adult animal | D29: m2 per head | E29: 1.5 | F29: 1.2 | G29: 1 | H29: =CHOOSE(Control!$C$5,E29,F29,G29) | I29: A | J29: placeholder — pending Stage 1 research
A30: QUAR | B30: Capital costs | C30: Quarantine pen and handling race | D30: RWF lump | E30: 800000 | F30: 600000 | G30: 500000 | H30: =CHOOSE(Control!$C$5,E30,F30,G30) | I30: A | J30: placeholder — pending Stage 1 research
A31: SOIL | B31: Capital costs | C31: Soil test | D31: RWF per sample | E31: 40000 | F31: 30000 | G31: 25000 | H31: =CHOOSE(Control!$C$5,E31,F31,G31) | I31: U | J31: placeholder — pending Stage 1 research | K31: Get lab quotes
A32: WATER | B32: Capital costs | C32: Water test | D32: RWF per sample | E32: 60000 | F32: 45000 | G32: 35000 | H32: =CHOOSE(Control!$C$5,E32,F32,G32) | I32: U | J32: placeholder — pending Stage 1 research | K32: Get lab quotes
A33: SURVEY | B33: Capital costs | C33: Survey, title and legal checks | D33: RWF lump | E33: 600000 | F33: 400000 | G33: 300000 | H33: =CHOOSE(Control!$C$5,E33,F33,G33) | I33: U | J33: placeholder — pending Stage 1 research
A34: PERMIT | B34: Capital costs | C34: Permits and compliance | D34: RWF lump | E34: 500000 | F34: 300000 | G34: 200000 | H34: =CHOOSE(Control!$C$5,E34,F34,G34) | I34: U | J34: placeholder — pending Stage 1 research
A35: PROF | B35: Capital costs | C35: Professional set-up visits (agronomist, vet) | D35: RWF lump | E35: 1000000 | F35: 800000 | G35: 600000 | H35: =CHOOSE(Control!$C$5,E35,F35,G35) | I35: A | J35: placeholder — pending Stage 1 research
A36: PV | B36: Capital costs | C36: Solar PV with battery | D36: RWF per kWp | E36: 2500000 | F36: 2000000 | G36: 1700000 | H36: =CHOOSE(Control!$C$5,E36,F36,G36) | I36: A | J36: placeholder — pending Stage 1 research
A37: SCALE | B37: Capital costs | C37: Livestock weighing scale | D37: RWF lump | E37: 600000 | F37: 450000 | G37: 350000 | H37: =CHOOSE(Control!$C$5,E37,F37,G37) | I37: A | J37: placeholder — pending Stage 1 research
B38: Operating costs
A39: VET | B39: Operating costs | C39: Veterinary care and medicines | D39: RWF per head per yr | E39: 8000 | F39: 6000 | G39: 5000 | H39: =CHOOSE(Control!$C$5,E39,F39,G39) | I39: A | J39: placeholder — pending Stage 1 research | K39: Confirm with a Rwandan vet
A40: MINERAL | B40: Operating costs | C40: Minerals and supplements | D40: RWF per head per yr | E40: 3000 | F40: 2500 | G40: 2000 | H40: =CHOOSE(Control!$C$5,E40,F40,G40) | I40: A | J40: placeholder — pending Stage 1 research
A41: FERT | B41: Operating costs | C41: Orchard inputs (fertiliser, compost, protection) | D41: RWF per ha per yr | E41: 900000 | F41: 700000 | G41: 550000 | H41: =CHOOSE(Control!$C$5,E41,F41,G41) | I41: A | J41: placeholder — pending Stage 1 research
A42: PASTM | B42: Operating costs | C42: Pasture and fodder upkeep | D42: RWF per ha per yr | E42: 150000 | F42: 100000 | G42: 80000 | H42: =CHOOSE(Control!$C$5,E42,F42,G42) | I42: A | J42: placeholder — pending Stage 1 research
A43: TRANS_KG | B43: Operating costs | C43: Transport of fruit to buyers | D43: RWF per kg | E43: 80 | F43: 60 | G43: 40 | H43: =CHOOSE(Control!$C$5,E43,F43,G43) | I43: U | J43: placeholder — pending Stage 1 research | K43: Depends on the unconfirmed location
A44: TRANS_HD | B44: Operating costs | C44: Transport of livestock to buyers | D44: RWF per head | E44: 3000 | F44: 2000 | G44: 1500 | H44: =CHOOSE(Control!$C$5,E44,F44,G44) | I44: U | J44: placeholder — pending Stage 1 research | K44: Depends on the unconfirmed location
A45: PACK | B45: Operating costs | C45: Packaging | D45: RWF per kg fruit | E45: 40 | F45: 30 | G45: 25 | H45: =CHOOSE(Control!$C$5,E45,F45,G45) | I45: A | J45: placeholder — pending Stage 1 research
A46: COMMS | B46: Operating costs | C46: Communications and software | D46: RWF per month | E46: 40000 | F46: 30000 | G46: 25000 | H46: =CHOOSE(Control!$C$5,E46,F46,G46) | I46: A | J46: placeholder — pending Stage 1 research
A47: UTIL | B47: Operating costs | C47: Utilities and fuel | D47: RWF per month | E47: 40000 | F47: 30000 | G47: 20000 | H47: =CHOOSE(Control!$C$5,E47,F47,G47) | I47: A | J47: placeholder — pending Stage 1 research
A48: ADMIN | B48: Operating costs | C48: Administration and accounting | D48: RWF per month | E48: 60000 | F48: 40000 | G48: 30000 | H48: =CHOOSE(Control!$C$5,E48,F48,G48) | I48: A | J48: placeholder — pending Stage 1 research
A49: INS | B49: Operating costs | C49: Livestock insurance premium | D49: share of herd value per yr | E49: 0.06 | F49: 0.05 | G49: 0.04 | H49: =CHOOSE(Control!$C$5,E49,F49,G49) | I49: U | J49: placeholder — pending Stage 1 research | K49: Check the national agriculture insurance scheme
A50: LANDFEE | B50: Operating costs | C50: Land fees and taxes | D50: RWF per yr | E50: 200000 | F50: 120000 | G50: 80000 | H50: =CHOOSE(Control!$C$5,E50,F50,G50) | I50: U | J50: placeholder — pending Stage 1 research | K50: Depends on the title
B51: Feed
A52: PAST_Y | B52: Feed | C52: Pasture yield | D52: t DM per ha per yr | E52: 6 | F52: 9 | G52: 12 | H52: =CHOOSE(Control!$C$5,E52,F52,G52) | I52: A | J52: placeholder — pending Stage 1 research
A53: FOD_Y | B53: Feed | C53: Fodder bank yield (cut-and-carry) | D53: t DM per ha per yr | E53: 12 | F53: 18 | G53: 24 | H53: =CHOOSE(Control!$C$5,E53,F53,G53) | I53: A | J53: placeholder — pending Stage 1 research
A54: GRAZE | B54: Feed | C54: Grazing utilisation | D54: share | E54: 0.5 | F54: 0.6 | G54: 0.65 | H54: =CHOOSE(Control!$C$5,E54,F54,G54) | I54: A | J54: placeholder — pending Stage 1 research
A55: CUT | B55: Feed | C55: Cut-and-carry utilisation | D55: share | E55: 0.7 | F55: 0.8 | G55: 0.85 | H55: =CHOOSE(Control!$C$5,E55,F55,G55) | I55: A | J55: placeholder — pending Stage 1 research
A56: CONS_EFF | B56: Feed | C56: Hay/silage conservation efficiency | D56: share | E56: 0.6 | F56: 0.7 | G56: 0.8 | H56: =CHOOSE(Control!$C$5,E56,F56,G56) | I56: A | J56: placeholder — pending Stage 1 research
A57: CONS_COST | B57: Feed | C57: Conservation cost | D57: RWF per kg DM | E57: 30 | F57: 20 | G57: 15 | H57: =CHOOSE(Control!$C$5,E57,F57,G57) | I57: A | J57: placeholder — pending Stage 1 research
A58: FEED_COST | B58: Feed | C58: Purchased feed | D58: RWF per kg DM | E58: 300 | F58: 220 | G58: 180 | H58: =CHOOSE(Control!$C$5,E58,F58,G58) | I58: A | J58: placeholder — pending Stage 1 research
A59: READY | B59: Feed | C59: Months from planting to first forage | D59: months | E59: 6 | F59: 5 | G59: 4 | H59: =CHOOSE(Control!$C$5,E59,F59,G59) | I59: A | J59: placeholder — pending Stage 1 research
B60: Livestock: Goats
A61: GT_PART | B61: Livestock: Goats | C61: Births (parturitions) per breeding female | D61: per yr | E61: 1.1 | F61: 1.3 | G61: 1.5 | H61: =CHOOSE(Control!$C$5,E61,F61,G61) | I61: A | J61: placeholder — pending Stage 1 research
B62: Livestock: Sheep
A63: SH_PART | B63: Livestock: Sheep | C63: Births (parturitions) per breeding female | D63: per yr | E63: 0.9 | F63: 1.1 | G63: 1.3 | H63: =CHOOSE(Control!$C$5,E63,F63,G63) | I63: A | J63: placeholder — pending Stage 1 research
B64: Livestock: Goats
A65: GT_LIT | B65: Livestock: Goats | C65: Litter size | D65: young per birth | E65: 1.3 | F65: 1.5 | G65: 1.7 | H65: =CHOOSE(Control!$C$5,E65,F65,G65) | I65: A | J65: placeholder — pending Stage 1 research
B66: Livestock: Sheep
A67: SH_LIT | B67: Livestock: Sheep | C67: Litter size | D67: young per birth | E67: 1.1 | F67: 1.2 | G67: 1.4 | H67: =CHOOSE(Control!$C$5,E67,F67,G67) | I67: A | J67: placeholder — pending Stage 1 research
B68: Livestock: Goats
A69: GT_YMORT | B69: Livestock: Goats | C69: Young mortality to weaning | D69: share | E69: 0.25 | F69: 0.15 | G69: 0.1 | H69: =CHOOSE(Control!$C$5,E69,F69,G69) | I69: A | J69: placeholder — pending Stage 1 research
B70: Livestock: Sheep
A71: SH_YMORT | B71: Livestock: Sheep | C71: Young mortality to weaning | D71: share | E71: 0.25 | F71: 0.15 | G71: 0.1 | H71: =CHOOSE(Control!$C$5,E71,F71,G71) | I71: A | J71: placeholder — pending Stage 1 research
B72: Livestock: Goats
A73: GT_AMORT | B73: Livestock: Goats | C73: Adult mortality | D73: share per yr | E73: 0.1 | F73: 0.06 | G73: 0.04 | H73: =CHOOSE(Control!$C$5,E73,F73,G73) | I73: A | J73: placeholder — pending Stage 1 research
B74: Livestock: Sheep
A75: SH_AMORT | B75: Livestock: Sheep | C75: Adult mortality | D75: share per yr | E75: 0.1 | F75: 0.06 | G75: 0.04 | H75: =CHOOSE(Control!$C$5,E75,F75,G75) | I75: A | J75: placeholder — pending Stage 1 research
B76: Livestock: Goats
A77: GT_CULL | B77: Livestock: Goats | C77: Adult cull rate | D77: share per yr | E77: 0.15 | F77: 0.15 | G77: 0.15 | H77: =CHOOSE(Control!$C$5,E77,F77,G77) | I77: A | J77: placeholder — pending Stage 1 research
B78: Livestock: Sheep
A79: SH_CULL | B79: Livestock: Sheep | C79: Adult cull rate | D79: share per yr | E79: 0.15 | F79: 0.15 | G79: 0.15 | H79: =CHOOSE(Control!$C$5,E79,F79,G79) | I79: A | J79: placeholder — pending Stage 1 research
B80: Livestock: Goats
A81: GT_SALEWT | B81: Livestock: Goats | C81: Live weight at sale (9 months) | D81: kg | E81: 20 | F81: 24 | G81: 28 | H81: =CHOOSE(Control!$C$5,E81,F81,G81) | I81: A | J81: placeholder — pending Stage 1 research
B82: Livestock: Sheep
A83: SH_SALEWT | B83: Livestock: Sheep | C83: Live weight at sale (9 months) | D83: kg | E83: 22 | F83: 26 | G83: 30 | H83: =CHOOSE(Control!$C$5,E83,F83,G83) | I83: A | J83: placeholder — pending Stage 1 research
B84: Livestock: Goats
A85: GT_ADULTWT | B85: Livestock: Goats | C85: Adult live weight (culls) | D85: kg | E85: 32 | F85: 35 | G85: 38 | H85: =CHOOSE(Control!$C$5,E85,F85,G85) | I85: A | J85: placeholder — pending Stage 1 research
B86: Livestock: Sheep
A87: SH_ADULTWT | B87: Livestock: Sheep | C87: Adult live weight (culls) | D87: kg | E87: 30 | F87: 33 | G87: 36 | H87: =CHOOSE(Control!$C$5,E87,F87,G87) | I87: A | J87: placeholder — pending Stage 1 research
B88: Livestock: Goats
A89: GT_PRICE | B89: Livestock: Goats | C89: Sale price, live weight | D89: RWF per kg | E89: 3000 | F89: 3500 | G89: 4000 | H89: =CHOOSE(Control!$C$5,E89,F89,G89) | I89: A | J89: placeholder — pending Stage 1 research
B90: Livestock: Sheep
A91: SH_PRICE | B91: Livestock: Sheep | C91: Sale price, live weight | D91: RWF per kg | E91: 2800 | F91: 3200 | G91: 3600 | H91: =CHOOSE(Control!$C$5,E91,F91,G91) | I91: A | J91: placeholder — pending Stage 1 research
B92: Livestock: Goats
A93: GT_FPRICE | B93: Livestock: Goats | C93: Breeding female purchase price | D93: RWF per head | E93: 60000 | F93: 50000 | G93: 45000 | H93: =CHOOSE(Control!$C$5,E93,F93,G93) | I93: A | J93: placeholder — pending Stage 1 research
B94: Livestock: Sheep
A95: SH_FPRICE | B95: Livestock: Sheep | C95: Breeding female purchase price | D95: RWF per head | E95: 55000 | F95: 45000 | G95: 40000 | H95: =CHOOSE(Control!$C$5,E95,F95,G95) | I95: A | J95: placeholder — pending Stage 1 research
B96: Livestock: Goats
A97: GT_MPRICE | B97: Livestock: Goats | C97: Breeding male purchase price | D97: RWF per head | E97: 250000 | F97: 200000 | G97: 150000 | H97: =CHOOSE(Control!$C$5,E97,F97,G97) | I97: A | J97: placeholder — pending Stage 1 research
B98: Livestock: Sheep
A99: SH_MPRICE | B99: Livestock: Sheep | C99: Breeding male purchase price | D99: RWF per head | E99: 200000 | F99: 150000 | G99: 120000 | H99: =CHOOSE(Control!$C$5,E99,F99,G99) | I99: A | J99: placeholder — pending Stage 1 research
B100: Livestock: Goats
A101: GT_BPREM | B101: Livestock: Goats | C101: Price premium for breeding-stock sales | D101: share | E101: 0.2 | F101: 0.3 | G101: 0.4 | H101: =CHOOSE(Control!$C$5,E101,F101,G101) | I101: A | J101: placeholder — pending Stage 1 research
...

Sheet Models
A1: Models
A2: What defines each farm model. Selected = the column for the model chosen on Control.
A4: ID | B4: Group | C4: Parameter | D4: Unit | E4: M1 | F4: M2 | G4: M3 | H4: Selected | I4: Label | J4: Notes
B5: Land use (share of total area)
A6: Z01 | B6: Land use (share of total area) | C6: Z0+Z1 base, store, nursery | D6: share | E6: 0.05 | F6: 0.05 | G6: 0.07 | H6: =CHOOSE(Control!$C$6,E6,F6,G6) | I6: A | J6: See zoning-concept.md
A7: Z2 | B7: Land use (share of total area) | C7: Z2 orchard | D7: share | E7: 0.25 | F7: 0.35 | G7: 0.38 | H7: =CHOOSE(Control!$C$6,E7,F7,G7) | I7: A
A8: Z3 | B8: Land use (share of total area) | C8: Z3 paddocks and fodder bank | D8: share | E8: 0.5 | F8: 0.4 | G8: 0.35 | H8: =CHOOSE(Control!$C$6,E8,F8,G8) | I8: A
A9: Z4 | B9: Land use (share of total area) | C9: Z4 boundary and shelter trees | D9: share | E9: 0.1 | F9: 0.1 | G9: 0.1 | H9: =CHOOSE(Control!$C$6,E9,F9,G9) | I9: A
A10: Z5 | B10: Land use (share of total area) | C10: Z5 lake/wetland buffer, steep, conservation | D10: share | E10: 0.1 | F10: 0.1 | G10: 0.1 | H10: =CHOOSE(Control!$C$6,E10,F10,G10) | I10: U | J10: Depends on shoreline and survey
A11: FODDER | B11: Land use (share of total area) | C11: Fodder bank share of Z3 | D11: share | E11: 0.3 | F11: 0.3 | G11: 0.35 | H11: =CHOOSE(Control!$C$6,E11,F11,G11) | I11: A
B12: Orchard mix (share of Z2)
A13: OR_AVO | B13: Orchard mix (share of Z2) | C13: Avocado | D13: share | E13: 1 | F13: 0.5 | G13: 0.4 | H13: =CHOOSE(Control!$C$6,E13,F13,G13) | I13: A | J13: Pending site suitability
A14: OR_MAN | B14: Orchard mix (share of Z2) | C14: Mango | D14: share | E14: 0 | F14: 0 | G14: 0.1 | H14: =CHOOSE(Control!$C$6,E14,F14,G14) | I14: A
A15: OR_PAS | B15: Orchard mix (share of Z2) | C15: Passion fruit | D15: share | E15: 0 | F15: 0.3 | G15: 0.2 | H15: =CHOOSE(Control!$C$6,E15,F15,G15) | I15: A
A16: OR_PAP | B16: Orchard mix (share of Z2) | C16: Papaya | D16: share | E16: 0 | F16: 0.2 | G16: 0.1 | H16: =CHOOSE(Control!$C$6,E16,F16,G16) | I16: A
A17: OR_TTO | B17: Orchard mix (share of Z2) | C17: Tree tomato | D17: share | E17: 0 | F17: 0 | G17: 0.1 | H17: =CHOOSE(Control!$C$6,E17,F17,G17) | I17: A
A18: OR_CIT | B18: Orchard mix (share of Z2) | C18: Citrus | D18: share | E18: 0 | F18: 0 | G18: 0.1 | H18: =CHOOSE(Control!$C$6,E18,F18,G18) | I18: A
A19: OR_MAC | B19: Orchard mix (share of Z2) | C19: Macadamia | D19: share | E19: 0 | F19: 0 | G19: 0 | H19: =CHOOSE(Control!$C$6,E19,F19,G19) | I19: A
B20: Livestock introduction
A21: GT_T1M | B21: Livestock introduction | C21: Goats tranche 1: month | D21: month # | E21: 9 | F21: 9 | G21: 9 | H21: =CHOOSE(Control!$C$6,E21,F21,G21) | I21: A | J21: After fencing, water, house and forage
A22: GT_T1F | B22: Livestock introduction | C22: Goats tranche 1: breeding females | D22: head | E22: 15 | F22: 20 | G22: 25 | H22: =CHOOSE(Control!$C$6,E22,F22,G22) | I22: A
A23: GT_T1MALE | B23: Livestock introduction | C23: Goats tranche 1: breeding males | D23: head | E23: 1 | F23: 1 | G23: 1 | H23: =CHOOSE(Control!$C$6,E23,F23,G23) | I23: A
A24: GT_T2M | B24: Livestock introduction | C24: Goats tranche 2: month | D24: month # | E24: 18 | F24: 18 | G24: 18 | H24: =CHOOSE(Control!$C$6,E24,F24,G24) | I24: A | J24: After quarantine and first results
A25: GT_T2F | B25: Livestock introduction | C25: Goats tranche 2: breeding females | D25: head | E25: 10 | F25: 15 | G25: 20 | H25: =CHOOSE(Control!$C$6,E25,F25,G25) | I25: A
A26: GT_T2MALE | B26: Livestock introduction | C26: Goats tranche 2: breeding males | D26: head | E26: 0 | F26: 1 | G26: 1 | H26: =CHOOSE(Control!$C$6,E26,F26,G26) | I26: A
A27: GT_TARGET | B27: Livestock introduction | C27: Goats: target breeding females | D27: head | E27: 40 | F27: 50 | G27: 60 | H27: =CHOOSE(Control!$C$6,E27,F27,G27) | I27: A | J27: Check against the feed balance
A28: SH_T1M | B28: Livestock introduction | C28: Sheep tranche 1: month | D28: month # | E28: 0 | F28: 12 | G28: 12 | H28: =CHOOSE(Control!$C$6,E28,F28,G28) | I28: A | J28: 0 = no sheep
A29: SH_T1F | B29: Livestock introduction | C29: Sheep tranche 1: breeding females | D29: head | E29: 0 | F29: 10 | G29: 15 | H29: =CHOOSE(Control!$C$6,E29,F29,G29) | I29: A
A30: SH_T1MALE | B30: Livestock introduction | C30: Sheep tranche 1: breeding males | D30: head | E30: 0 | F30: 1 | G30: 1 | H30: =CHOOSE(Control!$C$6,E30,F30,G30) | I30: A
A31: SH_T2M | B31: Livestock introduction | C31: Sheep tranche 2: month | D31: month # | E31: 0 | F31: 0 | G31: 24 | H31: =CHOOSE(Control!$C$6,E31,F31,G31) | I31: A | J31: 0 = none
A32: SH_T2F | B32: Livestock introduction | C32: Sheep tranche 2: breeding females | D32: head | E32: 0 | F32: 0 | G32: 10 | H32: =CHOOSE(Control!$C$6,E32,F32,G32) | I32: A
A33: SH_T2MALE | B33: Livestock introduction | C33: Sheep tranche 2: breeding males | D33: head | E33: 0 | F33: 0 | G33: 0 | H33: =CHOOSE(Control!$C$6,E33,F33,G33) | I33: A
A34: SH_TARGET | B34: Livestock introduction | C34: Sheep: target breeding females | D34: head | E34: 0 | F34: 20 | G34: 30 | H34: =CHOOSE(Control!$C$6,E34,F34,G34) | I34: A
B35: Livestock management
A36: RETAIN | B36: Livestock management | C36: Share of female young kept as replacements (while below target) | D36: share | E36: 0.6 | F36: 0.5 | G36: 0.5 | H36: =CHOOSE(Control!$C$6,E36,F36,G36) | I36: A
A37: BSHARE | B37: Livestock management | C37: Share of young stock sold as breeding stock | D37: share | E37: 0 | F37: 0.1 | G37: 0.2 | H37: =CHOOSE(Control!$C$6,E37,F37,G37) | I37: A | J37: Needs records and genetics
A38: CONSERVE | B38: Livestock management | C38: Share of surplus forage conserved (hay/silage) | D38: share | E38: 0.3 | F38: 0.5 | G38: 0.7 | H38: =CHOOSE(Control!$C$6,E38,F38,G38) | I38: A
B39: Operations
A40: WORKERS | B40: Operations | C40: Permanent workers | D40: people | E40: 1 | F40: 2 | G40: 3 | H40: =CHOOSE(Control!$C$6,E40,F40,G40) | I40: A
B41: Capital items
A42: SOIL_N | B42: Capital items | C42: Soil samples | D42: samples | E42: 6 | F42: 8 | G42: 10 | H42: =CHOOSE(Control!$C$6,E42,F42,G42) | I42: A | J42: See soil-water-testing-plan.md
A43: WATER_N | B43: Capital items | C43: Water samples | D43: samples | E43: 2 | F43: 3 | G43: 4 | H43: =CHOOSE(Control!$C$6,E43,F43,G43) | I43: A
A44: IFENCE_M | B44: Capital items | C44: Internal paddock fence | D44: m per ha of Z3 | E44: 250 | F44: 300 | G44: 350 | H44: =CHOOSE(Control!$C$6,E44,F44,G44) | I44: A
A45: GATES | B45: Capital items | C45: Gates | D45: count | E45: 2 | F45: 3 | G45: 4 | H45: =CHOOSE(Control!$C$6,E45,F45,G45) | I45: A
A46: STORAGE | B46: Capital items | C46: Water storage | D46: m3 | E46: 10 | F46: 20 | G46: 40 | H46: =CHOOSE(Control!$C$6,E46,F46,G46) | I46: A
A47: BOREHOLE | B47: Capital items | C47: Borehole (1 = yes) | D47: flag | E47: 0 | F47: 0 | G47: 1 | H47: =CHOOSE(Control!$C$6,E47,F47,G47) | I47: U | J47: Only if legal and viable
A48: SOLARPUMP | B48: Capital items | C48: Solar pump (1 = yes) | D48: flag | E48: 0 | F48: 1 | G48: 1 | H48: =CHOOSE(Control!$C$6,E48,F48,G48) | I48: A
A49: DRIPON | B49: Capital items | C49: Drip on orchard (1 = yes) | D49: flag | E49: 0 | F49: 1 | G49: 1 | H49: =CHOOSE(Control!$C$6,E49,F49,G49) | I49: A
A50: PV_KWP | B50: Capital items | C50: Solar PV size | D50: kWp | E50: 0.3 | F50: 0.6 | G50: 2 | H50: =CHOOSE(Control!$C$6,E50,F50,G50) | I50: A | J50: Lights, sensors, comms
A51: SENSORS | B51: Capital items | C51: Sensors and controllers | D51: RWF lump | E51: 150000 | F51: 600000 | G51: 3000000 | H51: =CHOOSE(Control!$C$6,E51,F51,G51) | I51: A | J51: M1/M2 founder-built; M3 industrial-grade
A52: CONNECT | B52: Capital items | C52: Connectivity (router, gateway) | D52: RWF lump | E52: 80000 | F52: 150000 | G52: 600000 | H52: =CHOOSE(Control!$C$6,E52,F52,G52) | I52: A
A53: SOFTWARE | B53: Capital items | C53: Software and devices | D53: RWF lump | E53: 0 | F53: 0 | G53: 1500000 | H53: =CHOOSE(Control!$C$6,E53,F53,G53) | I53: A | J53: Founder builds; hosting in opex
A54: SECURITY | B54: Capital items | C54: Security (lights, cameras) | D54: RWF lump | E54: 200000 | F54: 500000 | G54: 1500000 | H54: =CHOOSE(Control!$C$6,E54,F54,G54) | I54: A
A55: NURSERY | B55: Capital items | C55: Nursery (shade net, tools) | D55: RWF lump | E55: 0 | F55: 300000 | G55: 800000 | H55: =CHOOSE(Control!$C$6,E55,F55,G55) | I55: A
A56: COOLSTORE | B56: Capital items | C56: Cool store / packhouse | D56: RWF lump | E56: 0 | F56: 0 | G56: 5000000 | H56: =CHOOSE(Control!$C$6,E56,F56,G56) | I56: A
A57: FEEDSTORE | B57: Capital items | C57: Feed store | D57: RWF lump | E57: 500000 | F57: 800000 | G57: 1500000 | H57: =CHOOSE(Control!$C$6,E57,F57,G57) | I57: A
A58: TOOLS | B58: Capital items | C58: Tools and small equipment | D58: RWF lump | E58: 600000 | F58: 900000 | G58: 1500000 | H58: =CHOOSE(Control!$C$6,E58,F58,G58) | I58: A

Sheet Curves
A1: Curves
A2: Yield per plant by farm year, harvest seasonality by calendar month, pasture growth by month.
A4: ID | B4: Crop | C4: Unit | D4: Y1 | E4: Y2 | F4: Y3 | G4: Y4 | H4: Y5 | I4: Y6 | J4: Y7 | K4: Y8 | L4: Y9 | M4: Y10 | N4: Label | O4: Source / note
A5: AVO_CURVE | B5: Avocado (grafted) | C5: kg per plant | D5: 0 | E5: 0 | F5: 5 | G5: 15 | H5: 30 | I5: 50 | J5: 70 | K5: 90 | L5: 100 | M5: 110 | N5: A | O5: placeholder — pending Stage 1 research. Planted in year 1; short-cycle crops repeat their first years.
A6: MAN_CURVE | B6: Mango (grafted) | C6: kg per plant | D6: 0 | E6: 0 | F6: 5 | G6: 15 | H6: 30 | I6: 45 | J6: 60 | K6: 75 | L6: 90 | M6: 100 | N6: A | O6: placeholder — pending Stage 1 research. Planted in year 1; short-cycle crops repeat their first years.
A7: PAS_CURVE | B7: Passion fruit | C7: kg per plant | D7: 2 | E7: 10 | F7: 6 | G7: 0 | H7: 0 | I7: 0 | J7: 0 | K7: 0 | L7: 0 | M7: 0 | N7: A | O7: placeholder — pending Stage 1 research. Planted in year 1; short-cycle crops repeat their first years.
A8: PAP_CURVE | B8: Papaya | C8: kg per plant | D8: 5 | E8: 30 | F8: 20 | G8: 0 | H8: 0 | I8: 0 | J8: 0 | K8: 0 | L8: 0 | M8: 0 | N8: A | O8: placeholder — pending Stage 1 research. Planted in year 1; short-cycle crops repeat their first years.
A9: TTO_CURVE | B9: Tree tomato | C9: kg per plant | D9: 0 | E9: 10 | F9: 15 | G9: 10 | H9: 0 | I9: 0 | J9: 0 | K9: 0 | L9: 0 | M9: 0 | N9: A | O9: placeholder — pending Stage 1 research. Planted in year 1; short-cycle crops repeat their first years.
A10: CIT_CURVE | B10: Citrus | C10: kg per plant | D10: 0 | E10: 0 | F10: 5 | G10: 15 | H10: 30 | I10: 45 | J10: 60 | K10: 70 | L10: 80 | M10: 90 | N10: A | O10: placeholder — pending Stage 1 research. Planted in year 1; short-cycle crops repeat their first years.
A11: MAC_CURVE | B11: Macadamia (nut in shell) | C11: kg per plant | D11: 0 | E11: 0 | F11: 0 | G11: 1 | H11: 3 | I11: 6 | J11: 9 | K11: 12 | L11: 15 | M11: 18 | N11: A | O11: placeholder — pending Stage 1 research. Planted in year 1; short-cycle crops repeat their first years.
A14: ID | B14: Crop | C14: Unit | D14: Jan | E14: Feb | F14: Mar | G14: Apr | H14: May | I14: Jun | J14: Jul | K14: Aug | L14: Sep | M14: Oct | N14: Nov | O14: Dec | P14: Sum (must be 1) | Q14: Label | R14: Note
A15: AVO_SEASON | B15: Avocado (grafted) | C15: share of year | D15: 0.083333 | E15: 0.083333 | F15: 0.083333 | G15: 0.083333 | H15: 0.083333 | I15: 0.083333 | J15: 0.083333 | K15: 0.083333 | L15: 0.083333 | M15: 0.083333 | N15: 0.083333 | O15: 0.083337 | P15: =SUM(D15:O15) | Q15: A | R15: Uniform until the Rwandan harvest calendar is sourced
A16: MAN_SEASON | B16: Mango (grafted) | C16: share of year | D16: 0.083333 | E16: 0.083333 | F16: 0.083333 | G16: 0.083333 | H16: 0.083333 | I16: 0.083333 | J16: 0.083333 | K16: 0.083333 | L16: 0.083333 | M16: 0.083333 | N16: 0.083333 | O16: 0.083337 | P16: =SUM(D16:O16) | Q16: A | R16: Uniform until the Rwandan harvest calendar is sourced
A17: PAS_SEASON | B17: Passion fruit | C17: share of year | D17: 0.083333 | E17: 0.083333 | F17: 0.083333 | G17: 0.083333 | H17: 0.083333 | I17: 0.083333 | J17: 0.083333 | K17: 0.083333 | L17: 0.083333 | M17: 0.083333 | N17: 0.083333 | O17: 0.083337 | P17: =SUM(D17:O17) | Q17: A | R17: Uniform until the Rwandan harvest calendar is sourced
A18: PAP_SEASON | B18: Papaya | C18: share of year | D18: 0.083333 | E18: 0.083333 | F18: 0.083333 | G18: 0.083333 | H18: 0.083333 | I18: 0.083333 | J18: 0.083333 | K18: 0.083333 | L18: 0.083333 | M18: 0.083333 | N18: 0.083333 | O18: 0.083337 | P18: =SUM(D18:O18) | Q18: A | R18: Uniform until the Rwandan harvest calendar is sourced
A19: TTO_SEASON | B19: Tree tomato | C19: share of year | D19: 0.083333 | E19: 0.083333 | F19: 0.083333 | G19: 0.083333 | H19: 0.083333 | I19: 0.083333 | J19: 0.083333 | K19: 0.083333 | L19: 0.083333 | M19: 0.083333 | N19: 0.083333 | O19: 0.083337 | P19: =SUM(D19:O19) | Q19: A | R19: Uniform until the Rwandan harvest calendar is sourced
A20: CIT_SEASON | B20: Citrus | C20: share of year | D20: 0.083333 | E20: 0.083333 | F20: 0.083333 | G20: 0.083333 | H20: 0.083333 | I20: 0.083333 | J20: 0.083333 | K20: 0.083333 | L20: 0.083333 | M20: 0.083333 | N20: 0.083333 | O20: 0.083337 | P20: =SUM(D20:O20) | Q20: A | R20: Uniform until the Rwandan harvest calendar is sourced
A21: MAC_SEASON | B21: Macadamia (nut in shell) | C21: share of year | D21: 0.083333 | E21: 0.083333 | F21: 0.083333 | G21: 0.083333 | H21: 0.083333 | I21: 0.083333 | J21: 0.083333 | K21: 0.083333 | L21: 0.083333 | M21: 0.083333 | N21: 0.083333 | O21: 0.083337 | P21: =SUM(D21:O21) | Q21: A | R21: Uniform until the Rwandan harvest calendar is sourced
A24: ID | B24: Series | C24: Unit | D24: Jan | E24: Feb | F24: Mar | G24: Apr | H24: May | I24: Jun | J24: Jul | K24: Aug | L24: Sep | M24: Oct | N24: Nov | O24: Dec | P24: Average (must be 1) | Q24: Label | R24: Note
A25: PGROWTH | B25: Pasture growth factor | C25: x average | D25: 0.9 | E25: 0.8 | F25: 1.3 | G25: 1.5 | H25: 1.4 | I25: 0.6 | J25: 0.4 | K25: 0.4 | L25: 0.8 | M25: 1.2 | N25: 1.4 | O25: 1.3 | P25: =AVERAGE(D25:O25) | Q25: A | R25: Shape follows the bimodal rains; calibrate to zone rainfall

Sheet Sensitivity
A1: Sensitivity
A2: Multipliers that flex the drivers that matter most. Leave at 1 (delay 0) for the plain scenario.
A4: Key | B4: Driver | C4: Setting | D4: How it is applied
A5: S_PRICE_FRUIT | B5: Fruit prices | C5: 1 | D5: Multiplies every fruit farm-gate price
A6: S_PRICE_LIVE | B6: Livestock prices | C6: 1 | D6: Multiplies the live-weight price of goats and sheep
A7: S_YIELD | B7: Fruit yields | C7: 1 | D7: Multiplies every yield curve
A8: S_MORT | B8: Livestock mortality | C8: 1 | D8: Multiplies young and adult mortality
A9: S_FEED | B9: Purchased feed cost | C9: 1 | D9: Multiplies the purchased-feed price
A10: S_LABOR | B10: Labour cost | C10: 1 | D10: Multiplies permanent and casual wages
A11: S_CAPEX | B11: Capital costs | C11: 1 | D11: Multiplies every capital item, seedling and animal purchase
A12: S_TRANS | B12: Transport cost | C12: 1 | D12: Multiplies transport per kg and per head
A13: S_DELAY | B13: Delay to tree maturity | C13: 0 | D13: Years added before perennial trees start their yield curve
B16: Results log (Stage 3): set one driver at a time to 0.8 and 1.2, record the outputs, reset to 1.
B17: Driver | C17: Setting | D17: NPV (RWF) | E17: Funding gap (RWF) | F17: Payback year | G17: Date / note

Sheet Land
A1: Land
A2: Areas by zone and crop for the selected model.
A3: Key | B3: Item | C3: Value | D3: Unit
A4: L_AREA | B4: Total area | C4: =Control!$C$7 | D4: ha
A5: L_PERIM | B5: Perimeter of a square of that area | C5: =4*SQRT(C4*10000) | D5: m
A6: L_BOUND | B6: Boundary length with shape factor | C6: =C5*Assumptions!$H$184 | D6: m
A7: L_Z01 | B7: Z0+Z1 base, store, nursery | C7: =C4*Models!$H$6 | D7: ha
A8: L_Z2 | B8: Z2 orchard | C8: =C4*Models!$H$7 | D8: ha
A9: L_Z3 | B9: Z3 paddocks and fodder bank | C9: =C4*Models!$H$8 | D9: ha
A10: L_Z4 | B10: Z4 boundary and shelter trees | C10: =C4*Models!$H$9 | D10: ha
A11: L_Z5 | B11: Z5 buffer and conservation | C11: =C4*Models!$H$10 | D11: ha
A12: L_PADDOCK | B12: Paddocks (grazed) | C12: =C9*(1-Models!$H$11) | D12: ha
A13: L_FODDER | B13: Fodder bank (cut-and-carry) | C13: =C9*Models!$H$11 | D13: ha
B15: Orchard by crop
A16: L_AVO | B16: Avocado (grafted) | C16: =Land!$C$8*Models!$H$13 | D16: ha
A17: L_MAN | B17: Mango (grafted) | C17: =Land!$C$8*Models!$H$14 | D17: ha
A18: L_PAS | B18: Passion fruit | C18: =Land!$C$8*Models!$H$15 | D18: ha
A19: L_PAP | B19: Papaya | C19: =Land!$C$8*Models!$H$16 | D19: ha
A20: L_TTO | B20: Tree tomato | C20: =Land!$C$8*Models!$H$17 | D20: ha
A21: L_CIT | B21: Citrus | C21: =Land!$C$8*Models!$H$18 | D21: ha
A22: L_MAC | B22: Macadamia (nut in shell) | C22: =Land!$C$8*Models!$H$19 | D22: ha
B24: Checks
B25: Land shares sum to 100% | C25: =Models!$H$6+Models!$H$7+Models!$H$8+Models!$H$9+Models!$H$10
B26: Orchard mix sums to 100% | C26: =Models!$H$13+Models!$H$14+Models!$H$15+Models!$H$16+Models!$H$17+Models!$H$18+Models!$H$19

Sheet Trees
A1: Trees
A2: Annual orchard and boundary-tree engine for the selected model and scenario.
B3: Farm year | D3: 1 | E3: 2 | F3: 3 | G3: 4 | H3: 5 | I3: 6 | J3: 7 | K3: 8 | L3: 9 | M3: 10
B5: Avocado (grafted)
A6: AVO_AREA | B6: Area | C6: =Land!$C$16
A7: AVO_PLANTS | B7: Plants planted | C7: =ROUND(C6*Assumptions!$H$121,0)
A8: AVO_STAND | B8: Final stand | C8: =C7*Assumptions!$H$122
A9: AVO_EST | B9: Establishment cost | C9: =C7*(Assumptions!$H$123+Assumptions!$H$124)*Sensitivity!$C$11
A10: AVO_GAP | B10: Gap-filling cost (year 2) | C10: =C7*(1-Assumptions!$H$122)*Assumptions!$H$123*Sensitivity!$C$11
A11: AVO_AGE | B11: Age in production cycle | C11: years | D11: =IF(Assumptions!$H$128=0,D$3-Sensitivity!$C$13,MOD(D$3-1,MAX(1,Assumptions!$H$128))+1) | E11: =IF(Assumptions!$H$128=0,E$3-Sensitivity!$C$13,MOD(E$3-1,MAX(1,Assumptions!$H$128))+1) | F11: =IF(Assumptions!$H$128=0,F$3-Sensitivity!$C$13,MOD(F$3-1,MAX(1,Assumptions!$H$128))+1) | G11: =IF(Assumptions!$H$128=0,G$3-Sensitivity!$C$13,MOD(G$3-1,MAX(1,Assumptions!$H$128))+1) | H11: =IF(Assumptions!$H$128=0,H$3-Sensitivity!$C$13,MOD(H$3-1,MAX(1,Assumptions!$H$128))+1) | I11: =IF(Assumptions!$H$128=0,I$3-Sensitivity!$C$13,MOD(I$3-1,MAX(1,Assumptions!$H$128))+1) | J11: =IF(Assumptions!$H$128=0,J$3-Sensitivity!$C$13,MOD(J$3-1,MAX(1,Assumptions!$H$128))+1) | K11: =IF(Assumptions!$H$128=0,K$3-Sensitivity!$C$13,MOD(K$3-1,MAX(1,Assumptions!$H$128))+1) | ... M11: =IF(Assumptions!$H$128=0,M$3-Sensitivity!$C$13,MOD(M$3-1,MAX(1,Assumptions!$H$128))+1)
A12: AVO_YLD | B12: Yield per plant | C12: kg | D12: =IF(D11>=1,INDEX(Curves!$D$5:$M$5,1,MIN(10,MAX(1,D11))),0)*Assumptions!$H$125*Sensitivity!$C$7 | E12: =IF(E11>=1,INDEX(Curves!$D$5:$M$5,1,MIN(10,MAX(1,E11))),0)*Assumptions!$H$125*Sensitivity!$C$7 | F12: =IF(F11>=1,INDEX(Curves!$D$5:$M$5,1,MIN(10,MAX(1,F11))),0)*Assumptions!$H$125*Sensitivity!$C$7 | G12: =IF(G11>=1,INDEX(Curves!$D$5:$M$5,1,MIN(10,MAX(1,G11))),0)*Assumptions!$H$125*Sensitivity!$C$7 | H12: =IF(H11>=1,INDEX(Curves!$D$5:$M$5,1,MIN(10,MAX(1,H11))),0)*Assumptions!$H$125*Sensitivity!$C$7 | I12: =IF(I11>=1,INDEX(Curves!$D$5:$M$5,1,MIN(10,MAX(1,I11))),0)*Assumptions!$H$125*Sensitivity!$C$7 | J12: =IF(J11>=1,INDEX(Curves!$D$5:$M$5,1,MIN(10,MAX(1,J11))),0)*Assumptions!$H$125*Sensitivity!$C$7 | K12: =IF(K11>=1,INDEX(Curves!$D$5:$M$5,1,MIN(10,MAX(1,K11))),0)*Assumptions!$H$125*Sensitivity!$C$7 | ... M12: =IF(M11>=1,INDEX(Curves!$D$5:$M$5,1,MIN(10,MAX(1,M11))),0)*Assumptions!$H$125*Sensitivity!$C$7
A13: AVO_PROD | B13: Marketable production | C13: kg | D13: =Trees!$C$8*D12*Assumptions!$H$126 | E13: =Trees!$C$8*E12*Assumptions!$H$126 | F13: =Trees!$C$8*F12*Assumptions!$H$126 | G13: =Trees!$C$8*G12*Assumptions!$H$126 | H13: =Trees!$C$8*H12*Assumptions!$H$126 | I13: =Trees!$C$8*I12*Assumptions!$H$126 | J13: =Trees!$C$8*J12*Assumptions!$H$126 | K13: =Trees!$C$8*K12*Assumptions!$H$126 | ... M13: =Trees!$C$8*M12*Assumptions!$H$126
A14: AVO_REV | B14: Sales | C14: RWF | D14: =D13*Assumptions!$H$127*Sensitivity!$C$5 | E14: =E13*Assumptions!$H$127*Sensitivity!$C$5 | F14: =F13*Assumptions!$H$127*Sensitivity!$C$5 | G14: =G13*Assumptions!$H$127*Sensitivity!$C$5 | H14: =H13*Assumptions!$H$127*Sensitivity!$C$5 | I14: =I13*Assumptions!$H$127*Sensitivity!$C$5 | J14: =J13*Assumptions!$H$127*Sensitivity!$C$5 | K14: =K13*Assumptions!$H$127*Sensitivity!$C$5 | ... M14: =M13*Assumptions!$H$127*Sensitivity!$C$5
A15: AVO_REPL | B15: Replanting (short-cycle crops) | C15: RWF | D15: =IF(AND(Assumptions!$H$128>0,D$3>1,MOD(D$3-1,MAX(1,Assumptions!$H$128))=0),Trees!$C$7*(Assumptions!$H$123+Assumptions!$H$124)*Sensitivity!$C$11,0) | E15: =IF(AND(Assumptions!$H$128>0,E$3>1,MOD(E$3-1,MAX(1,Assumptions!$H$128))=0),Trees!$C$7*(Assumptions!$H$123+Assumptions!$H$124)*Sensitivity!$C$11,0) | F15: =IF(AND(Assumptions!$H$128>0,F$3>1,MOD(F$3-1,MAX(1,Assumptions!$H$128))=0),Trees!$C$7*(Assumptions!$H$123+Assumptions!$H$124)*Sensitivity!$C$11,0) | G15: =IF(AND(Assumptions!$H$128>0,G$3>1,MOD(G$3-1,MAX(1,Assumptions!$H$128))=0),Trees!$C$7*(Assumptions!$H$123+Assumptions!$H$124)*Sensitivity!$C$11,0) | H15: =IF(AND(Assumptions!$H$128>0,H$3>1,MOD(H$3-1,MAX(1,Assumptions!$H$128))=0),Trees!$C$7*(Assumptions!$H$123+Assumptions!$H$124)*Sensitivity!$C$11,0) | I15: =IF(AND(Assumptions!$H$128>0,I$3>1,MOD(I$3-1,MAX(1,Assumptions!$H$128))=0),Trees!$C$7*(Assumptions!$H$123+Assumptions!$H$124)*Sensitivity!$C$11,0) | J15: =IF(AND(Assumptions!$H$128>0,J$3>1,MOD(J$3-1,MAX(1,Assumptions!$H$128))=0),Trees!$C$7*(Assumptions!$H$123+Assumptions!$H$124)*Sensitivity!$C$11,0) | K15: =IF(AND(Assumptions!$H$128>0,K$3>1,MOD(K$3-1,MAX(1,Assumptions!$H$128))=0),Trees!$C$7*(Assumptions!$H$123+Assumptions!$H$124)*Sensitivity!$C$11,0) | ... M15: =IF(AND(Assumptions!$H$128>0,M$3>1,MOD(M$3-1,MAX(1,Assumptions!$H$128))=0),Trees!$C$7*(Assumptions!$H$123+Assumptions!$H$124)*Sensitivity!$C$11,0)
B17: Mango (grafted)
A18: MAN_AREA | B18: Area | C18: =Land!$C$17
A19: MAN_PLANTS | B19: Plants planted | C19: =ROUND(C18*Assumptions!$H$130,0)
A20: MAN_STAND | B20: Final stand | C20: =C19*Assumptions!$H$131
A21: MAN_EST | B21: Establishment cost | C21: =C19*(Assumptions!$H$132+Assumptions!$H$133)*Sensitivity!$C$11
A22: MAN_GAP | B22: Gap-filling cost (year 2) | C22: =C19*(1-Assumptions!$H$131)*Assumptions!$H$132*Sensitivity!$C$11
A23: MAN_AGE | B23: Age in production cycle | C23: years | D23: =IF(Assumptions!$H$137=0,D$3-Sensitivity!$C$13,MOD(D$3-1,MAX(1,Assumptions!$H$137))+1) | E23: =IF(Assumptions!$H$137=0,E$3-Sensitivity!$C$13,MOD(E$3-1,MAX(1,Assumptions!$H$137))+1) | F23: =IF(Assumptions!$H$137=0,F$3-Sensitivity!$C$13,MOD(F$3-1,MAX(1,Assumptions!$H$137))+1) | G23: =IF(Assumptions!$H$137=0,G$3-Sensitivity!$C$13,MOD(G$3-1,MAX(1,Assumptions!$H$137))+1) | H23: =IF(Assumptions!$H$137=0,H$3-Sensitivity!$C$13,MOD(H$3-1,MAX(1,Assumptions!$H$137))+1) | I23: =IF(Assumptions!$H$137=0,I$3-Sensitivity!$C$13,MOD(I$3-1,MAX(1,Assumptions!$H$137))+1) | J23: =IF(Assumptions!$H$137=0,J$3-Sensitivity!$C$13,MOD(J$3-1,MAX(1,Assumptions!$H$137))+1) | K23: =IF(Assumptions!$H$137=0,K$3-Sensitivity!$C$13,MOD(K$3-1,MAX(1,Assumptions!$H$137))+1) | ... M23: =IF(Assumptions!$H$137=0,M$3-Sensitivity!$C$13,MOD(M$3-1,MAX(1,Assumptions!$H$137))+1)
A24: MAN_YLD | B24: Yield per plant | C24: kg | D24: =IF(D23>=1,INDEX(Curves!$D$6:$M$6,1,MIN(10,MAX(1,D23))),0)*Assumptions!$H$134*Sensitivity!$C$7 | E24: =IF(E23>=1,INDEX(Curves!$D$6:$M$6,1,MIN(10,MAX(1,E23))),0)*Assumptions!$H$134*Sensitivity!$C$7 | F24: =IF(F23>=1,INDEX(Curves!$D$6:$M$6,1,MIN(10,MAX(1,F23))),0)*Assumptions!$H$134*Sensitivity!$C$7 | G24: =IF(G23>=1,INDEX(Curves!$D$6:$M$6,1,MIN(10,MAX(1,G23))),0)*Assumptions!$H$134*Sensitivity!$C$7 | H24: =IF(H23>=1,INDEX(Curves!$D$6:$M$6,1,MIN(10,MAX(1,H23))),0)*Assumptions!$H$134*Sensitivity!$C$7 | I24: =IF(I23>=1,INDEX(Curves!$D$6:$M$6,1,MIN(10,MAX(1,I23))),0)*Assumptions!$H$134*Sensitivity!$C$7 | J24: =IF(J23>=1,INDEX(Curves!$D$6:$M$6,1,MIN(10,MAX(1,J23))),0)*Assumptions!$H$134*Sensitivity!$C$7 | K24: =IF(K23>=1,INDEX(Curves!$D$6:$M$6,1,MIN(10,MAX(1,K23))),0)*Assumptions!$H$134*Sensitivity!$C$7 | ... M24: =IF(M23>=1,INDEX(Curves!$D$6:$M$6,1,MIN(10,MAX(1,M23))),0)*Assumptions!$H$134*Sensitivity!$C$7
A25: MAN_PROD | B25: Marketable production | C25: kg | D25: =Trees!$C$20*D24*Assumptions!$H$135 | E25: =Trees!$C$20*E24*Assumptions!$H$135 | F25: =Trees!$C$20*F24*Assumptions!$H$135 | G25: =Trees!$C$20*G24*Assumptions!$H$135 | H25: =Trees!$C$20*H24*Assumptions!$H$135 | I25: =Trees!$C$20*I24*Assumptions!$H$135 | J25: =Trees!$C$20*J24*Assumptions!$H$135 | K25: =Trees!$C$20*K24*Assumptions!$H$135 | ... M25: =Trees!$C$20*M24*Assumptions!$H$135
A26: MAN_REV | B26: Sales | C26: RWF | D26: =D25*Assumptions!$H$136*Sensitivity!$C$5 | E26: =E25*Assumptions!$H$136*Sensitivity!$C$5 | F26: =F25*Assumptions!$H$136*Sensitivity!$C$5 | G26: =G25*Assumptions!$H$136*Sensitivity!$C$5 | H26: =H25*Assumptions!$H$136*Sensitivity!$C$5 | I26: =I25*Assumptions!$H$136*Sensitivity!$C$5 | J26: =J25*Assumptions!$H$136*Sensitivity!$C$5 | K26: =K25*Assumptions!$H$136*Sensitivity!$C$5 | ... M26: =M25*Assumptions!$H$136*Sensitivity!$C$5
A27: MAN_REPL | B27: Replanting (short-cycle crops) | C27: RWF | D27: =IF(AND(Assumptions!$H$137>0,D$3>1,MOD(D$3-1,MAX(1,Assumptions!$H$137))=0),Trees!$C$19*(Assumptions!$H$132+Assumptions!$H$133)*Sensitivity!$C$11,0) | E27: =IF(AND(Assumptions!$H$137>0,E$3>1,MOD(E$3-1,MAX(1,Assumptions!$H$137))=0),Trees!$C$19*(Assumptions!$H$132+Assumptions!$H$133)*Sensitivity!$C$11,0) | F27: =IF(AND(Assumptions!$H$137>0,F$3>1,MOD(F$3-1,MAX(1,Assumptions!$H$137))=0),Trees!$C$19*(Assumptions!$H$132+Assumptions!$H$133)*Sensitivity!$C$11,0) | G27: =IF(AND(Assumptions!$H$137>0,G$3>1,MOD(G$3-1,MAX(1,Assumptions!$H$137))=0),Trees!$C$19*(Assumptions!$H$132+Assumptions!$H$133)*Sensitivity!$C$11,0) | H27: =IF(AND(Assumptions!$H$137>0,H$3>1,MOD(H$3-1,MAX(1,Assumptions!$H$137))=0),Trees!$C$19*(Assumptions!$H$132+Assumptions!$H$133)*Sensitivity!$C$11,0) | I27: =IF(AND(Assumptions!$H$137>0,I$3>1,MOD(I$3-1,MAX(1,Assumptions!$H$137))=0),Trees!$C$19*(Assumptions!$H$132+Assumptions!$H$133)*Sensitivity!$C$11,0) | J27: =IF(AND(Assumptions!$H$137>0,J$3>1,MOD(J$3-1,MAX(1,Assumptions!$H$137))=0),Trees!$C$19*(Assumptions!$H$132+Assumptions!$H$133)*Sensitivity!$C$11,0) | K27: =IF(AND(Assumptions!$H$137>0,K$3>1,MOD(K$3-1,MAX(1,Assumptions!$H$137))=0),Trees!$C$19*(Assumptions!$H$132+Assumptions!$H$133)*Sensitivity!$C$11,0) | ... M27: =IF(AND(Assumptions!$H$137>0,M$3>1,MOD(M$3-1,MAX(1,Assumptions!$H$137))=0),Trees!$C$19*(Assumptions!$H$132+Assumptions!$H$133)*Sensitivity!$C$11,0)
B29: Passion fruit
A30: PAS_AREA | B30: Area | C30: =Land!$C$18
A31: PAS_PLANTS | B31: Plants planted | C31: =ROUND(C30*Assumptions!$H$139,0)
A32: PAS_STAND | B32: Final stand | C32: =C31*Assumptions!$H$140
A33: PAS_EST | B33: Establishment cost | C33: =C31*(Assumptions!$H$141+Assumptions!$H$142)*Sensitivity!$C$11
A34: PAS_GAP | B34: Gap-filling cost (year 2) | C34: =C31*(1-Assumptions!$H$140)*Assumptions!$H$141*Sensitivity!$C$11
A35: PAS_AGE | B35: Age in production cycle | C35: years | D35: =IF(Assumptions!$H$146=0,D$3-Sensitivity!$C$13,MOD(D$3-1,MAX(1,Assumptions!$H$146))+1) | E35: =IF(Assumptions!$H$146=0,E$3-Sensitivity!$C$13,MOD(E$3-1,MAX(1,Assumptions!$H$146))+1) | F35: =IF(Assumptions!$H$146=0,F$3-Sensitivity!$C$13,MOD(F$3-1,MAX(1,Assumptions!$H$146))+1) | G35: =IF(Assumptions!$H$146=0,G$3-Sensitivity!$C$13,MOD(G$3-1,MAX(1,Assumptions!$H$146))+1) | H35: =IF(Assumptions!$H$146=0,H$3-Sensitivity!$C$13,MOD(H$3-1,MAX(1,Assumptions!$H$146))+1) | I35: =IF(Assumptions!$H$146=0,I$3-Sensitivity!$C$13,MOD(I$3-1,MAX(1,Assumptions!$H$146))+1) | J35: =IF(Assumptions!$H$146=0,J$3-Sensitivity!$C$13,MOD(J$3-1,MAX(1,Assumptions!$H$146))+1) | K35: =IF(Assumptions!$H$146=0,K$3-Sensitivity!$C$13,MOD(K$3-1,MAX(1,Assumptions!$H$146))+1) | ... M35: =IF(Assumptions!$H$146=0,M$3-Sensitivity!$C$13,MOD(M$3-1,MAX(1,Assumptions!$H$146))+1)
A36: PAS_YLD | B36: Yield per plant | C36: kg | D36: =IF(D35>=1,INDEX(Curves!$D$7:$M$7,1,MIN(10,MAX(1,D35))),0)*Assumptions!$H$143*Sensitivity!$C$7 | E36: =IF(E35>=1,INDEX(Curves!$D$7:$M$7,1,MIN(10,MAX(1,E35))),0)*Assumptions!$H$143*Sensitivity!$C$7 | F36: =IF(F35>=1,INDEX(Curves!$D$7:$M$7,1,MIN(10,MAX(1,F35))),0)*Assumptions!$H$143*Sensitivity!$C$7 | G36: =IF(G35>=1,INDEX(Curves!$D$7:$M$7,1,MIN(10,MAX(1,G35))),0)*Assumptions!$H$143*Sensitivity!$C$7 | H36: =IF(H35>=1,INDEX(Curves!$D$7:$M$7,1,MIN(10,MAX(1,H35))),0)*Assumptions!$H$143*Sensitivity!$C$7 | I36: =IF(I35>=1,INDEX(Curves!$D$7:$M$7,1,MIN(10,MAX(1,I35))),0)*Assumptions!$H$143*Sensitivity!$C$7 | J36: =IF(J35>=1,INDEX(Curves!$D$7:$M$7,1,MIN(10,MAX(1,J35))),0)*Assumptions!$H$143*Sensitivity!$C$7 | K36: =IF(K35>=1,INDEX(Curves!$D$7:$M$7,1,MIN(10,MAX(1,K35))),0)*Assumptions!$H$143*Sensitivity!$C$7 | ... M36: =IF(M35>=1,INDEX(Curves!$D$7:$M$7,1,MIN(10,MAX(1,M35))),0)*Assumptions!$H$143*Sensitivity!$C$7
A37: PAS_PROD | B37: Marketable production | C37: kg | D37: =Trees!$C$32*D36*Assumptions!$H$144 | E37: =Trees!$C$32*E36*Assumptions!$H$144 | F37: =Trees!$C$32*F36*Assumptions!$H$144 | G37: =Trees!$C$32*G36*Assumptions!$H$144 | H37: =Trees!$C$32*H36*Assumptions!$H$144 | I37: =Trees!$C$32*I36*Assumptions!$H$144 | J37: =Trees!$C$32*J36*Assumptions!$H$144 | K37: =Trees!$C$32*K36*Assumptions!$H$144 | ... M37: =Trees!$C$32*M36*Assumptions!$H$144
A38: PAS_REV | B38: Sales | C38: RWF | D38: =D37*Assumptions!$H$145*Sensitivity!$C$5 | E38: =E37*Assumptions!$H$145*Sensitivity!$C$5 | F38: =F37*Assumptions!$H$145*Sensitivity!$C$5 | G38: =G37*Assumptions!$H$145*Sensitivity!$C$5 | H38: =H37*Assumptions!$H$145*Sensitivity!$C$5 | I38: =I37*Assumptions!$H$145*Sensitivity!$C$5 | J38: =J37*Assumptions!$H$145*Sensitivity!$C$5 | K38: =K37*Assumptions!$H$145*Sensitivity!$C$5 | ... M38: =M37*Assumptions!$H$145*Sensitivity!$C$5
A39: PAS_REPL | B39: Replanting (short-cycle crops) | C39: RWF | D39: =IF(AND(Assumptions!$H$146>0,D$3>1,MOD(D$3-1,MAX(1,Assumptions!$H$146))=0),Trees!$C$31*(Assumptions!$H$141+Assumptions!$H$142)*Sensitivity!$C$11,0) | E39: =IF(AND(Assumptions!$H$146>0,E$3>1,MOD(E$3-1,MAX(1,Assumptions!$H$146))=0),Trees!$C$31*(Assumptions!$H$141+Assumptions!$H$142)*Sensitivity!$C$11,0) | F39: =IF(AND(Assumptions!$H$146>0,F$3>1,MOD(F$3-1,MAX(1,Assumptions!$H$146))=0),Trees!$C$31*(Assumptions!$H$141+Assumptions!$H$142)*Sensitivity!$C$11,0) | G39: =IF(AND(Assumptions!$H$146>0,G$3>1,MOD(G$3-1,MAX(1,Assumptions!$H$146))=0),Trees!$C$31*(Assumptions!$H$141+Assumptions!$H$142)*Sensitivity!$C$11,0) | H39: =IF(AND(Assumptions!$H$146>0,H$3>1,MOD(H$3-1,MAX(1,Assumptions!$H$146))=0),Trees!$C$31*(Assumptions!$H$141+Assumptions!$H$142)*Sensitivity!$C$11,0) | I39: =IF(AND(Assumptions!$H$146>0,I$3>1,MOD(I$3-1,MAX(1,Assumptions!$H$146))=0),Trees!$C$31*(Assumptions!$H$141+Assumptions!$H$142)*Sensitivity!$C$11,0) | J39: =IF(AND(Assumptions!$H$146>0,J$3>1,MOD(J$3-1,MAX(1,Assumptions!$H$146))=0),Trees!$C$31*(Assumptions!$H$141+Assumptions!$H$142)*Sensitivity!$C$11,0) | K39: =IF(AND(Assumptions!$H$146>0,K$3>1,MOD(K$3-1,MAX(1,Assumptions!$H$146))=0),Trees!$C$31*(Assumptions!$H$141+Assumptions!$H$142)*Sensitivity!$C$11,0) | ... M39: =IF(AND(Assumptions!$H$146>0,M$3>1,MOD(M$3-1,MAX(1,Assumptions!$H$146))=0),Trees!$C$31*(Assumptions!$H$141+Assumptions!$H$142)*Sensitivity!$C$11,0)
B41: Papaya
A42: PAP_AREA | B42: Area | C42: =Land!$C$19
A43: PAP_PLANTS | B43: Plants planted | C43: =ROUND(C42*Assumptions!$H$148,0)
A44: PAP_STAND | B44: Final stand | C44: =C43*Assumptions!$H$149
A45: PAP_EST | B45: Establishment cost | C45: =C43*(Assumptions!$H$150+Assumptions!$H$151)*Sensitivity!$C$11
A46: PAP_GAP | B46: Gap-filling cost (year 2) | C46: =C43*(1-Assumptions!$H$149)*Assumptions!$H$150*Sensitivity!$C$11
A47: PAP_AGE | B47: Age in production cycle | C47: years | D47: =IF(Assumptions!$H$155=0,D$3-Sensitivity!$C$13,MOD(D$3-1,MAX(1,Assumptions!$H$155))+1) | E47: =IF(Assumptions!$H$155=0,E$3-Sensitivity!$C$13,MOD(E$3-1,MAX(1,Assumptions!$H$155))+1) | F47: =IF(Assumptions!$H$155=0,F$3-Sensitivity!$C$13,MOD(F$3-1,MAX(1,Assumptions!$H$155))+1) | G47: =IF(Assumptions!$H$155=0,G$3-Sensitivity!$C$13,MOD(G$3-1,MAX(1,Assumptions!$H$155))+1) | H47: =IF(Assumptions!$H$155=0,H$3-Sensitivity!$C$13,MOD(H$3-1,MAX(1,Assumptions!$H$155))+1) | I47: =IF(Assumptions!$H$155=0,I$3-Sensitivity!$C$13,MOD(I$3-1,MAX(1,Assumptions!$H$155))+1) | J47: =IF(Assumptions!$H$155=0,J$3-Sensitivity!$C$13,MOD(J$3-1,MAX(1,Assumptions!$H$155))+1) | K47: =IF(Assumptions!$H$155=0,K$3-Sensitivity!$C$13,MOD(K$3-1,MAX(1,Assumptions!$H$155))+1) | ... M47: =IF(Assumptions!$H$155=0,M$3-Sensitivity!$C$13,MOD(M$3-1,MAX(1,Assumptions!$H$155))+1)
A48: PAP_YLD | B48: Yield per plant | C48: kg | D48: =IF(D47>=1,INDEX(Curves!$D$8:$M$8,1,MIN(10,MAX(1,D47))),0)*Assumptions!$H$152*Sensitivity!$C$7 | E48: =IF(E47>=1,INDEX(Curves!$D$8:$M$8,1,MIN(10,MAX(1,E47))),0)*Assumptions!$H$152*Sensitivity!$C$7 | F48: =IF(F47>=1,INDEX(Curves!$D$8:$M$8,1,MIN(10,MAX(1,F47))),0)*Assumptions!$H$152*Sensitivity!$C$7 | G48: =IF(G47>=1,INDEX(Curves!$D$8:$M$8,1,MIN(10,MAX(1,G47))),0)*Assumptions!$H$152*Sensitivity!$C$7 | H48: =IF(H47>=1,INDEX(Curves!$D$8:$M$8,1,MIN(10,MAX(1,H47))),0)*Assumptions!$H$152*Sensitivity!$C$7 | I48: =IF(I47>=1,INDEX(Curves!$D$8:$M$8,1,MIN(10,MAX(1,I47))),0)*Assumptions!$H$152*Sensitivity!$C$7 | J48: =IF(J47>=1,INDEX(Curves!$D$8:$M$8,1,MIN(10,MAX(1,J47))),0)*Assumptions!$H$152*Sensitivity!$C$7 | K48: =IF(K47>=1,INDEX(Curves!$D$8:$M$8,1,MIN(10,MAX(1,K47))),0)*Assumptions!$H$152*Sensitivity!$C$7 | ... M48: =IF(M47>=1,INDEX(Curves!$D$8:$M$8,1,MIN(10,MAX(1,M47))),0)*Assumptions!$H$152*Sensitivity!$C$7
A49: PAP_PROD | B49: Marketable production | C49: kg | D49: =Trees!$C$44*D48*Assumptions!$H$153 | E49: =Trees!$C$44*E48*Assumptions!$H$153 | F49: =Trees!$C$44*F48*Assumptions!$H$153 | G49: =Trees!$C$44*G48*Assumptions!$H$153 | H49: =Trees!$C$44*H48*Assumptions!$H$153 | I49: =Trees!$C$44*I48*Assumptions!$H$153 | J49: =Trees!$C$44*J48*Assumptions!$H$153 | K49: =Trees!$C$44*K48*Assumptions!$H$153 | ... M49: =Trees!$C$44*M48*Assumptions!$H$153
A50: PAP_REV | B50: Sales | C50: RWF | D50: =D49*Assumptions!$H$154*Sensitivity!$C$5 | E50: =E49*Assumptions!$H$154*Sensitivity!$C$5 | F50: =F49*Assumptions!$H$154*Sensitivity!$C$5 | G50: =G49*Assumptions!$H$154*Sensitivity!$C$5 | H50: =H49*Assumptions!$H$154*Sensitivity!$C$5 | I50: =I49*Assumptions!$H$154*Sensitivity!$C$5 | J50: =J49*Assumptions!$H$154*Sensitivity!$C$5 | K50: =K49*Assumptions!$H$154*Sensitivity!$C$5 | ... M50: =M49*Assumptions!$H$154*Sensitivity!$C$5
A51: PAP_REPL | B51: Replanting (short-cycle crops) | C51: RWF | D51: =IF(AND(Assumptions!$H$155>0,D$3>1,MOD(D$3-1,MAX(1,Assumptions!$H$155))=0),Trees!$C$43*(Assumptions!$H$150+Assumptions!$H$151)*Sensitivity!$C$11,0) | E51: =IF(AND(Assumptions!$H$155>0,E$3>1,MOD(E$3-1,MAX(1,Assumptions!$H$155))=0),Trees!$C$43*(Assumptions!$H$150+Assumptions!$H$151)*Sensitivity!$C$11,0) | F51: =IF(AND(Assumptions!$H$155>0,F$3>1,MOD(F$3-1,MAX(1,Assumptions!$H$155))=0),Trees!$C$43*(Assumptions!$H$150+Assumptions!$H$151)*Sensitivity!$C$11,0) | G51: =IF(AND(Assumptions!$H$155>0,G$3>1,MOD(G$3-1,MAX(1,Assumptions!$H$155))=0),Trees!$C$43*(Assumptions!$H$150+Assumptions!$H$151)*Sensitivity!$C$11,0) | H51: =IF(AND(Assumptions!$H$155>0,H$3>1,MOD(H$3-1,MAX(1,Assumptions!$H$155))=0),Trees!$C$43*(Assumptions!$H$150+Assumptions!$H$151)*Sensitivity!$C$11,0) | I51: =IF(AND(Assumptions!$H$155>0,I$3>1,MOD(I$3-1,MAX(1,Assumptions!$H$155))=0),Trees!$C$43*(Assumptions!$H$150+Assumptions!$H$151)*Sensitivity!$C$11,0) | J51: =IF(AND(Assumptions!$H$155>0,J$3>1,MOD(J$3-1,MAX(1,Assumptions!$H$155))=0),Trees!$C$43*(Assumptions!$H$150+Assumptions!$H$151)*Sensitivity!$C$11,0) | K51: =IF(AND(Assumptions!$H$155>0,K$3>1,MOD(K$3-1,MAX(1,Assumptions!$H$155))=0),Trees!$C$43*(Assumptions!$H$150+Assumptions!$H$151)*Sensitivity!$C$11,0) | ... M51: =IF(AND(Assumptions!$H$155>0,M$3>1,MOD(M$3-1,MAX(1,Assumptions!$H$155))=0),Trees!$C$43*(Assumptions!$H$150+Assumptions!$H$151)*Sensitivity!$C$11,0)
B53: Tree tomato
A54: TTO_AREA | B54: Area | C54: =Land!$C$20
A55: TTO_PLANTS | B55: Plants planted | C55: =ROUND(C54*Assumptions!$H$157,0)
A56: TTO_STAND | B56: Final stand | C56: =C55*Assumptions!$H$158
A57: TTO_EST | B57: Establishment cost | C57: =C55*(Assumptions!$H$159+Assumptions!$H$160)*Sensitivity!$C$11
A58: TTO_GAP | B58: Gap-filling cost (year 2) | C58: =C55*(1-Assumptions!$H$158)*Assumptions!$H$159*Sensitivity!$C$11
A59: TTO_AGE | B59: Age in production cycle | C59: years | D59: =IF(Assumptions!$H$164=0,D$3-Sensitivity!$C$13,MOD(D$3-1,MAX(1,Assumptions!$H$164))+1) | E59: =IF(Assumptions!$H$164=0,E$3-Sensitivity!$C$13,MOD(E$3-1,MAX(1,Assumptions!$H$164))+1) | F59: =IF(Assumptions!$H$164=0,F$3-Sensitivity!$C$13,MOD(F$3-1,MAX(1,Assumptions!$H$164))+1) | G59: =IF(Assumptions!$H$164=0,G$3-Sensitivity!$C$13,MOD(G$3-1,MAX(1,Assumptions!$H$164))+1) | H59: =IF(Assumptions!$H$164=0,H$3-Sensitivity!$C$13,MOD(H$3-1,MAX(1,Assumptions!$H$164))+1) | I59: =IF(Assumptions!$H$164=0,I$3-Sensitivity!$C$13,MOD(I$3-1,MAX(1,Assumptions!$H$164))+1) | J59: =IF(Assumptions!$H$164=0,J$3-Sensitivity!$C$13,MOD(J$3-1,MAX(1,Assumptions!$H$164))+1) | K59: =IF(Assumptions!$H$164=0,K$3-Sensitivity!$C$13,MOD(K$3-1,MAX(1,Assumptions!$H$164))+1) | ... M59: =IF(Assumptions!$H$164=0,M$3-Sensitivity!$C$13,MOD(M$3-1,MAX(1,Assumptions!$H$164))+1)
A60: TTO_YLD | B60: Yield per plant | C60: kg | D60: =IF(D59>=1,INDEX(Curves!$D$9:$M$9,1,MIN(10,MAX(1,D59))),0)*Assumptions!$H$161*Sensitivity!$C$7 | E60: =IF(E59>=1,INDEX(Curves!$D$9:$M$9,1,MIN(10,MAX(1,E59))),0)*Assumptions!$H$161*Sensitivity!$C$7 | F60: =IF(F59>=1,INDEX(Curves!$D$9:$M$9,1,MIN(10,MAX(1,F59))),0)*Assumptions!$H$161*Sensitivity!$C$7 | G60: =IF(G59>=1,INDEX(Curves!$D$9:$M$9,1,MIN(10,MAX(1,G59))),0)*Assumptions!$H$161*Sensitivity!$C$7 | H60: =IF(H59>=1,INDEX(Curves!$D$9:$M$9,1,MIN(10,MAX(1,H59))),0)*Assumptions!$H$161*Sensitivity!$C$7 | I60: =IF(I59>=1,INDEX(Curves!$D$9:$M$9,1,MIN(10,MAX(1,I59))),0)*Assumptions!$H$161*Sensitivity!$C$7 | J60: =IF(J59>=1,INDEX(Curves!$D$9:$M$9,1,MIN(10,MAX(1,J59))),0)*Assumptions!$H$161*Sensitivity!$C$7 | K60: =IF(K59>=1,INDEX(Curves!$D$9:$M$9,1,MIN(10,MAX(1,K59))),0)*Assumptions!$H$161*Sensitivity!$C$7 | ... M60: =IF(M59>=1,INDEX(Curves!$D$9:$M$9,1,MIN(10,MAX(1,M59))),0)*Assumptions!$H$161*Sensitivity!$C$7
A61: TTO_PROD | B61: Marketable production | C61: kg | D61: =Trees!$C$56*D60*Assumptions!$H$162 | E61: =Trees!$C$56*E60*Assumptions!$H$162 | F61: =Trees!$C$56*F60*Assumptions!$H$162 | G61: =Trees!$C$56*G60*Assumptions!$H$162 | H61: =Trees!$C$56*H60*Assumptions!$H$162 | I61: =Trees!$C$56*I60*Assumptions!$H$162 | J61: =Trees!$C$56*J60*Assumptions!$H$162 | K61: =Trees!$C$56*K60*Assumptions!$H$162 | ... M61: =Trees!$C$56*M60*Assumptions!$H$162
A62: TTO_REV | B62: Sales | C62: RWF | D62: =D61*Assumptions!$H$163*Sensitivity!$C$5 | E62: =E61*Assumptions!$H$163*Sensitivity!$C$5 | F62: =F61*Assumptions!$H$163*Sensitivity!$C$5 | G62: =G61*Assumptions!$H$163*Sensitivity!$C$5 | H62: =H61*Assumptions!$H$163*Sensitivity!$C$5 | I62: =I61*Assumptions!$H$163*Sensitivity!$C$5 | J62: =J61*Assumptions!$H$163*Sensitivity!$C$5 | K62: =K61*Assumptions!$H$163*Sensitivity!$C$5 | ... M62: =M61*Assumptions!$H$163*Sensitivity!$C$5
A63: TTO_REPL | B63: Replanting (short-cycle crops) | C63: RWF | D63: =IF(AND(Assumptions!$H$164>0,D$3>1,MOD(D$3-1,MAX(1,Assumptions!$H$164))=0),Trees!$C$55*(Assumptions!$H$159+Assumptions!$H$160)*Sensitivity!$C$11,0) | E63: =IF(AND(Assumptions!$H$164>0,E$3>1,MOD(E$3-1,MAX(1,Assumptions!$H$164))=0),Trees!$C$55*(Assumptions!$H$159+Assumptions!$H$160)*Sensitivity!$C$11,0) | F63: =IF(AND(Assumptions!$H$164>0,F$3>1,MOD(F$3-1,MAX(1,Assumptions!$H$164))=0),Trees!$C$55*(Assumptions!$H$159+Assumptions!$H$160)*Sensitivity!$C$11,0) | G63: =IF(AND(Assumptions!$H$164>0,G$3>1,MOD(G$3-1,MAX(1,Assumptions!$H$164))=0),Trees!$C$55*(Assumptions!$H$159+Assumptions!$H$160)*Sensitivity!$C$11,0) | H63: =IF(AND(Assumptions!$H$164>0,H$3>1,MOD(H$3-1,MAX(1,Assumptions!$H$164))=0),Trees!$C$55*(Assumptions!$H$159+Assumptions!$H$160)*Sensitivity!$C$11,0) | I63: =IF(AND(Assumptions!$H$164>0,I$3>1,MOD(I$3-1,MAX(1,Assumptions!$H$164))=0),Trees!$C$55*(Assumptions!$H$159+Assumptions!$H$160)*Sensitivity!$C$11,0) | J63: =IF(AND(Assumptions!$H$164>0,J$3>1,MOD(J$3-1,MAX(1,Assumptions!$H$164))=0),Trees!$C$55*(Assumptions!$H$159+Assumptions!$H$160)*Sensitivity!$C$11,0) | K63: =IF(AND(Assumptions!$H$164>0,K$3>1,MOD(K$3-1,MAX(1,Assumptions!$H$164))=0),Trees!$C$55*(Assumptions!$H$159+Assumptions!$H$160)*Sensitivity!$C$11,0) | ... M63: =IF(AND(Assumptions!$H$164>0,M$3>1,MOD(M$3-1,MAX(1,Assumptions!$H$164))=0),Trees!$C$55*(Assumptions!$H$159+Assumptions!$H$160)*Sensitivity!$C$11,0)
B65: Citrus
A66: CIT_AREA | B66: Area | C66: =Land!$C$21
A67: CIT_PLANTS | B67: Plants planted | C67: =ROUND(C66*Assumptions!$H$166,0)
A68: CIT_STAND | B68: Final stand | C68: =C67*Assumptions!$H$167
A69: CIT_EST | B69: Establishment cost | C69: =C67*(Assumptions!$H$168+Assumptions!$H$169)*Sensitivity!$C$11
A70: CIT_GAP | B70: Gap-filling cost (year 2) | C70: =C67*(1-Assumptions!$H$167)*Assumptions!$H$168*Sensitivity!$C$11
A71: CIT_AGE | B71: Age in production cycle | C71: years | D71: =IF(Assumptions!$H$173=0,D$3-Sensitivity!$C$13,MOD(D$3-1,MAX(1,Assumptions!$H$173))+1) | E71: =IF(Assumptions!$H$173=0,E$3-Sensitivity!$C$13,MOD(E$3-1,MAX(1,Assumptions!$H$173))+1) | F71: =IF(Assumptions!$H$173=0,F$3-Sensitivity!$C$13,MOD(F$3-1,MAX(1,Assumptions!$H$173))+1) | G71: =IF(Assumptions!$H$173=0,G$3-Sensitivity!$C$13,MOD(G$3-1,MAX(1,Assumptions!$H$173))+1) | H71: =IF(Assumptions!$H$173=0,H$3-Sensitivity!$C$13,MOD(H$3-1,MAX(1,Assumptions!$H$173))+1) | I71: =IF(Assumptions!$H$173=0,I$3-Sensitivity!$C$13,MOD(I$3-1,MAX(1,Assumptions!$H$173))+1) | J71: =IF(Assumptions!$H$173=0,J$3-Sensitivity!$C$13,MOD(J$3-1,MAX(1,Assumptions!$H$173))+1) | K71: =IF(Assumptions!$H$173=0,K$3-Sensitivity!$C$13,MOD(K$3-1,MAX(1,Assumptions!$H$173))+1) | ... M71: =IF(Assumptions!$H$173=0,M$3-Sensitivity!$C$13,MOD(M$3-1,MAX(1,Assumptions!$H$173))+1)
A72: CIT_YLD | B72: Yield per plant | C72: kg | D72: =IF(D71>=1,INDEX(Curves!$D$10:$M$10,1,MIN(10,MAX(1,D71))),0)*Assumptions!$H$170*Sensitivity!$C$7 | E72: =IF(E71>=1,INDEX(Curves!$D$10:$M$10,1,MIN(10,MAX(1,E71))),0)*Assumptions!$H$170*Sensitivity!$C$7 | F72: =IF(F71>=1,INDEX(Curves!$D$10:$M$10,1,MIN(10,MAX(1,F71))),0)*Assumptions!$H$170*Sensitivity!$C$7 | G72: =IF(G71>=1,INDEX(Curves!$D$10:$M$10,1,MIN(10,MAX(1,G71))),0)*Assumptions!$H$170*Sensitivity!$C$7 | H72: =IF(H71>=1,INDEX(Curves!$D$10:$M$10,1,MIN(10,MAX(1,H71))),0)*Assumptions!$H$170*Sensitivity!$C$7 | I72: =IF(I71>=1,INDEX(Curves!$D$10:$M$10,1,MIN(10,MAX(1,I71))),0)*Assumptions!$H$170*Sensitivity!$C$7 | J72: =IF(J71>=1,INDEX(Curves!$D$10:$M$10,1,MIN(10,MAX(1,J71))),0)*Assumptions!$H$170*Sensitivity!$C$7 | K72: =IF(K71>=1,INDEX(Curves!$D$10:$M$10,1,MIN(10,MAX(1,K71))),0)*Assumptions!$H$170*Sensitivity!$C$7 | ... M72: =IF(M71>=1,INDEX(Curves!$D$10:$M$10,1,MIN(10,MAX(1,M71))),0)*Assumptions!$H$170*Sensitivity!$C$7
A73: CIT_PROD | B73: Marketable production | C73: kg | D73: =Trees!$C$68*D72*Assumptions!$H$171 | E73: =Trees!$C$68*E72*Assumptions!$H$171 | F73: =Trees!$C$68*F72*Assumptions!$H$171 | G73: =Trees!$C$68*G72*Assumptions!$H$171 | H73: =Trees!$C$68*H72*Assumptions!$H$171 | I73: =Trees!$C$68*I72*Assumptions!$H$171 | J73: =Trees!$C$68*J72*Assumptions!$H$171 | K73: =Trees!$C$68*K72*Assumptions!$H$171 | ... M73: =Trees!$C$68*M72*Assumptions!$H$171
A74: CIT_REV | B74: Sales | C74: RWF | D74: =D73*Assumptions!$H$172*Sensitivity!$C$5 | E74: =E73*Assumptions!$H$172*Sensitivity!$C$5 | F74: =F73*Assumptions!$H$172*Sensitivity!$C$5 | G74: =G73*Assumptions!$H$172*Sensitivity!$C$5 | H74: =H73*Assumptions!$H$172*Sensitivity!$C$5 | I74: =I73*Assumptions!$H$172*Sensitivity!$C$5 | J74: =J73*Assumptions!$H$172*Sensitivity!$C$5 | K74: =K73*Assumptions!$H$172*Sensitivity!$C$5 | ... M74: =M73*Assumptions!$H$172*Sensitivity!$C$5
A75: CIT_REPL | B75: Replanting (short-cycle crops) | C75: RWF | D75: =IF(AND(Assumptions!$H$173>0,D$3>1,MOD(D$3-1,MAX(1,Assumptions!$H$173))=0),Trees!$C$67*(Assumptions!$H$168+Assumptions!$H$169)*Sensitivity!$C$11,0) | E75: =IF(AND(Assumptions!$H$173>0,E$3>1,MOD(E$3-1,MAX(1,Assumptions!$H$173))=0),Trees!$C$67*(Assumptions!$H$168+Assumptions!$H$169)*Sensitivity!$C$11,0) | F75: =IF(AND(Assumptions!$H$173>0,F$3>1,MOD(F$3-1,MAX(1,Assumptions!$H$173))=0),Trees!$C$67*(Assumptions!$H$168+Assumptions!$H$169)*Sensitivity!$C$11,0) | G75: =IF(AND(Assumptions!$H$173>0,G$3>1,MOD(G$3-1,MAX(1,Assumptions!$H$173))=0),Trees!$C$67*(Assumptions!$H$168+Assumptions!$H$169)*Sensitivity!$C$11,0) | H75: =IF(AND(Assumptions!$H$173>0,H$3>1,MOD(H$3-1,MAX(1,Assumptions!$H$173))=0),Trees!$C$67*(Assumptions!$H$168+Assumptions!$H$169)*Sensitivity!$C$11,0) | I75: =IF(AND(Assumptions!$H$173>0,I$3>1,MOD(I$3-1,MAX(1,Assumptions!$H$173))=0),Trees!$C$67*(Assumptions!$H$168+Assumptions!$H$169)*Sensitivity!$C$11,0) | J75: =IF(AND(Assumptions!$H$173>0,J$3>1,MOD(J$3-1,MAX(1,Assumptions!$H$173))=0),Trees!$C$67*(Assumptions!$H$168+Assumptions!$H$169)*Sensitivity!$C$11,0) | K75: =IF(AND(Assumptions!$H$173>0,K$3>1,MOD(K$3-1,MAX(1,Assumptions!$H$173))=0),Trees!$C$67*(Assumptions!$H$168+Assumptions!$H$169)*Sensitivity!$C$11,0) | ... M75: =IF(AND(Assumptions!$H$173>0,M$3>1,MOD(M$3-1,MAX(1,Assumptions!$H$173))=0),Trees!$C$67*(Assumptions!$H$168+Assumptions!$H$169)*Sensitivity!$C$11,0)
B77: Macadamia (nut in shell)
A78: MAC_AREA | B78: Area | C78: =Land!$C$22
A79: MAC_PLANTS | B79: Plants planted | C79: =ROUND(C78*Assumptions!$H$175,0)
A80: MAC_STAND | B80: Final stand | C80: =C79*Assumptions!$H$176
A81: MAC_EST | B81: Establishment cost | C81: =C79*(Assumptions!$H$177+Assumptions!$H$178)*Sensitivity!$C$11
A82: MAC_GAP | B82: Gap-filling cost (year 2) | C82: =C79*(1-Assumptions!$H$176)*Assumptions!$H$177*Sensitivity!$C$11
A83: MAC_AGE | B83: Age in production cycle | C83: years | D83: =IF(Assumptions!$H$182=0,D$3-Sensitivity!$C$13,MOD(D$3-1,MAX(1,Assumptions!$H$182))+1) | E83: =IF(Assumptions!$H$182=0,E$3-Sensitivity!$C$13,MOD(E$3-1,MAX(1,Assumptions!$H$182))+1) | F83: =IF(Assumptions!$H$182=0,F$3-Sensitivity!$C$13,MOD(F$3-1,MAX(1,Assumptions!$H$182))+1) | G83: =IF(Assumptions!$H$182=0,G$3-Sensitivity!$C$13,MOD(G$3-1,MAX(1,Assumptions!$H$182))+1) | H83: =IF(Assumptions!$H$182=0,H$3-Sensitivity!$C$13,MOD(H$3-1,MAX(1,Assumptions!$H$182))+1) | I83: =IF(Assumptions!$H$182=0,I$3-Sensitivity!$C$13,MOD(I$3-1,MAX(1,Assumptions!$H$182))+1) | J83: =IF(Assumptions!$H$182=0,J$3-Sensitivity!$C$13,MOD(J$3-1,MAX(1,Assumptions!$H$182))+1) | K83: =IF(Assumptions!$H$182=0,K$3-Sensitivity!$C$13,MOD(K$3-1,MAX(1,Assumptions!$H$182))+1) | ... M83: =IF(Assumptions!$H$182=0,M$3-Sensitivity!$C$13,MOD(M$3-1,MAX(1,Assumptions!$H$182))+1)
A84: MAC_YLD | B84: Yield per plant | C84: kg | D84: =IF(D83>=1,INDEX(Curves!$D$11:$M$11,1,MIN(10,MAX(1,D83))),0)*Assumptions!$H$179*Sensitivity!$C$7 | E84: =IF(E83>=1,INDEX(Curves!$D$11:$M$11,1,MIN(10,MAX(1,E83))),0)*Assumptions!$H$179*Sensitivity!$C$7 | F84: =IF(F83>=1,INDEX(Curves!$D$11:$M$11,1,MIN(10,MAX(1,F83))),0)*Assumptions!$H$179*Sensitivity!$C$7 | G84: =IF(G83>=1,INDEX(Curves!$D$11:$M$11,1,MIN(10,MAX(1,G83))),0)*Assumptions!$H$179*Sensitivity!$C$7 | H84: =IF(H83>=1,INDEX(Curves!$D$11:$M$11,1,MIN(10,MAX(1,H83))),0)*Assumptions!$H$179*Sensitivity!$C$7 | I84: =IF(I83>=1,INDEX(Curves!$D$11:$M$11,1,MIN(10,MAX(1,I83))),0)*Assumptions!$H$179*Sensitivity!$C$7 | J84: =IF(J83>=1,INDEX(Curves!$D$11:$M$11,1,MIN(10,MAX(1,J83))),0)*Assumptions!$H$179*Sensitivity!$C$7 | K84: =IF(K83>=1,INDEX(Curves!$D$11:$M$11,1,MIN(10,MAX(1,K83))),0)*Assumptions!$H$179*Sensitivity!$C$7 | ... M84: =IF(M83>=1,INDEX(Curves!$D$11:$M$11,1,MIN(10,MAX(1,M83))),0)*Assumptions!$H$179*Sensitivity!$C$7
A85: MAC_PROD | B85: Marketable production | C85: kg | D85: =Trees!$C$80*D84*Assumptions!$H$180 | E85: =Trees!$C$80*E84*Assumptions!$H$180 | F85: =Trees!$C$80*F84*Assumptions!$H$180 | G85: =Trees!$C$80*G84*Assumptions!$H$180 | H85: =Trees!$C$80*H84*Assumptions!$H$180 | I85: =Trees!$C$80*I84*Assumptions!$H$180 | J85: =Trees!$C$80*J84*Assumptions!$H$180 | K85: =Trees!$C$80*K84*Assumptions!$H$180 | ... M85: =Trees!$C$80*M84*Assumptions!$H$180
A86: MAC_REV | B86: Sales | C86: RWF | D86: =D85*Assumptions!$H$181*Sensitivity!$C$5 | E86: =E85*Assumptions!$H$181*Sensitivity!$C$5 | F86: =F85*Assumptions!$H$181*Sensitivity!$C$5 | G86: =G85*Assumptions!$H$181*Sensitivity!$C$5 | H86: =H85*Assumptions!$H$181*Sensitivity!$C$5 | I86: =I85*Assumptions!$H$181*Sensitivity!$C$5 | J86: =J85*Assumptions!$H$181*Sensitivity!$C$5 | K86: =K85*Assumptions!$H$181*Sensitivity!$C$5 | ... M86: =M85*Assumptions!$H$181*Sensitivity!$C$5
A87: MAC_REPL | B87: Replanting (short-cycle crops) | C87: RWF | D87: =IF(AND(Assumptions!$H$182>0,D$3>1,MOD(D$3-1,MAX(1,Assumptions!$H$182))=0),Trees!$C$79*(Assumptions!$H$177+Assumptions!$H$178)*Sensitivity!$C$11,0) | E87: =IF(AND(Assumptions!$H$182>0,E$3>1,MOD(E$3-1,MAX(1,Assumptions!$H$182))=0),Trees!$C$79*(Assumptions!$H$177+Assumptions!$H$178)*Sensitivity!$C$11,0) | F87: =IF(AND(Assumptions!$H$182>0,F$3>1,MOD(F$3-1,MAX(1,Assumptions!$H$182))=0),Trees!$C$79*(Assumptions!$H$177+Assumptions!$H$178)*Sensitivity!$C$11,0) | G87: =IF(AND(Assumptions!$H$182>0,G$3>1,MOD(G$3-1,MAX(1,Assumptions!$H$182))=0),Trees!$C$79*(Assumptions!$H$177+Assumptions!$H$178)*Sensitivity!$C$11,0) | H87: =IF(AND(Assumptions!$H$182>0,H$3>1,MOD(H$3-1,MAX(1,Assumptions!$H$182))=0),Trees!$C$79*(Assumptions!$H$177+Assumptions!$H$178)*Sensitivity!$C$11,0) | I87: =IF(AND(Assumptions!$H$182>0,I$3>1,MOD(I$3-1,MAX(1,Assumptions!$H$182))=0),Trees!$C$79*(Assumptions!$H$177+Assumptions!$H$178)*Sensitivity!$C$11,0) | J87: =IF(AND(Assumptions!$H$182>0,J$3>1,MOD(J$3-1,MAX(1,Assumptions!$H$182))=0),Trees!$C$79*(Assumptions!$H$177+Assumptions!$H$178)*Sensitivity!$C$11,0) | K87: =IF(AND(Assumptions!$H$182>0,K$3>1,MOD(K$3-1,MAX(1,Assumptions!$H$182))=0),Trees!$C$79*(Assumptions!$H$177+Assumptions!$H$178)*Sensitivity!$C$11,0) | ... M87: =IF(AND(Assumptions!$H$182>0,M$3>1,MOD(M$3-1,MAX(1,Assumptions!$H$182))=0),Trees!$C$79*(Assumptions!$H$177+Assumptions!$H$178)*Sensitivity!$C$11,0)
B89: Boundary timber and poles
A90: TIM_TREES | B90: Trees planted on the boundary | C90: =ROUND(Land!$C$6/Assumptions!$H$185,0)
A91: TIM_STAND | B91: Final stand | C91: =C90*Assumptions!$H$186
A92: TIM_EST | B92: Establishment cost | C92: =C90*(Assumptions!$H$187+Assumptions!$H$188)*Sensitivity!$C$11
A93: TIM_MEMO | B93: Memo: standing value of remaining trees at Y10 (not in NPV) | C93: =C91*(1-Assumptions!$H$190)*Assumptions!$H$192
A94: TIM_REV | B94: Pole sales (first thinning) | C94: RWF | D94: =IF(D$3=Assumptions!$H$189,Trees!$C$91*Assumptions!$H$190*Assumptions!$H$191,0) | E94: =IF(E$3=Assumptions!$H$189,Trees!$C$91*Assumptions!$H$190*Assumptions!$H$191,0) | F94: =IF(F$3=Assumptions!$H$189,Trees!$C$91*Assumptions!$H$190*Assumptions!$H$191,0) | G94: =IF(G$3=Assumptions!$H$189,Trees!$C$91*Assumptions!$H$190*Assumptions!$H$191,0) | H94: =IF(H$3=Assumptions!$H$189,Trees!$C$91*Assumptions!$H$190*Assumptions!$H$191,0) | I94: =IF(I$3=Assumptions!$H$189,Trees!$C$91*Assumptions!$H$190*Assumptions!$H$191,0) | J94: =IF(J$3=Assumptions!$H$189,Trees!$C$91*Assumptions!$H$190*Assumptions!$H$191,0) | K94: =IF(K$3=Assumptions!$H$189,Trees!$C$91*Assumptions!$H$190*Assumptions!$H$191,0) | ... M94: =IF(M$3=Assumptions!$H$189,Trees!$C$91*Assumptions!$H$190*Assumptions!$H$191,0)
B96: Totals
A97: TR_EST | B97: Orchard establishment cost (all crops) | C97: =Trees!$C$9+Trees!$C$21+Trees!$C$33+Trees!$C$45+Trees!$C$57+Trees!$C$69+Trees!$C$81
A98: TR_GAP | B98: Gap-filling cost, year 2 (all crops) | C98: =Trees!$C$10+Trees!$C$22+Trees!$C$34+Trees!$C$46+Trees!$C$58+Trees!$C$70+Trees!$C$82
A99: TR_REV | B99: Fruit sales (all crops) | C99: RWF | D99: =D14+D26+D38+D50+D62+D74+D86 | E99: =E14+E26+E38+E50+E62+E74+E86 | F99: =F14+F26+F38+F50+F62+F74+F86 | G99: =G14+G26+G38+G50+G62+G74+G86 | H99: =H14+H26+H38+H50+H62+H74+H86 | I99: =I14+I26+I38+I50+I62+I74+I86 | J99: =J14+J26+J38+J50+J62+J74+J86 | K99: =K14+K26+K38+K50+K62+K74+K86 | ... M99: =M14+M26+M38+M50+M62+M74+M86
A100: TR_PROD | B100: Marketable fruit (all crops) | C100: kg | D100: =D13+D25+D37+D49+D61+D73+D85 | E100: =E13+E25+E37+E49+E61+E73+E85 | F100: =F13+F25+F37+F49+F61+F73+F85 | G100: =G13+G25+G37+G49+G61+G73+G85 | H100: =H13+H25+H37+H49+H61+H73+H85 | I100: =I13+I25+I37+I49+I61+I73+I85 | J100: =J13+J25+J37+J49+J61+J73+J85 | K100: =K13+K25+K37+K49+K61+K73+K85 | ... M100: =M13+M25+M37+M49+M61+M73+M85
A101: TR_REPL | B101: Replanting (all crops) | C101: RWF | D101: =D15+D27+D39+D51+D63+D75+D87 | E101: =E15+E27+E39+E51+E63+E75+E87 | F101: =F15+F27+F39+F51+F63+F75+F87 | G101: =G15+G27+G39+G51+G63+G75+G87 | H101: =H15+H27+H39+H51+H63+H75+H87 | I101: =I15+I27+I39+I51+I63+I75+I87 | J101: =J15+J27+J39+J51+J63+J75+J87 | K101: =K15+K27+K39+K51+K63+K75+K87 | ... M101: =M15+M27+M39+M51+M63+M75+M87

Sheet Livestock
A1: Livestock
A2: Monthly herd engine. Young are sold at 9 months; females give first birth 6 months after joining.
B3: Month | D3: 1 | E3: 2 | F3: 3 | G3: 4 | H3: 5 | I3: 6 | J3: 7 | K3: 8 | L3: 9 | M3: 10 | N3: 11 | O3: 12 | P3: 13 | Q3: 14 | R3: 15 | S3: 16 | T3: 17 | U3: 18 | V3: 19 | W3: 20 | X3: 21 | Y3: 22 | Z3: 23 | AA3: 24 | AB3: 25 | AC3: 26 | AD3: 27 | AE3: 28 | AF3: 29 | AG3: 30 | AH3: 31 | AI3: 32 | AJ3: 33 | AK3: 34 | AL3: 35 | AM3: 36 | AN3: 37 | AO3: 38 | AP3: 39 | AQ3: 40 | AR3: 41 | AS3: 42 | AT3: 43 | AU3: 44 | AV3: 45 | AW3: 46 | AX3: 47 | AY3: 48 | AZ3: 49 | BA3: 50 | BB3: 51 | BC3: 52 | BD3: 53 | BE3: 54 | BF3: 55 | BG3: 56 | BH3: 57 | BI3: 58 | BJ3: 59 | BK3: 60 | BL3: 61 | BM3: 62 | BN3: 63 | BO3: 64 | BP3: 65 | BQ3: 66 | BR3: 67 | BS3: 68 | BT3: 69 | BU3: 70 | BV3: 71 | BW3: 72 | BX3: 73 | BY3: 74 | BZ3: 75 | CA3: 76 | CB3: 77 | CC3: 78 | CD3: 79 | CE3: 80 | CF3: 81 | CG3: 82 | CH3: 83 | CI3: 84 | CJ3: 85 | CK3: 86 | CL3: 87 | CM3: 88 | CN3: 89 | CO3: 90 | CP3: 91 | CQ3: 92 | CR3: 93 | CS3: 94 | CT3: 95 | CU3: 96 | CV3: 97 | CW3: 98 | CX3: 99 | CY3: 100 | CZ3: 101 | DA3: 102 | DB3: 103 | DC3: 104 | DD3: 105 | DE3: 106 | DF3: 107 | DG3: 108 | DH3: 109 | DI3: 110 | DJ3: 111 | DK3: 112 | DL3: 113 | DM3: 114 | DN3: 115 | DO3: 116 | DP3: 117 | DQ3: 118 | DR3: 119 | DS3: 120
B4: Farm year | D4: =INT((D$3-1)/12)+1 | E4: =INT((E$3-1)/12)+1 | F4: =INT((F$3-1)/12)+1 | G4: =INT((G$3-1)/12)+1 | H4: =INT((H$3-1)/12)+1 | I4: =INT((I$3-1)/12)+1 | J4: =INT((J$3-1)/12)+1 | K4: =INT((K$3-1)/12)+1 | ... DS4: =INT((DS$3-1)/12)+1
B5: Calendar month | D5: =MOD(Control!$C$10+D$3-2,12)+1 | E5: =MOD(Control!$C$10+E$3-2,12)+1 | F5: =MOD(Control!$C$10+F$3-2,12)+1 | G5: =MOD(Control!$C$10+G$3-2,12)+1 | H5: =MOD(Control!$C$10+H$3-2,12)+1 | I5: =MOD(Control!$C$10+I$3-2,12)+1 | J5: =MOD(Control!$C$10+J$3-2,12)+1 | K5: =MOD(Control!$C$10+K$3-2,12)+1 | ... DS5: =MOD(Control!$C$10+DS$3-2,12)+1
B6: Month starting | D6: =DATE(Control!$C$9+INT((Control!$C$10+D$3-2)/12),D$5,1) | E6: =DATE(Control!$C$9+INT((Control!$C$10+E$3-2)/12),E$5,1) | F6: =DATE(Control!$C$9+INT((Control!$C$10+F$3-2)/12),F$5,1) | G6: =DATE(Control!$C$9+INT((Control!$C$10+G$3-2)/12),G$5,1) | H6: =DATE(Control!$C$9+INT((Control!$C$10+H$3-2)/12),H$5,1) | I6: =DATE(Control!$C$9+INT((Control!$C$10+I$3-2)/12),I$5,1) | J6: =DATE(Control!$C$9+INT((Control!$C$10+J$3-2)/12),J$5,1) | K6: =DATE(Control!$C$9+INT((Control!$C$10+K$3-2)/12),K$5,1) | ... DS6: =DATE(Control!$C$9+INT((Control!$C$10+DS$3-2)/12),DS$5,1)
B8: Goats
A9: GT_FBUY | B9: Breeding females bought | C9: head | D9: =IF(D$3=Models!$H$21,Models!$H$22,0)+IF(D$3=Models!$H$24,Models!$H$25,0) | E9: =IF(E$3=Models!$H$21,Models!$H$22,0)+IF(E$3=Models!$H$24,Models!$H$25,0) | F9: =IF(F$3=Models!$H$21,Models!$H$22,0)+IF(F$3=Models!$H$24,Models!$H$25,0) | G9: =IF(G$3=Models!$H$21,Models!$H$22,0)+IF(G$3=Models!$H$24,Models!$H$25,0) | H9: =IF(H$3=Models!$H$21,Models!$H$22,0)+IF(H$3=Models!$H$24,Models!$H$25,0) | I9: =IF(I$3=Models!$H$21,Models!$H$22,0)+IF(I$3=Models!$H$24,Models!$H$25,0) | J9: =IF(J$3=Models!$H$21,Models!$H$22,0)+IF(J$3=Models!$H$24,Models!$H$25,0) | K9: =IF(K$3=Models!$H$21,Models!$H$22,0)+IF(K$3=Models!$H$24,Models!$H$25,0) | ... DS9: =IF(DS$3=Models!$H$21,Models!$H$22,0)+IF(DS$3=Models!$H$24,Models!$H$25,0)
A10: GT_MBUYT | B10: Breeding males bought in tranches | C10: head | D10: =IF(D$3=Models!$H$21,Models!$H$23,0)+IF(D$3=Models!$H$24,Models!$H$26,0) | E10: =IF(E$3=Models!$H$21,Models!$H$23,0)+IF(E$3=Models!$H$24,Models!$H$26,0) | F10: =IF(F$3=Models!$H$21,Models!$H$23,0)+IF(F$3=Models!$H$24,Models!$H$26,0) | G10: =IF(G$3=Models!$H$21,Models!$H$23,0)+IF(G$3=Models!$H$24,Models!$H$26,0) | H10: =IF(H$3=Models!$H$21,Models!$H$23,0)+IF(H$3=Models!$H$24,Models!$H$26,0) | I10: =IF(I$3=Models!$H$21,Models!$H$23,0)+IF(I$3=Models!$H$24,Models!$H$26,0) | J10: =IF(J$3=Models!$H$21,Models!$H$23,0)+IF(J$3=Models!$H$24,Models!$H$26,0) | K10: =IF(K$3=Models!$H$21,Models!$H$23,0)+IF(K$3=Models!$H$24,Models!$H$26,0) | ... DS10: =IF(DS$3=Models!$H$21,Models!$H$23,0)+IF(DS$3=Models!$H$24,Models!$H$26,0)
A11: GT_FOPEN | B11: Breeding females, opening | C11: head | D11: =0 | E11: =D18 | F11: =E18 | G11: =F18 | H11: =G18 | I11: =H18 | J11: =I18 | K11: =J18 | L11: =K18 | ... DS11: =DR18
A12: GT_FDEATH | B12: Female deaths | C12: head | D12: =D11*MIN(1,Assumptions!$H$73*Sensitivity!$C$8)/12 | E12: =E11*MIN(1,Assumptions!$H$73*Sensitivity!$C$8)/12 | F12: =F11*MIN(1,Assumptions!$H$73*Sensitivity!$C$8)/12 | G12: =G11*MIN(1,Assumptions!$H$73*Sensitivity!$C$8)/12 | H12: =H11*MIN(1,Assumptions!$H$73*Sensitivity!$C$8)/12 | I12: =I11*MIN(1,Assumptions!$H$73*Sensitivity!$C$8)/12 | J12: =J11*MIN(1,Assumptions!$H$73*Sensitivity!$C$8)/12 | K12: =K11*MIN(1,Assumptions!$H$73*Sensitivity!$C$8)/12 | ... DS12: =DS11*MIN(1,Assumptions!$H$73*Sensitivity!$C$8)/12
A13: GT_FCULL | B13: Females culled (sold) | C13: head | D13: =D11*Assumptions!$H$77/12 | E13: =E11*Assumptions!$H$77/12 | F13: =F11*Assumptions!$H$77/12 | G13: =G11*Assumptions!$H$77/12 | H13: =H11*Assumptions!$H$77/12 | I13: =I11*Assumptions!$H$77/12 | J13: =J11*Assumptions!$H$77/12 | K13: =K11*Assumptions!$H$77/12 | ... DS13: =DS11*Assumptions!$H$77/12
A14: GT_BIRTHS | B14: Young born | C14: head | D14: =0 | E14: =0 | F14: =0 | G14: =0 | H14: =0 | I14: =0 | J14: =D18*Assumptions!$H$61/12*Assumptions!$H$65 | K14: =E18*Assumptions!$H$61/12*Assumptions!$H$65 | L14: =F18*Assumptions!$H$61/12*Assumptions!$H$65 | M14: =G18*Assumptions!$H$61/12*Assumptions!$H$65 | N14: =H18*Assumptions!$H$61/12*Assumptions!$H$65 | O14: =I18*Assumptions!$H$61/12*Assumptions!$H$65 | P14: =J18*Assumptions!$H$61/12*Assumptions!$H$65 | Q14: =K18*Assumptions!$H$61/12*Assumptions!$H$65 | ... DS14: =DM18*Assumptions!$H$61/12*Assumptions!$H$65
A15: GT_YSURV | B15: Young surviving to weaning | C15: head | D15: =D14*(1-MIN(1,Assumptions!$H$69*Sensitivity!$C$8)) | E15: =E14*(1-MIN(1,Assumptions!$H$69*Sensitivity!$C$8)) | F15: =F14*(1-MIN(1,Assumptions!$H$69*Sensitivity!$C$8)) | G15: =G14*(1-MIN(1,Assumptions!$H$69*Sensitivity!$C$8)) | H15: =H14*(1-MIN(1,Assumptions!$H$69*Sensitivity!$C$8)) | I15: =I14*(1-MIN(1,Assumptions!$H$69*Sensitivity!$C$8)) | J15: =J14*(1-MIN(1,Assumptions!$H$69*Sensitivity!$C$8)) | K15: =K14*(1-MIN(1,Assumptions!$H$69*Sensitivity!$C$8)) | ... DS15: =DS14*(1-MIN(1,Assumptions!$H$69*Sensitivity!$C$8))
A16: GT_YREACH | B16: Young reaching sale age (9 months) | C16: head | D16: =0 | E16: =0 | F16: =0 | G16: =0 | H16: =0 | I16: =0 | J16: =0 | K16: =0 | L16: =0 | M16: =D15 | N16: =E15 | O16: =F15 | P16: =G15 | Q16: =H15 | R16: =I15 | S16: =J15 | T16: =K15 | ... DS16: =DJ15
A17: GT_RETAINED | B17: Female young kept as replacements | C17: head | D17: =MIN(D16*Assumptions!$H$117*Models!$H$36,MAX(0,Models!$H$27-(D11-D12-D13+D9))) | E17: =MIN(E16*Assumptions!$H$117*Models!$H$36,MAX(0,Models!$H$27-(E11-E12-E13+E9))) | F17: =MIN(F16*Assumptions!$H$117*Models!$H$36,MAX(0,Models!$H$27-(F11-F12-F13+F9))) | G17: =MIN(G16*Assumptions!$H$117*Models!$H$36,MAX(0,Models!$H$27-(G11-G12-G13+G9))) | H17: =MIN(H16*Assumptions!$H$117*Models!$H$36,MAX(0,Models!$H$27-(H11-H12-H13+H9))) | I17: =MIN(I16*Assumptions!$H$117*Models!$H$36,MAX(0,Models!$H$27-(I11-I12-I13+I9))) | J17: =MIN(J16*Assumptions!$H$117*Models!$H$36,MAX(0,Models!$H$27-(J11-J12-J13+J9))) | K17: =MIN(K16*Assumptions!$H$117*Models!$H$36,MAX(0,Models!$H$27-(K11-K12-K13+K9))) | ... DS17: =MIN(DS16*Assumptions!$H$117*Models!$H$36,MAX(0,Models!$H$27-(DS11-DS12-DS13+DS9)))
A18: GT_FCLOSE | B18: Breeding females, closing | C18: head | D18: =D11-D12-D13+D9+D17 | E18: =E11-E12-E13+E9+E17 | F18: =F11-F12-F13+F9+F17 | G18: =G11-G12-G13+G9+G17 | H18: =H11-H12-H13+H9+H17 | I18: =I11-I12-I13+I9+I17 | J18: =J11-J12-J13+J9+J17 | K18: =K11-K12-K13+K9+K17 | ... DS18: =DS11-DS12-DS13+DS9+DS17
A19: GT_YSOLD | B19: Young sold | C19: head | D19: =D16-D17 | E19: =E16-E17 | F19: =F16-F17 | G19: =G16-G17 | H19: =H16-H17 | I19: =I16-I17 | J19: =J16-J17 | K19: =K16-K17 | ... DS19: =DS16-DS17
A20: GT_YHAND | B20: Young on hand | C20: head | D20: =0+D15-D16 | E20: =D20+E15-E16 | F20: =E20+F15-F16 | G20: =F20+G15-G16 | H20: =G20+H15-H16 | I20: =H20+I15-I16 | J20: =I20+J15-J16 | K20: =J20+K15-K16 | L20: =K20+L15-L16 | ... DS20: =DR20+DS15-DS16
A21: GT_MNEED | B21: Breeding males needed | C21: head | D21: =IF(D18>0,ROUNDUP(D18/Assumptions!$H$113,0),0) | E21: =IF(E18>0,ROUNDUP(E18/Assumptions!$H$113,0),0) | F21: =IF(F18>0,ROUNDUP(F18/Assumptions!$H$113,0),0) | G21: =IF(G18>0,ROUNDUP(G18/Assumptions!$H$113,0),0) | H21: =IF(H18>0,ROUNDUP(H18/Assumptions!$H$113,0),0) | I21: =IF(I18>0,ROUNDUP(I18/Assumptions!$H$113,0),0) | J21: =IF(J18>0,ROUNDUP(J18/Assumptions!$H$113,0),0) | K21: =IF(K18>0,ROUNDUP(K18/Assumptions!$H$113,0),0) | ... DS21: =IF(DS18>0,ROUNDUP(DS18/Assumptions!$H$113,0),0)
A22: GT_MALES | B22: Breeding males | C22: head | D22: =MAX(0+D10,D21) | E22: =MAX(D22+E10,E21) | F22: =MAX(E22+F10,F21) | G22: =MAX(F22+G10,G21) | H22: =MAX(G22+H10,H21) | I22: =MAX(H22+I10,I21) | J22: =MAX(I22+J10,J21) | K22: =MAX(J22+K10,K21) | L22: =MAX(K22+L10,L21) | ... DS22: =MAX(DR22+DS10,DS21)
A23: GT_MBUY | B23: Breeding males bought (all) | C23: head | D23: =D22-0 | E23: =E22-D22 | F23: =F22-E22 | G23: =G22-F22 | H23: =H22-G22 | I23: =I22-H22 | J23: =J22-I22 | K23: =K22-J22 | L23: =L22-K22 | ... DS23: =DS22-DR22
A24: GT_HEAD | B24: All animals | C24: head | D24: =D18+D22+D20 | E24: =E18+E22+E20 | F24: =F18+F22+F20 | G24: =G18+G22+G20 | H24: =H18+H22+H20 | I24: =I18+I22+I20 | J24: =J18+J22+J20 | K24: =K18+K22+K20 | ... DS24: =DS18+DS22+DS20
A25: GT_SOLDHD | B25: Animals sold | C25: head | D25: =D19+D13 | E25: =E19+E13 | F25: =F19+F13 | G25: =G19+G13 | H25: =H19+H13 | I25: =I19+I13 | J25: =J19+J13 | K25: =K19+K13 | ... DS25: =DS19+DS13
A26: GT_REV_Y | B26: Sales: young stock | C26: RWF | D26: =D19*Assumptions!$H$81*Assumptions!$H$89*Sensitivity!$C$6*(1+Models!$H$37*Assumptions!$H$101) | E26: =E19*Assumptions!$H$81*Assumptions!$H$89*Sensitivity!$C$6*(1+Models!$H$37*Assumptions!$H$101) | F26: =F19*Assumptions!$H$81*Assumptions!$H$89*Sensitivity!$C$6*(1+Models!$H$37*Assumptions!$H$101) | G26: =G19*Assumptions!$H$81*Assumptions!$H$89*Sensitivity!$C$6*(1+Models!$H$37*Assumptions!$H$101) | H26: =H19*Assumptions!$H$81*Assumptions!$H$89*Sensitivity!$C$6*(1+Models!$H$37*Assumptions!$H$101) | I26: =I19*Assumptions!$H$81*Assumptions!$H$89*Sensitivity!$C$6*(1+Models!$H$37*Assumptions!$H$101) | J26: =J19*Assumptions!$H$81*Assumptions!$H$89*Sensitivity!$C$6*(1+Models!$H$37*Assumptions!$H$101) | K26: =K19*Assumptions!$H$81*Assumptions!$H$89*Sensitivity!$C$6*(1+Models!$H$37*Assumptions!$H$101) | ... DS26: =DS19*Assumptions!$H$81*Assumptions!$H$89*Sensitivity!$C$6*(1+Models!$H$37*Assumptions!$H$101)
A27: GT_REV_C | B27: Sales: culled adults | C27: RWF | D27: =D13*Assumptions!$H$85*Assumptions!$H$89*Sensitivity!$C$6 | E27: =E13*Assumptions!$H$85*Assumptions!$H$89*Sensitivity!$C$6 | F27: =F13*Assumptions!$H$85*Assumptions!$H$89*Sensitivity!$C$6 | G27: =G13*Assumptions!$H$85*Assumptions!$H$89*Sensitivity!$C$6 | H27: =H13*Assumptions!$H$85*Assumptions!$H$89*Sensitivity!$C$6 | I27: =I13*Assumptions!$H$85*Assumptions!$H$89*Sensitivity!$C$6 | J27: =J13*Assumptions!$H$85*Assumptions!$H$89*Sensitivity!$C$6 | K27: =K13*Assumptions!$H$85*Assumptions!$H$89*Sensitivity!$C$6 | ... DS27: =DS13*Assumptions!$H$85*Assumptions!$H$89*Sensitivity!$C$6
A28: GT_BUYCOST | B28: Animal purchases | C28: RWF | D28: =(D9*Assumptions!$H$93+D23*Assumptions!$H$97)*Sensitivity!$C$11 | E28: =(E9*Assumptions!$H$93+E23*Assumptions!$H$97)*Sensitivity!$C$11 | F28: =(F9*Assumptions!$H$93+F23*Assumptions!$H$97)*Sensitivity!$C$11 | G28: =(G9*Assumptions!$H$93+G23*Assumptions!$H$97)*Sensitivity!$C$11 | H28: =(H9*Assumptions!$H$93+H23*Assumptions!$H$97)*Sensitivity!$C$11 | I28: =(I9*Assumptions!$H$93+I23*Assumptions!$H$97)*Sensitivity!$C$11 | J28: =(J9*Assumptions!$H$93+J23*Assumptions!$H$97)*Sensitivity!$C$11 | K28: =(K9*Assumptions!$H$93+K23*Assumptions!$H$97)*Sensitivity!$C$11 | ... DS28: =(DS9*Assumptions!$H$93+DS23*Assumptions!$H$97)*Sensitivity!$C$11
A29: GT_VALUE | B29: Breeding herd value (insurance basis) | C29: RWF | D29: =D18*Assumptions!$H$93+D22*Assumptions!$H$97 | E29: =E18*Assumptions!$H$93+E22*Assumptions!$H$97 | F29: =F18*Assumptions!$H$93+F22*Assumptions!$H$97 | G29: =G18*Assumptions!$H$93+G22*Assumptions!$H$97 | H29: =H18*Assumptions!$H$93+H22*Assumptions!$H$97 | I29: =I18*Assumptions!$H$93+I22*Assumptions!$H$97 | J29: =J18*Assumptions!$H$93+J22*Assumptions!$H$97 | K29: =K18*Assumptions!$H$93+K22*Assumptions!$H$97 | ... DS29: =DS18*Assumptions!$H$93+DS22*Assumptions!$H$97
A30: GT_DEMAND | B30: Feed demand | C30: kg DM | D30: =((D18+D22)*Assumptions!$H$105+D20*Assumptions!$H$109)*30.42 | E30: =((E18+E22)*Assumptions!$H$105+E20*Assumptions!$H$109)*30.42 | F30: =((F18+F22)*Assumptions!$H$105+F20*Assumptions!$H$109)*30.42 | G30: =((G18+G22)*Assumptions!$H$105+G20*Assumptions!$H$109)*30.42 | H30: =((H18+H22)*Assumptions!$H$105+H20*Assumptions!$H$109)*30.42 | I30: =((I18+I22)*Assumptions!$H$105+I20*Assumptions!$H$109)*30.42 | J30: =((J18+J22)*Assumptions!$H$105+J20*Assumptions!$H$109)*30.42 | K30: =((K18+K22)*Assumptions!$H$105+K20*Assumptions!$H$109)*30.42 | ... DS30: =((DS18+DS22)*Assumptions!$H$105+DS20*Assumptions!$H$109)*30.42
B32: Sheep
A33: SH_FBUY | B33: Breeding females bought | C33: head | D33: =IF(D$3=Models!$H$28,Models!$H$29,0)+IF(D$3=Models!$H$31,Models!$H$32,0) | E33: =IF(E$3=Models!$H$28,Models!$H$29,0)+IF(E$3=Models!$H$31,Models!$H$32,0) | F33: =IF(F$3=Models!$H$28,Models!$H$29,0)+IF(F$3=Models!$H$31,Models!$H$32,0) | G33: =IF(G$3=Models!$H$28,Models!$H$29,0)+IF(G$3=Models!$H$31,Models!$H$32,0) | H33: =IF(H$3=Models!$H$28,Models!$H$29,0)+IF(H$3=Models!$H$31,Models!$H$32,0) | I33: =IF(I$3=Models!$H$28,Models!$H$29,0)+IF(I$3=Models!$H$31,Models!$H$32,0) | J33: =IF(J$3=Models!$H$28,Models!$H$29,0)+IF(J$3=Models!$H$31,Models!$H$32,0) | K33: =IF(K$3=Models!$H$28,Models!$H$29,0)+IF(K$3=Models!$H$31,Models!$H$32,0) | ... DS33: =IF(DS$3=Models!$H$28,Models!$H$29,0)+IF(DS$3=Models!$H$31,Models!$H$32,0)
A34: SH_MBUYT | B34: Breeding males bought in tranches | C34: head | D34: =IF(D$3=Models!$H$28,Models!$H$30,0)+IF(D$3=Models!$H$31,Models!$H$33,0) | E34: =IF(E$3=Models!$H$28,Models!$H$30,0)+IF(E$3=Models!$H$31,Models!$H$33,0) | F34: =IF(F$3=Models!$H$28,Models!$H$30,0)+IF(F$3=Models!$H$31,Models!$H$33,0) | G34: =IF(G$3=Models!$H$28,Models!$H$30,0)+IF(G$3=Models!$H$31,Models!$H$33,0) | H34: =IF(H$3=Models!$H$28,Models!$H$30,0)+IF(H$3=Models!$H$31,Models!$H$33,0) | I34: =IF(I$3=Models!$H$28,Models!$H$30,0)+IF(I$3=Models!$H$31,Models!$H$33,0) | J34: =IF(J$3=Models!$H$28,Models!$H$30,0)+IF(J$3=Models!$H$31,Models!$H$33,0) | K34: =IF(K$3=Models!$H$28,Models!$H$30,0)+IF(K$3=Models!$H$31,Models!$H$33,0) | ... DS34: =IF(DS$3=Models!$H$28,Models!$H$30,0)+IF(DS$3=Models!$H$31,Models!$H$33,0)
A35: SH_FOPEN | B35: Breeding females, opening | C35: head | D35: =0 | E35: =D42 | F35: =E42 | G35: =F42 | H35: =G42 | I35: =H42 | J35: =I42 | K35: =J42 | L35: =K42 | ... DS35: =DR42
A36: SH_FDEATH | B36: Female deaths | C36: head | D36: =D35*MIN(1,Assumptions!$H$75*Sensitivity!$C$8)/12 | E36: =E35*MIN(1,Assumptions!$H$75*Sensitivity!$C$8)/12 | F36: =F35*MIN(1,Assumptions!$H$75*Sensitivity!$C$8)/12 | G36: =G35*MIN(1,Assumptions!$H$75*Sensitivity!$C$8)/12 | H36: =H35*MIN(1,Assumptions!$H$75*Sensitivity!$C$8)/12 | I36: =I35*MIN(1,Assumptions!$H$75*Sensitivity!$C$8)/12 | J36: =J35*MIN(1,Assumptions!$H$75*Sensitivity!$C$8)/12 | K36: =K35*MIN(1,Assumptions!$H$75*Sensitivity!$C$8)/12 | ... DS36: =DS35*MIN(1,Assumptions!$H$75*Sensitivity!$C$8)/12
A37: SH_FCULL | B37: Females culled (sold) | C37: head | D37: =D35*Assumptions!$H$79/12 | E37: =E35*Assumptions!$H$79/12 | F37: =F35*Assumptions!$H$79/12 | G37: =G35*Assumptions!$H$79/12 | H37: =H35*Assumptions!$H$79/12 | I37: =I35*Assumptions!$H$79/12 | J37: =J35*Assumptions!$H$79/12 | K37: =K35*Assumptions!$H$79/12 | ... DS37: =DS35*Assumptions!$H$79/12
A38: SH_BIRTHS | B38: Young born | C38: head | D38: =0 | E38: =0 | F38: =0 | G38: =0 | H38: =0 | I38: =0 | J38: =D42*Assumptions!$H$63/12*Assumptions!$H$67 | K38: =E42*Assumptions!$H$63/12*Assumptions!$H$67 | L38: =F42*Assumptions!$H$63/12*Assumptions!$H$67 | M38: =G42*Assumptions!$H$63/12*Assumptions!$H$67 | N38: =H42*Assumptions!$H$63/12*Assumptions!$H$67 | O38: =I42*Assumptions!$H$63/12*Assumptions!$H$67 | P38: =J42*Assumptions!$H$63/12*Assumptions!$H$67 | Q38: =K42*Assumptions!$H$63/12*Assumptions!$H$67 | ... DS38: =DM42*Assumptions!$H$63/12*Assumptions!$H$67
A39: SH_YSURV | B39: Young surviving to weaning | C39: head | D39: =D38*(1-MIN(1,Assumptions!$H$71*Sensitivity!$C$8)) | E39: =E38*(1-MIN(1,Assumptions!$H$71*Sensitivity!$C$8)) | F39: =F38*(1-MIN(1,Assumptions!$H$71*Sensitivity!$C$8)) | G39: =G38*(1-MIN(1,Assumptions!$H$71*Sensitivity!$C$8)) | H39: =H38*(1-MIN(1,Assumptions!$H$71*Sensitivity!$C$8)) | I39: =I38*(1-MIN(1,Assumptions!$H$71*Sensitivity!$C$8)) | J39: =J38*(1-MIN(1,Assumptions!$H$71*Sensitivity!$C$8)) | K39: =K38*(1-MIN(1,Assumptions!$H$71*Sensitivity!$C$8)) | ... DS39: =DS38*(1-MIN(1,Assumptions!$H$71*Sensitivity!$C$8))
A40: SH_YREACH | B40: Young reaching sale age (9 months) | C40: head | D40: =0 | E40: =0 | F40: =0 | G40: =0 | H40: =0 | I40: =0 | J40: =0 | K40: =0 | L40: =0 | M40: =D39 | N40: =E39 | O40: =F39 | P40: =G39 | Q40: =H39 | R40: =I39 | S40: =J39 | T40: =K39 | ... DS40: =DJ39
A41: SH_RETAINED | B41: Female young kept as replacements | C41: head | D41: =MIN(D40*Assumptions!$H$119*Models!$H$36,MAX(0,Models!$H$34-(D35-D36-D37+D33))) | E41: =MIN(E40*Assumptions!$H$119*Models!$H$36,MAX(0,Models!$H$34-(E35-E36-E37+E33))) | F41: =MIN(F40*Assumptions!$H$119*Models!$H$36,MAX(0,Models!$H$34-(F35-F36-F37+F33))) | G41: =MIN(G40*Assumptions!$H$119*Models!$H$36,MAX(0,Models!$H$34-(G35-G36-G37+G33))) | H41: =MIN(H40*Assumptions!$H$119*Models!$H$36,MAX(0,Models!$H$34-(H35-H36-H37+H33))) | I41: =MIN(I40*Assumptions!$H$119*Models!$H$36,MAX(0,Models!$H$34-(I35-I36-I37+I33))) | J41: =MIN(J40*Assumptions!$H$119*Models!$H$36,MAX(0,Models!$H$34-(J35-J36-J37+J33))) | K41: =MIN(K40*Assumptions!$H$119*Models!$H$36,MAX(0,Models!$H$34-(K35-K36-K37+K33))) | ... DS41: =MIN(DS40*Assumptions!$H$119*Models!$H$36,MAX(0,Models!$H$34-(DS35-DS36-DS37+DS33)))
A42: SH_FCLOSE | B42: Breeding females, closing | C42: head | D42: =D35-D36-D37+D33+D41 | E42: =E35-E36-E37+E33+E41 | F42: =F35-F36-F37+F33+F41 | G42: =G35-G36-G37+G33+G41 | H42: =H35-H36-H37+H33+H41 | I42: =I35-I36-I37+I33+I41 | J42: =J35-J36-J37+J33+J41 | K42: =K35-K36-K37+K33+K41 | ... DS42: =DS35-DS36-DS37+DS33+DS41
A43: SH_YSOLD | B43: Young sold | C43: head | D43: =D40-D41 | E43: =E40-E41 | F43: =F40-F41 | G43: =G40-G41 | H43: =H40-H41 | I43: =I40-I41 | J43: =J40-J41 | K43: =K40-K41 | ... DS43: =DS40-DS41
A44: SH_YHAND | B44: Young on hand | C44: head | D44: =0+D39-D40 | E44: =D44+E39-E40 | F44: =E44+F39-F40 | G44: =F44+G39-G40 | H44: =G44+H39-H40 | I44: =H44+I39-I40 | J44: =I44+J39-J40 | K44: =J44+K39-K40 | L44: =K44+L39-L40 | ... DS44: =DR44+DS39-DS40
A45: SH_MNEED | B45: Breeding males needed | C45: head | D45: =IF(D42>0,ROUNDUP(D42/Assumptions!$H$115,0),0) | E45: =IF(E42>0,ROUNDUP(E42/Assumptions!$H$115,0),0) | F45: =IF(F42>0,ROUNDUP(F42/Assumptions!$H$115,0),0) | G45: =IF(G42>0,ROUNDUP(G42/Assumptions!$H$115,0),0) | H45: =IF(H42>0,ROUNDUP(H42/Assumptions!$H$115,0),0) | I45: =IF(I42>0,ROUNDUP(I42/Assumptions!$H$115,0),0) | J45: =IF(J42>0,ROUNDUP(J42/Assumptions!$H$115,0),0) | K45: =IF(K42>0,ROUNDUP(K42/Assumptions!$H$115,0),0) | ... DS45: =IF(DS42>0,ROUNDUP(DS42/Assumptions!$H$115,0),0)
A46: SH_MALES | B46: Breeding males | C46: head | D46: =MAX(0+D34,D45) | E46: =MAX(D46+E34,E45) | F46: =MAX(E46+F34,F45) | G46: =MAX(F46+G34,G45) | H46: =MAX(G46+H34,H45) | I46: =MAX(H46+I34,I45) | J46: =MAX(I46+J34,J45) | K46: =MAX(J46+K34,K45) | L46: =MAX(K46+L34,L45) | ... DS46: =MAX(DR46+DS34,DS45)
A47: SH_MBUY | B47: Breeding males bought (all) | C47: head | D47: =D46-0 | E47: =E46-D46 | F47: =F46-E46 | G47: =G46-F46 | H47: =H46-G46 | I47: =I46-H46 | J47: =J46-I46 | K47: =K46-J46 | L47: =L46-K46 | ... DS47: =DS46-DR46
A48: SH_HEAD | B48: All animals | C48: head | D48: =D42+D46+D44 | E48: =E42+E46+E44 | F48: =F42+F46+F44 | G48: =G42+G46+G44 | H48: =H42+H46+H44 | I48: =I42+I46+I44 | J48: =J42+J46+J44 | K48: =K42+K46+K44 | ... DS48: =DS42+DS46+DS44
A49: SH_SOLDHD | B49: Animals sold | C49: head | D49: =D43+D37 | E49: =E43+E37 | F49: =F43+F37 | G49: =G43+G37 | H49: =H43+H37 | I49: =I43+I37 | J49: =J43+J37 | K49: =K43+K37 | ... DS49: =DS43+DS37
A50: SH_REV_Y | B50: Sales: young stock | C50: RWF | D50: =D43*Assumptions!$H$83*Assumptions!$H$91*Sensitivity!$C$6*(1+Models!$H$37*Assumptions!$H$103) | E50: =E43*Assumptions!$H$83*Assumptions!$H$91*Sensitivity!$C$6*(1+Models!$H$37*Assumptions!$H$103) | F50: =F43*Assumptions!$H$83*Assumptions!$H$91*Sensitivity!$C$6*(1+Models!$H$37*Assumptions!$H$103) | G50: =G43*Assumptions!$H$83*Assumptions!$H$91*Sensitivity!$C$6*(1+Models!$H$37*Assumptions!$H$103) | H50: =H43*Assumptions!$H$83*Assumptions!$H$91*Sensitivity!$C$6*(1+Models!$H$37*Assumptions!$H$103) | I50: =I43*Assumptions!$H$83*Assumptions!$H$91*Sensitivity!$C$6*(1+Models!$H$37*Assumptions!$H$103) | J50: =J43*Assumptions!$H$83*Assumptions!$H$91*Sensitivity!$C$6*(1+Models!$H$37*Assumptions!$H$103) | K50: =K43*Assumptions!$H$83*Assumptions!$H$91*Sensitivity!$C$6*(1+Models!$H$37*Assumptions!$H$103) | ... DS50: =DS43*Assumptions!$H$83*Assumptions!$H$91*Sensitivity!$C$6*(1+Models!$H$37*Assumptions!$H$103)
A51: SH_REV_C | B51: Sales: culled adults | C51: RWF | D51: =D37*Assumptions!$H$87*Assumptions!$H$91*Sensitivity!$C$6 | E51: =E37*Assumptions!$H$87*Assumptions!$H$91*Sensitivity!$C$6 | F51: =F37*Assumptions!$H$87*Assumptions!$H$91*Sensitivity!$C$6 | G51: =G37*Assumptions!$H$87*Assumptions!$H$91*Sensitivity!$C$6 | H51: =H37*Assumptions!$H$87*Assumptions!$H$91*Sensitivity!$C$6 | I51: =I37*Assumptions!$H$87*Assumptions!$H$91*Sensitivity!$C$6 | J51: =J37*Assumptions!$H$87*Assumptions!$H$91*Sensitivity!$C$6 | K51: =K37*Assumptions!$H$87*Assumptions!$H$91*Sensitivity!$C$6 | ... DS51: =DS37*Assumptions!$H$87*Assumptions!$H$91*Sensitivity!$C$6
A52: SH_BUYCOST | B52: Animal purchases | C52: RWF | D52: =(D33*Assumptions!$H$95+D47*Assumptions!$H$99)*Sensitivity!$C$11 | E52: =(E33*Assumptions!$H$95+E47*Assumptions!$H$99)*Sensitivity!$C$11 | F52: =(F33*Assumptions!$H$95+F47*Assumptions!$H$99)*Sensitivity!$C$11 | G52: =(G33*Assumptions!$H$95+G47*Assumptions!$H$99)*Sensitivity!$C$11 | H52: =(H33*Assumptions!$H$95+H47*Assumptions!$H$99)*Sensitivity!$C$11 | I52: =(I33*Assumptions!$H$95+I47*Assumptions!$H$99)*Sensitivity!$C$11 | J52: =(J33*Assumptions!$H$95+J47*Assumptions!$H$99)*Sensitivity!$C$11 | K52: =(K33*Assumptions!$H$95+K47*Assumptions!$H$99)*Sensitivity!$C$11 | ... DS52: =(DS33*Assumptions!$H$95+DS47*Assumptions!$H$99)*Sensitivity!$C$11
A53: SH_VALUE | B53: Breeding herd value (insurance basis) | C53: RWF | D53: =D42*Assumptions!$H$95+D46*Assumptions!$H$99 | E53: =E42*Assumptions!$H$95+E46*Assumptions!$H$99 | F53: =F42*Assumptions!$H$95+F46*Assumptions!$H$99 | G53: =G42*Assumptions!$H$95+G46*Assumptions!$H$99 | H53: =H42*Assumptions!$H$95+H46*Assumptions!$H$99 | I53: =I42*Assumptions!$H$95+I46*Assumptions!$H$99 | J53: =J42*Assumptions!$H$95+J46*Assumptions!$H$99 | K53: =K42*Assumptions!$H$95+K46*Assumptions!$H$99 | ... DS53: =DS42*Assumptions!$H$95+DS46*Assumptions!$H$99
A54: SH_DEMAND | B54: Feed demand | C54: kg DM | D54: =((D42+D46)*Assumptions!$H$107+D44*Assumptions!$H$111)*30.42 | E54: =((E42+E46)*Assumptions!$H$107+E44*Assumptions!$H$111)*30.42 | F54: =((F42+F46)*Assumptions!$H$107+F44*Assumptions!$H$111)*30.42 | G54: =((G42+G46)*Assumptions!$H$107+G44*Assumptions!$H$111)*30.42 | H54: =((H42+H46)*Assumptions!$H$107+H44*Assumptions!$H$111)*30.42 | I54: =((I42+I46)*Assumptions!$H$107+I44*Assumptions!$H$111)*30.42 | J54: =((J42+J46)*Assumptions!$H$107+J44*Assumptions!$H$111)*30.42 | K54: =((K42+K46)*Assumptions!$H$107+K44*Assumptions!$H$111)*30.42 | ... DS54: =((DS42+DS46)*Assumptions!$H$107+DS44*Assumptions!$H$111)*30.42

Sheet Feed
A1: Feed
A2: Monthly dry-matter balance: forage grown, conserved and bought.
B3: Month | D3: 1 | E3: 2 | F3: 3 | G3: 4 | H3: 5 | I3: 6 | J3: 7 | K3: 8 | L3: 9 | M3: 10 | N3: 11 | O3: 12 | P3: 13 | Q3: 14 | R3: 15 | S3: 16 | T3: 17 | U3: 18 | V3: 19 | W3: 20 | X3: 21 | Y3: 22 | Z3: 23 | AA3: 24 | AB3: 25 | AC3: 26 | AD3: 27 | AE3: 28 | AF3: 29 | AG3: 30 | AH3: 31 | AI3: 32 | AJ3: 33 | AK3: 34 | AL3: 35 | AM3: 36 | AN3: 37 | AO3: 38 | AP3: 39 | AQ3: 40 | AR3: 41 | AS3: 42 | AT3: 43 | AU3: 44 | AV3: 45 | AW3: 46 | AX3: 47 | AY3: 48 | AZ3: 49 | BA3: 50 | BB3: 51 | BC3: 52 | BD3: 53 | BE3: 54 | BF3: 55 | BG3: 56 | BH3: 57 | BI3: 58 | BJ3: 59 | BK3: 60 | BL3: 61 | BM3: 62 | BN3: 63 | BO3: 64 | BP3: 65 | BQ3: 66 | BR3: 67 | BS3: 68 | BT3: 69 | BU3: 70 | BV3: 71 | BW3: 72 | BX3: 73 | BY3: 74 | BZ3: 75 | CA3: 76 | CB3: 77 | CC3: 78 | CD3: 79 | CE3: 80 | CF3: 81 | CG3: 82 | CH3: 83 | CI3: 84 | CJ3: 85 | CK3: 86 | CL3: 87 | CM3: 88 | CN3: 89 | CO3: 90 | CP3: 91 | CQ3: 92 | CR3: 93 | CS3: 94 | CT3: 95 | CU3: 96 | CV3: 97 | CW3: 98 | CX3: 99 | CY3: 100 | CZ3: 101 | DA3: 102 | DB3: 103 | DC3: 104 | DD3: 105 | DE3: 106 | DF3: 107 | DG3: 108 | DH3: 109 | DI3: 110 | DJ3: 111 | DK3: 112 | DL3: 113 | DM3: 114 | DN3: 115 | DO3: 116 | DP3: 117 | DQ3: 118 | DR3: 119 | DS3: 120
B4: Farm year | D4: =INT((D$3-1)/12)+1 | E4: =INT((E$3-1)/12)+1 | F4: =INT((F$3-1)/12)+1 | G4: =INT((G$3-1)/12)+1 | H4: =INT((H$3-1)/12)+1 | I4: =INT((I$3-1)/12)+1 | J4: =INT((J$3-1)/12)+1 | K4: =INT((K$3-1)/12)+1 | ... DS4: =INT((DS$3-1)/12)+1
B5: Calendar month | D5: =MOD(Control!$C$10+D$3-2,12)+1 | E5: =MOD(Control!$C$10+E$3-2,12)+1 | F5: =MOD(Control!$C$10+F$3-2,12)+1 | G5: =MOD(Control!$C$10+G$3-2,12)+1 | H5: =MOD(Control!$C$10+H$3-2,12)+1 | I5: =MOD(Control!$C$10+I$3-2,12)+1 | J5: =MOD(Control!$C$10+J$3-2,12)+1 | K5: =MOD(Control!$C$10+K$3-2,12)+1 | ... DS5: =MOD(Control!$C$10+DS$3-2,12)+1
B6: Month starting | D6: =DATE(Control!$C$9+INT((Control!$C$10+D$3-2)/12),D$5,1) | E6: =DATE(Control!$C$9+INT((Control!$C$10+E$3-2)/12),E$5,1) | F6: =DATE(Control!$C$9+INT((Control!$C$10+F$3-2)/12),F$5,1) | G6: =DATE(Control!$C$9+INT((Control!$C$10+G$3-2)/12),G$5,1) | H6: =DATE(Control!$C$9+INT((Control!$C$10+H$3-2)/12),H$5,1) | I6: =DATE(Control!$C$9+INT((Control!$C$10+I$3-2)/12),I$5,1) | J6: =DATE(Control!$C$9+INT((Control!$C$10+J$3-2)/12),J$5,1) | K6: =DATE(Control!$C$9+INT((Control!$C$10+K$3-2)/12),K$5,1) | ... DS6: =DATE(Control!$C$9+INT((Control!$C$10+DS$3-2)/12),DS$5,1)
A8: FD_DEMAND | B8: Feed demand (all animals) | C8: kg DM | D8: =Livestock!D30+Livestock!D54 | E8: =Livestock!E30+Livestock!E54 | F8: =Livestock!F30+Livestock!F54 | G8: =Livestock!G30+Livestock!G54 | H8: =Livestock!H30+Livestock!H54 | I8: =Livestock!I30+Livestock!I54 | J8: =Livestock!J30+Livestock!J54 | K8: =Livestock!K30+Livestock!K54 | ... DS8: =Livestock!DS30+Livestock!DS54
A9: FD_READY | B9: Forage established (1 = yes) | C9: flag | D9: =IF(D$3>=Control!$C$12+Assumptions!$H$59,1,0) | E9: =IF(E$3>=Control!$C$12+Assumptions!$H$59,1,0) | F9: =IF(F$3>=Control!$C$12+Assumptions!$H$59,1,0) | G9: =IF(G$3>=Control!$C$12+Assumptions!$H$59,1,0) | H9: =IF(H$3>=Control!$C$12+Assumptions!$H$59,1,0) | I9: =IF(I$3>=Control!$C$12+Assumptions!$H$59,1,0) | J9: =IF(J$3>=Control!$C$12+Assumptions!$H$59,1,0) | K9: =IF(K$3>=Control!$C$12+Assumptions!$H$59,1,0) | ... DS9: =IF(DS$3>=Control!$C$12+Assumptions!$H$59,1,0)
A10: FD_SUPPLY | B10: Forage available to animals | C10: kg DM | D10: =(Land!$C$12*Assumptions!$H$52*1000*Assumptions!$H$54+Land!$C$13*Assumptions!$H$53*1000*Assumptions!$H$55)/12*INDEX(Curves!$D$25:$O$25,1,D$5)*D9 | E10: =(Land!$C$12*Assumptions!$H$52*1000*Assumptions!$H$54+Land!$C$13*Assumptions!$H$53*1000*Assumptions!$H$55)/12*INDEX(Curves!$D$25:$O$25,1,E$5)*E9 | F10: =(Land!$C$12*Assumptions!$H$52*1000*Assumptions!$H$54+Land!$C$13*Assumptions!$H$53*1000*Assumptions!$H$55)/12*INDEX(Curves!$D$25:$O$25,1,F$5)*F9 | G10: =(Land!$C$12*Assumptions!$H$52*1000*Assumptions!$H$54+Land!$C$13*Assumptions!$H$53*1000*Assumptions!$H$55)/12*INDEX(Curves!$D$25:$O$25,1,G$5)*G9 | H10: =(Land!$C$12*Assumptions!$H$52*1000*Assumptions!$H$54+Land!$C$13*Assumptions!$H$53*1000*Assumptions!$H$55)/12*INDEX(Curves!$D$25:$O$25,1,H$5)*H9 | I10: =(Land!$C$12*Assumptions!$H$52*1000*Assumptions!$H$54+Land!$C$13*Assumptions!$H$53*1000*Assumptions!$H$55)/12*INDEX(Curves!$D$25:$O$25,1,I$5)*I9 | J10: =(Land!$C$12*Assumptions!$H$52*1000*Assumptions!$H$54+Land!$C$13*Assumptions!$H$53*1000*Assumptions!$H$55)/12*INDEX(Curves!$D$25:$O$25,1,J$5)*J9 | K10: =(Land!$C$12*Assumptions!$H$52*1000*Assumptions!$H$54+Land!$C$13*Assumptions!$H$53*1000*Assumptions!$H$55)/12*INDEX(Curves!$D$25:$O$25,1,K$5)*K9 | ... DS10: =(Land!$C$12*Assumptions!$H$52*1000*Assumptions!$H$54+Land!$C$13*Assumptions!$H$53*1000*Assumptions!$H$55)/12*INDEX(Curves!$D$25:$O$25,1,DS$5)*DS9
A11: FD_SURPLUS | B11: Surplus forage | C11: kg DM | D11: =MAX(0,D10-D8) | E11: =MAX(0,E10-E8) | F11: =MAX(0,F10-F8) | G11: =MAX(0,G10-G8) | H11: =MAX(0,H10-H8) | I11: =MAX(0,I10-I8) | J11: =MAX(0,J10-J8) | K11: =MAX(0,K10-K8) | ... DS11: =MAX(0,DS10-DS8)
A12: FD_DEFICIT | B12: Forage deficit | C12: kg DM | D12: =MAX(0,D8-D10) | E12: =MAX(0,E8-E10) | F12: =MAX(0,F8-F10) | G12: =MAX(0,G8-G10) | H12: =MAX(0,H8-H10) | I12: =MAX(0,I8-I10) | J12: =MAX(0,J8-J10) | K12: =MAX(0,K8-K10) | ... DS12: =MAX(0,DS8-DS10)
A13: FD_CONS | B13: Conserved as hay/silage | C13: kg DM | D13: =D11*Models!$H$38*Assumptions!$H$56 | E13: =E11*Models!$H$38*Assumptions!$H$56 | F13: =F11*Models!$H$38*Assumptions!$H$56 | G13: =G11*Models!$H$38*Assumptions!$H$56 | H13: =H11*Models!$H$38*Assumptions!$H$56 | I13: =I11*Models!$H$38*Assumptions!$H$56 | J13: =J11*Models!$H$38*Assumptions!$H$56 | K13: =K11*Models!$H$38*Assumptions!$H$56 | ... DS13: =DS11*Models!$H$38*Assumptions!$H$56
A14: FD_AVAIL | B14: Conserved feed available | C14: kg DM | D14: =0+D13 | E14: =D16+E13 | F14: =E16+F13 | G14: =F16+G13 | H14: =G16+H13 | I14: =H16+I13 | J14: =I16+J13 | K14: =J16+K13 | L14: =K16+L13 | ... DS14: =DR16+DS13
A15: FD_DRAWN | B15: Conserved feed used | C15: kg DM | D15: =MIN(D14,D12) | E15: =MIN(E14,E12) | F15: =MIN(F14,F12) | G15: =MIN(G14,G12) | H15: =MIN(H14,H12) | I15: =MIN(I14,I12) | J15: =MIN(J14,J12) | K15: =MIN(K14,K12) | ... DS15: =MIN(DS14,DS12)
A16: FD_STORE | B16: Conserved feed in store, closing | C16: kg DM | D16: =D14-D15 | E16: =E14-E15 | F16: =F14-F15 | G16: =G14-G15 | H16: =H14-H15 | I16: =I14-I15 | J16: =J14-J15 | K16: =K14-K15 | ... DS16: =DS14-DS15
A17: FD_BUY | B17: Feed bought | C17: kg DM | D17: =D12-D15 | E17: =E12-E15 | F17: =F12-F15 | G17: =G12-G15 | H17: =H12-H15 | I17: =I12-I15 | J17: =J12-J15 | K17: =K12-K15 | ... DS17: =DS12-DS15
A18: FD_BUYCOST | B18: Feed bought | C18: RWF | D18: =D17*Assumptions!$H$58*Sensitivity!$C$9 | E18: =E17*Assumptions!$H$58*Sensitivity!$C$9 | F18: =F17*Assumptions!$H$58*Sensitivity!$C$9 | G18: =G17*Assumptions!$H$58*Sensitivity!$C$9 | H18: =H17*Assumptions!$H$58*Sensitivity!$C$9 | I18: =I17*Assumptions!$H$58*Sensitivity!$C$9 | J18: =J17*Assumptions!$H$58*Sensitivity!$C$9 | K18: =K17*Assumptions!$H$58*Sensitivity!$C$9 | ... DS18: =DS17*Assumptions!$H$58*Sensitivity!$C$9
A19: FD_CONSCOST | B19: Conservation cost | C19: RWF | D19: =D13*Assumptions!$H$57 | E19: =E13*Assumptions!$H$57 | F19: =F13*Assumptions!$H$57 | G19: =G13*Assumptions!$H$57 | H19: =H13*Assumptions!$H$57 | I19: =I13*Assumptions!$H$57 | J19: =J13*Assumptions!$H$57 | K19: =K13*Assumptions!$H$57 | ... DS19: =DS13*Assumptions!$H$57

Sheet CapEx
A1: CapEx
A2: Capital items for the selected model. Contingency is added on top. Animal purchases are on Livestock.
A4: ID | B4: Item | C4: Category | D4: Essential / optional | E4: Quantity | F4: Unit | G4: Unit cost (RWF) | H4: Total (RWF) | I4: Month incurred | J4: Year incurred | K4: Life (yrs) | L4: Depreciation per yr (RWF)
A5: CX01 | B5: Soil tests | C5: Studies | D5: Essential | E5: =Models!$H$42 | F5: samples | G5: =Assumptions!$H$31 | H5: =E5*G5*Sensitivity!$C$11 | I5: =1 | J5: =INT((I5-1)/12)+1 | K5: 5 | L5: =IF(K5>0,H5/K5,0)
A6: CX02 | B6: Water tests | C6: Studies | D6: Essential | E6: =Models!$H$43 | F6: samples | G6: =Assumptions!$H$32 | H6: =E6*G6*Sensitivity!$C$11 | I6: =1 | J6: =INT((I6-1)/12)+1 | K6: 5 | L6: =IF(K6>0,H6/K6,0)
A7: CX03 | B7: Survey, title and legal checks | C7: Studies | D7: Essential | E7: =1 | F7: lump | G7: =Assumptions!$H$33 | H7: =E7*G7*Sensitivity!$C$11 | I7: =1 | J7: =INT((I7-1)/12)+1 | K7: 10 | L7: =IF(K7>0,H7/K7,0)
A8: CX04 | B8: Permits and compliance | C8: Studies | D8: Essential | E8: =1 | F8: lump | G8: =Assumptions!$H$34 | H8: =E8*G8*Sensitivity!$C$11 | I8: =2 | J8: =INT((I8-1)/12)+1 | K8: 10 | L8: =IF(K8>0,H8/K8,0)
A9: CX05 | B9: Professional set-up visits | C9: Studies | D9: Essential | E9: =1 | F9: lump | G9: =Assumptions!$H$35 | H9: =E9*G9*Sensitivity!$C$11 | I9: =2 | J9: =INT((I9-1)/12)+1 | K9: 5 | L9: =IF(K9>0,H9/K9,0)
A10: CX06 | B10: Perimeter fence | C10: Fencing | D10: Essential | E10: =Land!$C$6 | F10: m | G10: =Assumptions!$H$18 | H10: =E10*G10*Sensitivity!$C$11 | I10: =3 | J10: =INT((I10-1)/12)+1 | K10: 10 | L10: =IF(K10>0,H10/K10,0)
A11: CX07 | B11: Internal paddock fence | C11: Fencing | D11: Essential | E11: =Land!$C$9*Models!$H$44 | F11: m | G11: =Assumptions!$H$19 | H11: =E11*G11*Sensitivity!$C$11 | I11: =MAX(1,Models!$H$21-2) | J11: =INT((I11-1)/12)+1 | K11: 8 | L11: =IF(K11>0,H11/K11,0)
A12: CX08 | B12: Gates | C12: Fencing | D12: Essential | E12: =Models!$H$45 | F12: count | G12: =Assumptions!$H$20 | H12: =E12*G12*Sensitivity!$C$11 | I12: =3 | J12: =INT((I12-1)/12)+1 | K12: 10 | L12: =IF(K12>0,H12/K12,0)
A13: CX09 | B13: Water storage | C13: Water | D13: Essential | E13: =Models!$H$46 | F13: m3 | G13: =Assumptions!$H$21 | H13: =E13*G13*Sensitivity!$C$11 | I13: =3 | J13: =INT((I13-1)/12)+1 | K13: 15 | L13: =IF(K13>0,H13/K13,0)
A14: CX10 | B14: Rainwater harvesting fittings | C14: Water | D14: Essential | E14: =1 | F14: lump | G14: =Assumptions!$H$22 | H14: =E14*G14*Sensitivity!$C$11 | I14: =3 | J14: =INT((I14-1)/12)+1 | K14: 10 | L14: =IF(K14>0,H14/K14,0)
A15: CX11 | B15: Borehole | C15: Water | D15: Optional | E15: =Models!$H$47 | F15: flag | G15: =Assumptions!$H$23 | H15: =E15*G15*Sensitivity!$C$11 | I15: =4 | J15: =INT((I15-1)/12)+1 | K15: 20 | L15: =IF(K15>0,H15/K15,0)
A16: CX12 | B16: Solar pump system | C16: Water | D16: Optional | E16: =Models!$H$48 | F16: flag | G16: =Assumptions!$H$24 | H16: =E16*G16*Sensitivity!$C$11 | I16: =4 | J16: =INT((I16-1)/12)+1 | K16: 10 | L16: =IF(K16>0,H16/K16,0)
A17: CX13 | B17: Drip irrigation on the orchard | C17: Water | D17: Optional | E17: =Land!$C$8*Models!$H$49 | F17: ha | G17: =Assumptions!$H$25 | H17: =E17*G17*Sensitivity!$C$11 | I17: =MAX(1,Control!$C$11-1) | J17: =INT((I17-1)/12)+1 | K17: 8 | L17: =IF(K17>0,H17/K17,0)
A18: CX14 | B18: Orchard establishment (plants and planting) | C18: Orchard | D18: Essential | E18: =1 | F18: lump | G18: =Trees!$C$97 | H18: =E18*G18 | I18: =Control!$C$11 | J18: =INT((I18-1)/12)+1 | K18: 20 | L18: =IF(K18>0,H18/K18,0)
A19: CX15 | B19: Orchard gap filling | C19: Orchard | D19: Essential | E19: =1 | F19: lump | G19: =Trees!$C$98 | H19: =E19*G19 | I19: =Control!$C$11+12 | J19: =INT((I19-1)/12)+1 | K19: 20 | L19: =IF(K19>0,H19/K19,0)
A20: CX16 | B20: Boundary trees | C20: Orchard | D20: Essential | E20: =1 | F20: lump | G20: =Trees!$C$92 | H20: =E20*G20 | I20: =Control!$C$11 | J20: =INT((I20-1)/12)+1 | K20: 20 | L20: =IF(K20>0,H20/K20,0)
A21: CX17 | B21: Pasture establishment | C21: Feed | D21: Essential | E21: =Land!$C$12 | F21: ha | G21: =Assumptions!$H$26 | H21: =E21*G21*Sensitivity!$C$11 | I21: =Control!$C$12 | J21: =INT((I21-1)/12)+1 | K21: 5 | L21: =IF(K21>0,H21/K21,0)
A22: CX18 | B22: Fodder bank establishment | C22: Feed | D22: Essential | E22: =Land!$C$13 | F22: ha | G22: =Assumptions!$H$27 | H22: =E22*G22*Sensitivity!$C$11 | I22: =Control!$C$12 | J22: =INT((I22-1)/12)+1 | K22: 5 | L22: =IF(K22>0,H22/K22,0)
A23: CX19 | B23: Animal house | C23: Livestock | D23: Essential | E23: =(Models!$H$27+Models!$H$34)*1.1*Assumptions!$H$29 | F23: m2 | G23: =Assumptions!$H$28 | H23: =E23*G23*Sensitivity!$C$11 | I23: =MAX(1,Models!$H$21-1) | J23: =INT((I23-1)/12)+1 | K23: 15 | L23: =IF(K23>0,H23/K23,0)
A24: CX20 | B24: Quarantine pen and handling race | C24: Livestock | D24: Essential | E24: =1 | F24: lump | G24: =Assumptions!$H$30 | H24: =E24*G24*Sensitivity!$C$11 | I24: =MAX(1,Models!$H$21-1) | J24: =INT((I24-1)/12)+1 | K24: 10 | L24: =IF(K24>0,H24/K24,0)
A25: CX21 | B25: Feed store | C25: Livestock | D25: Essential | E25: =1 | F25: lump | G25: =Models!$H$57 | H25: =E25*G25*Sensitivity!$C$11 | I25: =MAX(1,Models!$H$21-1) | J25: =INT((I25-1)/12)+1 | K25: 15 | L25: =IF(K25>0,H25/K25,0)
A26: CX22 | B26: Livestock weighing scale | C26: Livestock | D26: Essential | E26: =1 | F26: lump | G26: =Assumptions!$H$37 | H26: =E26*G26*Sensitivity!$C$11 | I26: =Models!$H$21 | J26: =INT((I26-1)/12)+1 | K26: 8 | L26: =IF(K26>0,H26/K26,0)
A27: CX23 | B27: Tools and small equipment | C27: Equipment | D27: Essential | E27: =1 | F27: lump | G27: =Models!$H$58 | H27: =E27*G27*Sensitivity!$C$11 | I27: =2 | J27: =INT((I27-1)/12)+1 | K27: 5 | L27: =IF(K27>0,H27/K27,0)
A28: CX24 | B28: Solar PV with battery | C28: Energy and tech | D28: Essential | E28: =Models!$H$50 | F28: kWp | G28: =Assumptions!$H$36 | H28: =E28*G28*Sensitivity!$C$11 | I28: =3 | J28: =INT((I28-1)/12)+1 | K28: 10 | L28: =IF(K28>0,H28/K28,0)
A29: CX25 | B29: Connectivity | C29: Energy and tech | D29: Essential | E29: =1 | F29: lump | G29: =Models!$H$52 | H29: =E29*G29*Sensitivity!$C$11 | I29: =3 | J29: =INT((I29-1)/12)+1 | K29: 5 | L29: =IF(K29>0,H29/K29,0)
A30: CX26 | B30: Sensors and controllers | C30: Energy and tech | D30: Optional | E30: =1 | F30: lump | G30: =Models!$H$51 | H30: =E30*G30*Sensitivity!$C$11 | I30: =6 | J30: =INT((I30-1)/12)+1 | K30: 5 | L30: =IF(K30>0,H30/K30,0)
A31: CX27 | B31: Software and devices | C31: Energy and tech | D31: Optional | E31: =1 | F31: lump | G31: =Models!$H$53 | H31: =E31*G31*Sensitivity!$C$11 | I31: =6 | J31: =INT((I31-1)/12)+1 | K31: 3 | L31: =IF(K31>0,H31/K31,0)
A32: CX28 | B32: Security (lights, cameras) | C32: Energy and tech | D32: Essential | E32: =1 | F32: lump | G32: =Models!$H$54 | H32: =E32*G32*Sensitivity!$C$11 | I32: =3 | J32: =INT((I32-1)/12)+1 | K32: 7 | L32: =IF(K32>0,H32/K32,0)
A33: CX29 | B33: Nursery | C33: Orchard | D33: Optional | E33: =1 | F33: lump | G33: =Models!$H$55 | H33: =E33*G33*Sensitivity!$C$11 | I33: =2 | J33: =INT((I33-1)/12)+1 | K33: 5 | L33: =IF(K33>0,H33/K33,0)
A34: CX30 | B34: Cool store / packhouse | C34: Post-harvest | D34: Optional | E34: =1 | F34: lump | G34: =Models!$H$56 | H34: =E34*G34*Sensitivity!$C$11 | I34: =24 | J34: =INT((I34-1)/12)+1 | K34: 15 | L34: =IF(K34>0,H34/K34,0)
A36: CX_ESS | B36: Essential items | H36: =SUMIF($D$5:$D$34,"Essential",$H$5:$H$34)
A37: CX_OPT | B37: Optional items | H37: =SUMIF($D$5:$D$34,"Optional",$H$5:$H$34)
A38: CX_SUB | B38: All items | H38: =SUM($H$5:$H$34)
A39: CX_CONT | B39: Contingency | H39: =H38*Assumptions!$H$10
A40: CX_TOT | B40: Capital items including contingency | H40: =H38+H39

Sheet CashFlow
A1: CashFlow
A2: Monthly cash flow, pre-financing, real RWF. Months 1–24 are the requested monthly view; the engine runs 120 months.
B3: Month | D3: 1 | E3: 2 | F3: 3 | G3: 4 | H3: 5 | I3: 6 | J3: 7 | K3: 8 | L3: 9 | M3: 10 | N3: 11 | O3: 12 | P3: 13 | Q3: 14 | R3: 15 | S3: 16 | T3: 17 | U3: 18 | V3: 19 | W3: 20 | X3: 21 | Y3: 22 | Z3: 23 | AA3: 24 | AB3: 25 | AC3: 26 | AD3: 27 | AE3: 28 | AF3: 29 | AG3: 30 | AH3: 31 | AI3: 32 | AJ3: 33 | AK3: 34 | AL3: 35 | AM3: 36 | AN3: 37 | AO3: 38 | AP3: 39 | AQ3: 40 | AR3: 41 | AS3: 42 | AT3: 43 | AU3: 44 | AV3: 45 | AW3: 46 | AX3: 47 | AY3: 48 | AZ3: 49 | BA3: 50 | BB3: 51 | BC3: 52 | BD3: 53 | BE3: 54 | BF3: 55 | BG3: 56 | BH3: 57 | BI3: 58 | BJ3: 59 | BK3: 60 | BL3: 61 | BM3: 62 | BN3: 63 | BO3: 64 | BP3: 65 | BQ3: 66 | BR3: 67 | BS3: 68 | BT3: 69 | BU3: 70 | BV3: 71 | BW3: 72 | BX3: 73 | BY3: 74 | BZ3: 75 | CA3: 76 | CB3: 77 | CC3: 78 | CD3: 79 | CE3: 80 | CF3: 81 | CG3: 82 | CH3: 83 | CI3: 84 | CJ3: 85 | CK3: 86 | CL3: 87 | CM3: 88 | CN3: 89 | CO3: 90 | CP3: 91 | CQ3: 92 | CR3: 93 | CS3: 94 | CT3: 95 | CU3: 96 | CV3: 97 | CW3: 98 | CX3: 99 | CY3: 100 | CZ3: 101 | DA3: 102 | DB3: 103 | DC3: 104 | DD3: 105 | DE3: 106 | DF3: 107 | DG3: 108 | DH3: 109 | DI3: 110 | DJ3: 111 | DK3: 112 | DL3: 113 | DM3: 114 | DN3: 115 | DO3: 116 | DP3: 117 | DQ3: 118 | DR3: 119 | DS3: 120
B4: Farm year | D4: =INT((D$3-1)/12)+1 | E4: =INT((E$3-1)/12)+1 | F4: =INT((F$3-1)/12)+1 | G4: =INT((G$3-1)/12)+1 | H4: =INT((H$3-1)/12)+1 | I4: =INT((I$3-1)/12)+1 | J4: =INT((J$3-1)/12)+1 | K4: =INT((K$3-1)/12)+1 | ... DS4: =INT((DS$3-1)/12)+1
B5: Calendar month | D5: =MOD(Control!$C$10+D$3-2,12)+1 | E5: =MOD(Control!$C$10+E$3-2,12)+1 | F5: =MOD(Control!$C$10+F$3-2,12)+1 | G5: =MOD(Control!$C$10+G$3-2,12)+1 | H5: =MOD(Control!$C$10+H$3-2,12)+1 | I5: =MOD(Control!$C$10+I$3-2,12)+1 | J5: =MOD(Control!$C$10+J$3-2,12)+1 | K5: =MOD(Control!$C$10+K$3-2,12)+1 | ... DS5: =MOD(Control!$C$10+DS$3-2,12)+1
B6: Month starting | D6: =DATE(Control!$C$9+INT((Control!$C$10+D$3-2)/12),D$5,1) | E6: =DATE(Control!$C$9+INT((Control!$C$10+E$3-2)/12),E$5,1) | F6: =DATE(Control!$C$9+INT((Control!$C$10+F$3-2)/12),F$5,1) | G6: =DATE(Control!$C$9+INT((Control!$C$10+G$3-2)/12),G$5,1) | H6: =DATE(Control!$C$9+INT((Control!$C$10+H$3-2)/12),H$5,1) | I6: =DATE(Control!$C$9+INT((Control!$C$10+I$3-2)/12),I$5,1) | J6: =DATE(Control!$C$9+INT((Control!$C$10+J$3-2)/12),J$5,1) | K6: =DATE(Control!$C$9+INT((Control!$C$10+K$3-2)/12),K$5,1) | ... DS6: =DATE(Control!$C$9+INT((Control!$C$10+DS$3-2)/12),DS$5,1)
B8: Sales (accrual)
A9: CF_AVO | B9: Fruit: Avocado (grafted) | C9: RWF | D9: =INDEX(Trees!$D$14:$M$14,1,D$4)*INDEX(Curves!$D$15:$O$15,1,D$5) | E9: =INDEX(Trees!$D$14:$M$14,1,E$4)*INDEX(Curves!$D$15:$O$15,1,E$5) | F9: =INDEX(Trees!$D$14:$M$14,1,F$4)*INDEX(Curves!$D$15:$O$15,1,F$5) | G9: =INDEX(Trees!$D$14:$M$14,1,G$4)*INDEX(Curves!$D$15:$O$15,1,G$5) | H9: =INDEX(Trees!$D$14:$M$14,1,H$4)*INDEX(Curves!$D$15:$O$15,1,H$5) | I9: =INDEX(Trees!$D$14:$M$14,1,I$4)*INDEX(Curves!$D$15:$O$15,1,I$5) | J9: =INDEX(Trees!$D$14:$M$14,1,J$4)*INDEX(Curves!$D$15:$O$15,1,J$5) | K9: =INDEX(Trees!$D$14:$M$14,1,K$4)*INDEX(Curves!$D$15:$O$15,1,K$5) | ... DS9: =INDEX(Trees!$D$14:$M$14,1,DS$4)*INDEX(Curves!$D$15:$O$15,1,DS$5)
A10: CF_MAN | B10: Fruit: Mango (grafted) | C10: RWF | D10: =INDEX(Trees!$D$26:$M$26,1,D$4)*INDEX(Curves!$D$16:$O$16,1,D$5) | E10: =INDEX(Trees!$D$26:$M$26,1,E$4)*INDEX(Curves!$D$16:$O$16,1,E$5) | F10: =INDEX(Trees!$D$26:$M$26,1,F$4)*INDEX(Curves!$D$16:$O$16,1,F$5) | G10: =INDEX(Trees!$D$26:$M$26,1,G$4)*INDEX(Curves!$D$16:$O$16,1,G$5) | H10: =INDEX(Trees!$D$26:$M$26,1,H$4)*INDEX(Curves!$D$16:$O$16,1,H$5) | I10: =INDEX(Trees!$D$26:$M$26,1,I$4)*INDEX(Curves!$D$16:$O$16,1,I$5) | J10: =INDEX(Trees!$D$26:$M$26,1,J$4)*INDEX(Curves!$D$16:$O$16,1,J$5) | K10: =INDEX(Trees!$D$26:$M$26,1,K$4)*INDEX(Curves!$D$16:$O$16,1,K$5) | ... DS10: =INDEX(Trees!$D$26:$M$26,1,DS$4)*INDEX(Curves!$D$16:$O$16,1,DS$5)
A11: CF_PAS | B11: Fruit: Passion fruit | C11: RWF | D11: =INDEX(Trees!$D$38:$M$38,1,D$4)*INDEX(Curves!$D$17:$O$17,1,D$5) | E11: =INDEX(Trees!$D$38:$M$38,1,E$4)*INDEX(Curves!$D$17:$O$17,1,E$5) | F11: =INDEX(Trees!$D$38:$M$38,1,F$4)*INDEX(Curves!$D$17:$O$17,1,F$5) | G11: =INDEX(Trees!$D$38:$M$38,1,G$4)*INDEX(Curves!$D$17:$O$17,1,G$5) | H11: =INDEX(Trees!$D$38:$M$38,1,H$4)*INDEX(Curves!$D$17:$O$17,1,H$5) | I11: =INDEX(Trees!$D$38:$M$38,1,I$4)*INDEX(Curves!$D$17:$O$17,1,I$5) | J11: =INDEX(Trees!$D$38:$M$38,1,J$4)*INDEX(Curves!$D$17:$O$17,1,J$5) | K11: =INDEX(Trees!$D$38:$M$38,1,K$4)*INDEX(Curves!$D$17:$O$17,1,K$5) | ... DS11: =INDEX(Trees!$D$38:$M$38,1,DS$4)*INDEX(Curves!$D$17:$O$17,1,DS$5)
A12: CF_PAP | B12: Fruit: Papaya | C12: RWF | D12: =INDEX(Trees!$D$50:$M$50,1,D$4)*INDEX(Curves!$D$18:$O$18,1,D$5) | E12: =INDEX(Trees!$D$50:$M$50,1,E$4)*INDEX(Curves!$D$18:$O$18,1,E$5) | F12: =INDEX(Trees!$D$50:$M$50,1,F$4)*INDEX(Curves!$D$18:$O$18,1,F$5) | G12: =INDEX(Trees!$D$50:$M$50,1,G$4)*INDEX(Curves!$D$18:$O$18,1,G$5) | H12: =INDEX(Trees!$D$50:$M$50,1,H$4)*INDEX(Curves!$D$18:$O$18,1,H$5) | I12: =INDEX(Trees!$D$50:$M$50,1,I$4)*INDEX(Curves!$D$18:$O$18,1,I$5) | J12: =INDEX(Trees!$D$50:$M$50,1,J$4)*INDEX(Curves!$D$18:$O$18,1,J$5) | K12: =INDEX(Trees!$D$50:$M$50,1,K$4)*INDEX(Curves!$D$18:$O$18,1,K$5) | ... DS12: =INDEX(Trees!$D$50:$M$50,1,DS$4)*INDEX(Curves!$D$18:$O$18,1,DS$5)
A13: CF_TTO | B13: Fruit: Tree tomato | C13: RWF | D13: =INDEX(Trees!$D$62:$M$62,1,D$4)*INDEX(Curves!$D$19:$O$19,1,D$5) | E13: =INDEX(Trees!$D$62:$M$62,1,E$4)*INDEX(Curves!$D$19:$O$19,1,E$5) | F13: =INDEX(Trees!$D$62:$M$62,1,F$4)*INDEX(Curves!$D$19:$O$19,1,F$5) | G13: =INDEX(Trees!$D$62:$M$62,1,G$4)*INDEX(Curves!$D$19:$O$19,1,G$5) | H13: =INDEX(Trees!$D$62:$M$62,1,H$4)*INDEX(Curves!$D$19:$O$19,1,H$5) | I13: =INDEX(Trees!$D$62:$M$62,1,I$4)*INDEX(Curves!$D$19:$O$19,1,I$5) | J13: =INDEX(Trees!$D$62:$M$62,1,J$4)*INDEX(Curves!$D$19:$O$19,1,J$5) | K13: =INDEX(Trees!$D$62:$M$62,1,K$4)*INDEX(Curves!$D$19:$O$19,1,K$5) | ... DS13: =INDEX(Trees!$D$62:$M$62,1,DS$4)*INDEX(Curves!$D$19:$O$19,1,DS$5)
A14: CF_CIT | B14: Fruit: Citrus | C14: RWF | D14: =INDEX(Trees!$D$74:$M$74,1,D$4)*INDEX(Curves!$D$20:$O$20,1,D$5) | E14: =INDEX(Trees!$D$74:$M$74,1,E$4)*INDEX(Curves!$D$20:$O$20,1,E$5) | F14: =INDEX(Trees!$D$74:$M$74,1,F$4)*INDEX(Curves!$D$20:$O$20,1,F$5) | G14: =INDEX(Trees!$D$74:$M$74,1,G$4)*INDEX(Curves!$D$20:$O$20,1,G$5) | H14: =INDEX(Trees!$D$74:$M$74,1,H$4)*INDEX(Curves!$D$20:$O$20,1,H$5) | I14: =INDEX(Trees!$D$74:$M$74,1,I$4)*INDEX(Curves!$D$20:$O$20,1,I$5) | J14: =INDEX(Trees!$D$74:$M$74,1,J$4)*INDEX(Curves!$D$20:$O$20,1,J$5) | K14: =INDEX(Trees!$D$74:$M$74,1,K$4)*INDEX(Curves!$D$20:$O$20,1,K$5) | ... DS14: =INDEX(Trees!$D$74:$M$74,1,DS$4)*INDEX(Curves!$D$20:$O$20,1,DS$5)
A15: CF_MAC | B15: Fruit: Macadamia (nut in shell) | C15: RWF | D15: =INDEX(Trees!$D$86:$M$86,1,D$4)*INDEX(Curves!$D$21:$O$21,1,D$5) | E15: =INDEX(Trees!$D$86:$M$86,1,E$4)*INDEX(Curves!$D$21:$O$21,1,E$5) | F15: =INDEX(Trees!$D$86:$M$86,1,F$4)*INDEX(Curves!$D$21:$O$21,1,F$5) | G15: =INDEX(Trees!$D$86:$M$86,1,G$4)*INDEX(Curves!$D$21:$O$21,1,G$5) | H15: =INDEX(Trees!$D$86:$M$86,1,H$4)*INDEX(Curves!$D$21:$O$21,1,H$5) | I15: =INDEX(Trees!$D$86:$M$86,1,I$4)*INDEX(Curves!$D$21:$O$21,1,I$5) | J15: =INDEX(Trees!$D$86:$M$86,1,J$4)*INDEX(Curves!$D$21:$O$21,1,J$5) | K15: =INDEX(Trees!$D$86:$M$86,1,K$4)*INDEX(Curves!$D$21:$O$21,1,K$5) | ... DS15: =INDEX(Trees!$D$86:$M$86,1,DS$4)*INDEX(Curves!$D$21:$O$21,1,DS$5)
A16: CF_TIM | B16: Boundary poles | C16: RWF | D16: =INDEX(Trees!$D$94:$M$94,1,D$4)/12 | E16: =INDEX(Trees!$D$94:$M$94,1,E$4)/12 | F16: =INDEX(Trees!$D$94:$M$94,1,F$4)/12 | G16: =INDEX(Trees!$D$94:$M$94,1,G$4)/12 | H16: =INDEX(Trees!$D$94:$M$94,1,H$4)/12 | I16: =INDEX(Trees!$D$94:$M$94,1,I$4)/12 | J16: =INDEX(Trees!$D$94:$M$94,1,J$4)/12 | K16: =INDEX(Trees!$D$94:$M$94,1,K$4)/12 | ... DS16: =INDEX(Trees!$D$94:$M$94,1,DS$4)/12
A17: CF_GT_Y | B17: Goats: young stock | C17: RWF | D17: =Livestock!D26 | E17: =Livestock!E26 | F17: =Livestock!F26 | G17: =Livestock!G26 | H17: =Livestock!H26 | I17: =Livestock!I26 | J17: =Livestock!J26 | K17: =Livestock!K26 | ... DS17: =Livestock!DS26
A18: CF_GT_C | B18: Goats: culled adults | C18: RWF | D18: =Livestock!D27 | E18: =Livestock!E27 | F18: =Livestock!F27 | G18: =Livestock!G27 | H18: =Livestock!H27 | I18: =Livestock!I27 | J18: =Livestock!J27 | K18: =Livestock!K27 | ... DS18: =Livestock!DS27
A19: CF_SH_Y | B19: Sheep: young stock | C19: RWF | D19: =Livestock!D50 | E19: =Livestock!E50 | F19: =Livestock!F50 | G19: =Livestock!G50 | H19: =Livestock!H50 | I19: =Livestock!I50 | J19: =Livestock!J50 | K19: =Livestock!K50 | ... DS19: =Livestock!DS50
A20: CF_SH_C | B20: Sheep: culled adults | C20: RWF | D20: =Livestock!D51 | E20: =Livestock!E51 | F20: =Livestock!F51 | G20: =Livestock!G51 | H20: =Livestock!H51 | I20: =Livestock!I51 | J20: =Livestock!J51 | K20: =Livestock!K51 | ... DS20: =Livestock!DS51
A21: CF_SALES | B21: Total sales | C21: RWF | D21: =SUM(D9:D20) | E21: =SUM(E9:E20) | F21: =SUM(F9:F20) | G21: =SUM(G9:G20) | H21: =SUM(H9:H20) | I21: =SUM(I9:I20) | J21: =SUM(J9:J20) | K21: =SUM(K9:K20) | ... DS21: =SUM(DS9:DS20)
A22: CF_KG | B22: Memo: fruit marketed | C22: kg | D22: =INDEX(Trees!$D$13:$M$13,1,D$4)*INDEX(Curves!$D$15:$O$15,1,D$5)+INDEX(Trees!$D$25:$M$25,1,D$4)*INDEX(Curves!$D$16:$O$16,1,D$5)+INDEX(Trees!$D$37:$M$37,1,D$4)*INDEX(Curves!$D$17:$O$17,1,D$5)+INDEX(Trees!$D$49:$M$49,1,D$4)*INDEX(Curves!$D$18:$O$18,1,D$5)+INDEX(Trees!$D$61:$M$61,1,D$4)*INDEX(Curves!$D$19:$O$19,1,D$5)+INDEX(Trees!$D$73:$M$73,1,D$4)*INDEX(Curves!$D$20:$O$20,1,D$5)+INDEX(Trees!$D$85:$M$85,1,D$4)*INDEX(Curves!$D$21:$O$21,1,D$5) | E22: =INDEX(Trees!$D$13:$M$13,1,E$4)*INDEX(Curves!$D$15:$O$15,1,E$5)+INDEX(Trees!$D$25:$M$25,1,E$4)*INDEX(Curves!$D$16:$O$16,1,E$5)+INDEX(Trees!$D$37:$M$37,1,E$4)*INDEX(Curves!$D$17:$O$17,1,E$5)+INDEX(Trees!$D$49:$M$49,1,E$4)*INDEX(Curves!$D$18:$O$18,1,E$5)+INDEX(Trees!$D$61:$M$61,1,E$4)*INDEX(Curves!$D$19:$O$19,1,E$5)+INDEX(Trees!$D$73:$M$73,1,E$4)*INDEX(Curves!$D$20:$O$20,1,E$5)+INDEX(Trees!$D$85:$M$85,1,E$4)*INDEX(Curves!$D$21:$O$21,1,E$5) | F22: =INDEX(Trees!$D$13:$M$13,1,F$4)*INDEX(Curves!$D$15:$O$15,1,F$5)+INDEX(Trees!$D$25:$M$25,1,F$4)*INDEX(Curves!$D$16:$O$16,1,F$5)+INDEX(Trees!$D$37:$M$37,1,F$4)*INDEX(Curves!$D$17:$O$17,1,F$5)+INDEX(Trees!$D$49:$M$49,1,F$4)*INDEX(Curves!$D$18:$O$18,1,F$5)+INDEX(Trees!$D$61:$M$61,1,F$4)*INDEX(Curves!$D$19:$O$19,1,F$5)+INDEX(Trees!$D$73:$M$73,1,F$4)*INDEX(Curves!$D$20:$O$20,1,F$5)+INDEX(Trees!$D$85:$M$85,1,F$4)*INDEX(Curves!$D$21:$O$21,1,F$5) | G22: =INDEX(Trees!$D$13:$M$13,1,G$4)*INDEX(Curves!$D$15:$O$15,1,G$5)+INDEX(Trees!$D$25:$M$25,1,G$4)*INDEX(Curves!$D$16:$O$16,1,G$5)+INDEX(Trees!$D$37:$M$37,1,G$4)*INDEX(Curves!$D$17:$O$17,1,G$5)+INDEX(Trees!$D$49:$M$49,1,G$4)*INDEX(Curves!$D$18:$O$18,1,G$5)+INDEX(Trees!$D$61:$M$61,1,G$4)*INDEX(Curves!$D$19:$O$19,1,G$5)+INDEX(Trees!$D$73:$M$73,1,G$4)*INDEX(Curves!$D$20:$O$20,1,G$5)+INDEX(Trees!$D$85:$M$85,1,G$4)*INDEX(Curves!$D$21:$O$21,1,G$5) | H22: =INDEX(Trees!$D$13:$M$13,1,H$4)*INDEX(Curves!$D$15:$O$15,1,H$5)+INDEX(Trees!$D$25:$M$25,1,H$4)*INDEX(Curves!$D$16:$O$16,1,H$5)+INDEX(Trees!$D$37:$M$37,1,H$4)*INDEX(Curves!$D$17:$O$17,1,H$5)+INDEX(Trees!$D$49:$M$49,1,H$4)*INDEX(Curves!$D$18:$O$18,1,H$5)+INDEX(Trees!$D$61:$M$61,1,H$4)*INDEX(Curves!$D$19:$O$19,1,H$5)+INDEX(Trees!$D$73:$M$73,1,H$4)*INDEX(Curves!$D$20:$O$20,1,H$5)+INDEX(Trees!$D$85:$M$85,1,H$4)*INDEX(Curves!$D$21:$O$21,1,H$5) | I22: =INDEX(Trees!$D$13:$M$13,1,I$4)*INDEX(Curves!$D$15:$O$15,1,I$5)+INDEX(Trees!$D$25:$M$25,1,I$4)*INDEX(Curves!$D$16:$O$16,1,I$5)+INDEX(Trees!$D$37:$M$37,1,I$4)*INDEX(Curves!$D$17:$O$17,1,I$5)+INDEX(Trees!$D$49:$M$49,1,I$4)*INDEX(Curves!$D$18:$O$18,1,I$5)+INDEX(Trees!$D$61:$M$61,1,I$4)*INDEX(Curves!$D$19:$O$19,1,I$5)+INDEX(Trees!$D$73:$M$73,1,I$4)*INDEX(Curves!$D$20:$O$20,1,I$5)+INDEX(Trees!$D$85:$M$85,1,I$4)*INDEX(Curves!$D$21:$O$21,1,I$5) | J22: =INDEX(Trees!$D$13:$M$13,1,J$4)*INDEX(Curves!$D$15:$O$15,1,J$5)+INDEX(Trees!$D$25:$M$25,1,J$4)*INDEX(Curves!$D$16:$O$16,1,J$5)+INDEX(Trees!$D$37:$M$37,1,J$4)*INDEX(Curves!$D$17:$O$17,1,J$5)+INDEX(Trees!$D$49:$M$49,1,J$4)*INDEX(Curves!$D$18:$O$18,1,J$5)+INDEX(Trees!$D$61:$M$61,1,J$4)*INDEX(Curves!$D$19:$O$19,1,J$5)+INDEX(Trees!$D$73:$M$73,1,J$4)*INDEX(Curves!$D$20:$O$20,1,J$5)+INDEX(Trees!$D$85:$M$85,1,J$4)*INDEX(Curves!$D$21:$O$21,1,J$5) | K22: =INDEX(Trees!$D$13:$M$13,1,K$4)*INDEX(Curves!$D$15:$O$15,1,K$5)+INDEX(Trees!$D$25:$M$25,1,K$4)*INDEX(Curves!$D$16:$O$16,1,K$5)+INDEX(Trees!$D$37:$M$37,1,K$4)*INDEX(Curves!$D$17:$O$17,1,K$5)+INDEX(Trees!$D$49:$M$49,1,K$4)*INDEX(Curves!$D$18:$O$18,1,K$5)+INDEX(Trees!$D$61:$M$61,1,K$4)*INDEX(Curves!$D$19:$O$19,1,K$5)+INDEX(Trees!$D$73:$M$73,1,K$4)*INDEX(Curves!$D$20:$O$20,1,K$5)+INDEX(Trees!$D$85:$M$85,1,K$4)*INDEX(Curves!$D$21:$O$21,1,K$5) | ... DS22: =INDEX(Trees!$D$13:$M$13,1,DS$4)*INDEX(Curves!$D$15:$O$15,1,DS$5)+INDEX(Trees!$D$25:$M$25,1,DS$4)*INDEX(Curves!$D$16:$O$16,1,DS$5)+INDEX(Trees!$D$37:$M$37,1,DS$4)*INDEX(Curves!$D$17:$O$17,1,DS$5)+INDEX(Trees!$D$49:$M$49,1,DS$4)*INDEX(Curves!$D$18:$O$18,1,DS$5)+INDEX(Trees!$D$61:$M$61,1,DS$4)*INDEX(Curves!$D$19:$O$19,1,DS$5)+INDEX(Trees!$D$73:$M$73,1,DS$4)*INDEX(Curves!$D$20:$O$20,1,DS$5)+INDEX(Trees!$D$85:$M$85,1,DS$4)*INDEX(Curves!$D$21:$O$21,1,DS$5)
B24: Cash in
A25: CF_COLLECT | B25: Collections from customers | C25: RWF | D25: =D21*(1-Assumptions!$H$9) | E25: =E21*(1-Assumptions!$H$9)+D21*Assumptions!$H$9 | F25: =F21*(1-Assumptions!$H$9)+E21*Assumptions!$H$9 | G25: =G21*(1-Assumptions!$H$9)+F21*Assumptions!$H$9 | H25: =H21*(1-Assumptions!$H$9)+G21*Assumptions!$H$9 | I25: =I21*(1-Assumptions!$H$9)+H21*Assumptions!$H$9 | J25: =J21*(1-Assumptions!$H$9)+I21*Assumptions!$H$9 | K25: =K21*(1-Assumptions!$H$9)+J21*Assumptions!$H$9 | L25: =L21*(1-Assumptions!$H$9)+K21*Assumptions!$H$9 | ... DS25: =DS21*(1-Assumptions!$H$9)+DR21*Assumptions!$H$9
B27: Operating costs
A28: CF_PERM | B28: Permanent labour | C28: RWF | D28: =Models!$H$40*Assumptions!$H$14*Sensitivity!$C$10 | E28: =Models!$H$40*Assumptions!$H$14*Sensitivity!$C$10 | F28: =Models!$H$40*Assumptions!$H$14*Sensitivity!$C$10 | G28: =Models!$H$40*Assumptions!$H$14*Sensitivity!$C$10 | H28: =Models!$H$40*Assumptions!$H$14*Sensitivity!$C$10 | I28: =Models!$H$40*Assumptions!$H$14*Sensitivity!$C$10 | J28: =Models!$H$40*Assumptions!$H$14*Sensitivity!$C$10 | K28: =Models!$H$40*Assumptions!$H$14*Sensitivity!$C$10 | ... DS28: =Models!$H$40*Assumptions!$H$14*Sensitivity!$C$10
A29: CF_CASUAL | B29: Casual labour (orchard) | C29: RWF | D29: =Land!$C$8*Assumptions!$H$16*Assumptions!$H$15*Sensitivity!$C$10/12*IF(D$3>=Control!$C$11,1,0) | E29: =Land!$C$8*Assumptions!$H$16*Assumptions!$H$15*Sensitivity!$C$10/12*IF(E$3>=Control!$C$11,1,0) | F29: =Land!$C$8*Assumptions!$H$16*Assumptions!$H$15*Sensitivity!$C$10/12*IF(F$3>=Control!$C$11,1,0) | G29: =Land!$C$8*Assumptions!$H$16*Assumptions!$H$15*Sensitivity!$C$10/12*IF(G$3>=Control!$C$11,1,0) | H29: =Land!$C$8*Assumptions!$H$16*Assumptions!$H$15*Sensitivity!$C$10/12*IF(H$3>=Control!$C$11,1,0) | I29: =Land!$C$8*Assumptions!$H$16*Assumptions!$H$15*Sensitivity!$C$10/12*IF(I$3>=Control!$C$11,1,0) | J29: =Land!$C$8*Assumptions!$H$16*Assumptions!$H$15*Sensitivity!$C$10/12*IF(J$3>=Control!$C$11,1,0) | K29: =Land!$C$8*Assumptions!$H$16*Assumptions!$H$15*Sensitivity!$C$10/12*IF(K$3>=Control!$C$11,1,0) | ... DS29: =Land!$C$8*Assumptions!$H$16*Assumptions!$H$15*Sensitivity!$C$10/12*IF(DS$3>=Control!$C$11,1,0)
A30: CF_VET | B30: Veterinary care, medicines, minerals | C30: RWF | D30: =(Livestock!D24+Livestock!D48)*(Assumptions!$H$39+Assumptions!$H$40)/12 | E30: =(Livestock!E24+Livestock!E48)*(Assumptions!$H$39+Assumptions!$H$40)/12 | F30: =(Livestock!F24+Livestock!F48)*(Assumptions!$H$39+Assumptions!$H$40)/12 | G30: =(Livestock!G24+Livestock!G48)*(Assumptions!$H$39+Assumptions!$H$40)/12 | H30: =(Livestock!H24+Livestock!H48)*(Assumptions!$H$39+Assumptions!$H$40)/12 | I30: =(Livestock!I24+Livestock!I48)*(Assumptions!$H$39+Assumptions!$H$40)/12 | J30: =(Livestock!J24+Livestock!J48)*(Assumptions!$H$39+Assumptions!$H$40)/12 | K30: =(Livestock!K24+Livestock!K48)*(Assumptions!$H$39+Assumptions!$H$40)/12 | ... DS30: =(Livestock!DS24+Livestock!DS48)*(Assumptions!$H$39+Assumptions!$H$40)/12
A31: CF_FEED | B31: Feed bought | C31: RWF | D31: =Feed!D18 | E31: =Feed!E18 | F31: =Feed!F18 | G31: =Feed!G18 | H31: =Feed!H18 | I31: =Feed!I18 | J31: =Feed!J18 | K31: =Feed!K18 | ... DS31: =Feed!DS18
A32: CF_CONS | B32: Hay/silage conservation | C32: RWF | D32: =Feed!D19 | E32: =Feed!E19 | F32: =Feed!F19 | G32: =Feed!G19 | H32: =Feed!H19 | I32: =Feed!I19 | J32: =Feed!J19 | K32: =Feed!K19 | ... DS32: =Feed!DS19
A33: CF_FERT | B33: Orchard inputs | C33: RWF | D33: =Land!$C$8*Assumptions!$H$41/12*IF(D$3>=Control!$C$11,1,0) | E33: =Land!$C$8*Assumptions!$H$41/12*IF(E$3>=Control!$C$11,1,0) | F33: =Land!$C$8*Assumptions!$H$41/12*IF(F$3>=Control!$C$11,1,0) | G33: =Land!$C$8*Assumptions!$H$41/12*IF(G$3>=Control!$C$11,1,0) | H33: =Land!$C$8*Assumptions!$H$41/12*IF(H$3>=Control!$C$11,1,0) | I33: =Land!$C$8*Assumptions!$H$41/12*IF(I$3>=Control!$C$11,1,0) | J33: =Land!$C$8*Assumptions!$H$41/12*IF(J$3>=Control!$C$11,1,0) | K33: =Land!$C$8*Assumptions!$H$41/12*IF(K$3>=Control!$C$11,1,0) | ... DS33: =Land!$C$8*Assumptions!$H$41/12*IF(DS$3>=Control!$C$11,1,0)
A34: CF_PASTM | B34: Pasture and fodder upkeep | C34: RWF | D34: =(Land!$C$12+Land!$C$13)*Assumptions!$H$42/12*IF(D$3>=Control!$C$12,1,0) | E34: =(Land!$C$12+Land!$C$13)*Assumptions!$H$42/12*IF(E$3>=Control!$C$12,1,0) | F34: =(Land!$C$12+Land!$C$13)*Assumptions!$H$42/12*IF(F$3>=Control!$C$12,1,0) | G34: =(Land!$C$12+Land!$C$13)*Assumptions!$H$42/12*IF(G$3>=Control!$C$12,1,0) | H34: =(Land!$C$12+Land!$C$13)*Assumptions!$H$42/12*IF(H$3>=Control!$C$12,1,0) | I34: =(Land!$C$12+Land!$C$13)*Assumptions!$H$42/12*IF(I$3>=Control!$C$12,1,0) | J34: =(Land!$C$12+Land!$C$13)*Assumptions!$H$42/12*IF(J$3>=Control!$C$12,1,0) | K34: =(Land!$C$12+Land!$C$13)*Assumptions!$H$42/12*IF(K$3>=Control!$C$12,1,0) | ... DS34: =(Land!$C$12+Land!$C$13)*Assumptions!$H$42/12*IF(DS$3>=Control!$C$12,1,0)
A35: CF_REPL | B35: Replanting short-cycle crops | C35: RWF | D35: =IF(D$3=Control!$C$11+12*(D$4-1),INDEX(Trees!$D$101:$M$101,1,D$4),0) | E35: =IF(E$3=Control!$C$11+12*(E$4-1),INDEX(Trees!$D$101:$M$101,1,E$4),0) | F35: =IF(F$3=Control!$C$11+12*(F$4-1),INDEX(Trees!$D$101:$M$101,1,F$4),0) | G35: =IF(G$3=Control!$C$11+12*(G$4-1),INDEX(Trees!$D$101:$M$101,1,G$4),0) | H35: =IF(H$3=Control!$C$11+12*(H$4-1),INDEX(Trees!$D$101:$M$101,1,H$4),0) | I35: =IF(I$3=Control!$C$11+12*(I$4-1),INDEX(Trees!$D$101:$M$101,1,I$4),0) | J35: =IF(J$3=Control!$C$11+12*(J$4-1),INDEX(Trees!$D$101:$M$101,1,J$4),0) | K35: =IF(K$3=Control!$C$11+12*(K$4-1),INDEX(Trees!$D$101:$M$101,1,K$4),0) | ... DS35: =IF(DS$3=Control!$C$11+12*(DS$4-1),INDEX(Trees!$D$101:$M$101,1,DS$4),0)
A36: CF_TRANSF | B36: Transport: fruit | C36: RWF | D36: =D22*Assumptions!$H$43*Sensitivity!$C$12 | E36: =E22*Assumptions!$H$43*Sensitivity!$C$12 | F36: =F22*Assumptions!$H$43*Sensitivity!$C$12 | G36: =G22*Assumptions!$H$43*Sensitivity!$C$12 | H36: =H22*Assumptions!$H$43*Sensitivity!$C$12 | I36: =I22*Assumptions!$H$43*Sensitivity!$C$12 | J36: =J22*Assumptions!$H$43*Sensitivity!$C$12 | K36: =K22*Assumptions!$H$43*Sensitivity!$C$12 | ... DS36: =DS22*Assumptions!$H$43*Sensitivity!$C$12
A37: CF_TRANSL | B37: Transport: livestock | C37: RWF | D37: =(Livestock!D25+Livestock!D49)*Assumptions!$H$44*Sensitivity!$C$12 | E37: =(Livestock!E25+Livestock!E49)*Assumptions!$H$44*Sensitivity!$C$12 | F37: =(Livestock!F25+Livestock!F49)*Assumptions!$H$44*Sensitivity!$C$12 | G37: =(Livestock!G25+Livestock!G49)*Assumptions!$H$44*Sensitivity!$C$12 | H37: =(Livestock!H25+Livestock!H49)*Assumptions!$H$44*Sensitivity!$C$12 | I37: =(Livestock!I25+Livestock!I49)*Assumptions!$H$44*Sensitivity!$C$12 | J37: =(Livestock!J25+Livestock!J49)*Assumptions!$H$44*Sensitivity!$C$12 | K37: =(Livestock!K25+Livestock!K49)*Assumptions!$H$44*Sensitivity!$C$12 | ... DS37: =(Livestock!DS25+Livestock!DS49)*Assumptions!$H$44*Sensitivity!$C$12
A38: CF_PACK | B38: Packaging | C38: RWF | D38: =D22*Assumptions!$H$45 | E38: =E22*Assumptions!$H$45 | F38: =F22*Assumptions!$H$45 | G38: =G22*Assumptions!$H$45 | H38: =H22*Assumptions!$H$45 | I38: =I22*Assumptions!$H$45 | J38: =J22*Assumptions!$H$45 | K38: =K22*Assumptions!$H$45 | ... DS38: =DS22*Assumptions!$H$45
A39: CF_MKTG | B39: Marketing and sales | C39: RWF | D39: =D21*Assumptions!$H$11 | E39: =E21*Assumptions!$H$11 | F39: =F21*Assumptions!$H$11 | G39: =G21*Assumptions!$H$11 | H39: =H21*Assumptions!$H$11 | I39: =I21*Assumptions!$H$11 | J39: =J21*Assumptions!$H$11 | K39: =K21*Assumptions!$H$11 | ... DS39: =DS21*Assumptions!$H$11
A40: CF_COMMS | B40: Communications and software | C40: RWF | D40: =Assumptions!$H$46 | E40: =Assumptions!$H$46 | F40: =Assumptions!$H$46 | G40: =Assumptions!$H$46 | H40: =Assumptions!$H$46 | I40: =Assumptions!$H$46 | J40: =Assumptions!$H$46 | K40: =Assumptions!$H$46 | ... DS40: =Assumptions!$H$46
A41: CF_UTIL | B41: Utilities and fuel | C41: RWF | D41: =Assumptions!$H$47 | E41: =Assumptions!$H$47 | F41: =Assumptions!$H$47 | G41: =Assumptions!$H$47 | H41: =Assumptions!$H$47 | I41: =Assumptions!$H$47 | J41: =Assumptions!$H$47 | K41: =Assumptions!$H$47 | ... DS41: =Assumptions!$H$47
A42: CF_ADMIN | B42: Administration and accounting | C42: RWF | D42: =Assumptions!$H$48 | E42: =Assumptions!$H$48 | F42: =Assumptions!$H$48 | G42: =Assumptions!$H$48 | H42: =Assumptions!$H$48 | I42: =Assumptions!$H$48 | J42: =Assumptions!$H$48 | K42: =Assumptions!$H$48 | ... DS42: =Assumptions!$H$48
A43: CF_INS | B43: Livestock insurance | C43: RWF | D43: =(Livestock!D29+Livestock!D53)*Assumptions!$H$49/12 | E43: =(Livestock!E29+Livestock!E53)*Assumptions!$H$49/12 | F43: =(Livestock!F29+Livestock!F53)*Assumptions!$H$49/12 | G43: =(Livestock!G29+Livestock!G53)*Assumptions!$H$49/12 | H43: =(Livestock!H29+Livestock!H53)*Assumptions!$H$49/12 | I43: =(Livestock!I29+Livestock!I53)*Assumptions!$H$49/12 | J43: =(Livestock!J29+Livestock!J53)*Assumptions!$H$49/12 | K43: =(Livestock!K29+Livestock!K53)*Assumptions!$H$49/12 | ... DS43: =(Livestock!DS29+Livestock!DS53)*Assumptions!$H$49/12
A44: CF_RM | B44: Repairs and maintenance | C44: RWF | D44: =SUMIF(CapEx!$I$5:$I$34,"<"&D$3,CapEx!$H$5:$H$34)*(1+Assumptions!$H$10)*Assumptions!$H$12/12 | E44: =SUMIF(CapEx!$I$5:$I$34,"<"&E$3,CapEx!$H$5:$H$34)*(1+Assumptions!$H$10)*Assumptions!$H$12/12 | F44: =SUMIF(CapEx!$I$5:$I$34,"<"&F$3,CapEx!$H$5:$H$34)*(1+Assumptions!$H$10)*Assumptions!$H$12/12 | G44: =SUMIF(CapEx!$I$5:$I$34,"<"&G$3,CapEx!$H$5:$H$34)*(1+Assumptions!$H$10)*Assumptions!$H$12/12 | H44: =SUMIF(CapEx!$I$5:$I$34,"<"&H$3,CapEx!$H$5:$H$34)*(1+Assumptions!$H$10)*Assumptions!$H$12/12 | I44: =SUMIF(CapEx!$I$5:$I$34,"<"&I$3,CapEx!$H$5:$H$34)*(1+Assumptions!$H$10)*Assumptions!$H$12/12 | J44: =SUMIF(CapEx!$I$5:$I$34,"<"&J$3,CapEx!$H$5:$H$34)*(1+Assumptions!$H$10)*Assumptions!$H$12/12 | K44: =SUMIF(CapEx!$I$5:$I$34,"<"&K$3,CapEx!$H$5:$H$34)*(1+Assumptions!$H$10)*Assumptions!$H$12/12 | ... DS44: =SUMIF(CapEx!$I$5:$I$34,"<"&DS$3,CapEx!$H$5:$H$34)*(1+Assumptions!$H$10)*Assumptions!$H$12/12
A45: CF_LAND | B45: Land fees and taxes | C45: RWF | D45: =Assumptions!$H$50/12 | E45: =Assumptions!$H$50/12 | F45: =Assumptions!$H$50/12 | G45: =Assumptions!$H$50/12 | H45: =Assumptions!$H$50/12 | I45: =Assumptions!$H$50/12 | J45: =Assumptions!$H$50/12 | K45: =Assumptions!$H$50/12 | ... DS45: =Assumptions!$H$50/12
A46: CF_OPEX | B46: Total operating costs | C46: RWF | D46: =SUM(D28:D45) | E46: =SUM(E28:E45) | F46: =SUM(F28:F45) | G46: =SUM(G28:G45) | H46: =SUM(H28:H45) | I46: =SUM(I28:I45) | J46: =SUM(J28:J45) | K46: =SUM(K28:K45) | ... DS46: =SUM(DS28:DS45)
A48: CF_EBITDA | B48: EBITDA (sales less operating costs) | C48: RWF | D48: =D21-D46 | E48: =E21-E46 | F48: =F21-F46 | G48: =G21-G46 | H48: =H21-H46 | I48: =I21-I46 | J48: =J21-J46 | K48: =K21-K46 | ... DS48: =DS21-DS46
B50: Investment
A51: CF_CAPEX | B51: Capital items incl. contingency | C51: RWF | D51: =SUMIF(CapEx!$I$5:$I$34,D$3,CapEx!$H$5:$H$34)*(1+Assumptions!$H$10) | E51: =SUMIF(CapEx!$I$5:$I$34,E$3,CapEx!$H$5:$H$34)*(1+Assumptions!$H$10) | F51: =SUMIF(CapEx!$I$5:$I$34,F$3,CapEx!$H$5:$H$34)*(1+Assumptions!$H$10) | G51: =SUMIF(CapEx!$I$5:$I$34,G$3,CapEx!$H$5:$H$34)*(1+Assumptions!$H$10) | H51: =SUMIF(CapEx!$I$5:$I$34,H$3,CapEx!$H$5:$H$34)*(1+Assumptions!$H$10) | I51: =SUMIF(CapEx!$I$5:$I$34,I$3,CapEx!$H$5:$H$34)*(1+Assumptions!$H$10) | J51: =SUMIF(CapEx!$I$5:$I$34,J$3,CapEx!$H$5:$H$34)*(1+Assumptions!$H$10) | K51: =SUMIF(CapEx!$I$5:$I$34,K$3,CapEx!$H$5:$H$34)*(1+Assumptions!$H$10) | ... DS51: =SUMIF(CapEx!$I$5:$I$34,DS$3,CapEx!$H$5:$H$34)*(1+Assumptions!$H$10)
A52: CF_ANIMALS | B52: Animal purchases | C52: RWF | D52: =Livestock!D28+Livestock!D52 | E52: =Livestock!E28+Livestock!E52 | F52: =Livestock!F28+Livestock!F52 | G52: =Livestock!G28+Livestock!G52 | H52: =Livestock!H28+Livestock!H52 | I52: =Livestock!I28+Livestock!I52 | J52: =Livestock!J28+Livestock!J52 | K52: =Livestock!K28+Livestock!K52 | ... DS52: =Livestock!DS28+Livestock!DS52
A53: CF_INVEST | B53: Total investment | C53: RWF | D53: =D51+D52 | E53: =E51+E52 | F53: =F51+F52 | G53: =G51+G52 | H53: =H51+H52 | I53: =I51+I52 | J53: =J51+J52 | K53: =K51+K52 | ... DS53: =DS51+DS52
A55: CF_TAX | B55: Income tax paid (year end) | C55: RWF | D55: =IF(MOD(D$3,12)=0,MAX(0,SUMIF($D$4:$DS$4,D$4,$D$48:$DS$48)-SUMPRODUCT((CapEx!$J$5:$J$34<=D$4)*(CapEx!$J$5:$J$34+CapEx!$K$5:$K$34>D$4)*CapEx!$L$5:$L$34)*(1+Assumptions!$H$10))*Assumptions!$H$8,0) | E55: =IF(MOD(E$3,12)=0,MAX(0,SUMIF($D$4:$DS$4,E$4,$D$48:$DS$48)-SUMPRODUCT((CapEx!$J$5:$J$34<=E$4)*(CapEx!$J$5:$J$34+CapEx!$K$5:$K$34>E$4)*CapEx!$L$5:$L$34)*(1+Assumptions!$H$10))*Assumptions!$H$8,0) | F55: =IF(MOD(F$3,12)=0,MAX(0,SUMIF($D$4:$DS$4,F$4,$D$48:$DS$48)-SUMPRODUCT((CapEx!$J$5:$J$34<=F$4)*(CapEx!$J$5:$J$34+CapEx!$K$5:$K$34>F$4)*CapEx!$L$5:$L$34)*(1+Assumptions!$H$10))*Assumptions!$H$8,0) | G55: =IF(MOD(G$3,12)=0,MAX(0,SUMIF($D$4:$DS$4,G$4,$D$48:$DS$48)-SUMPRODUCT((CapEx!$J$5:$J$34<=G$4)*(CapEx!$J$5:$J$34+CapEx!$K$5:$K$34>G$4)*CapEx!$L$5:$L$34)*(1+Assumptions!$H$10))*Assumptions!$H$8,0) | H55: =IF(MOD(H$3,12)=0,MAX(0,SUMIF($D$4:$DS$4,H$4,$D$48:$DS$48)-SUMPRODUCT((CapEx!$J$5:$J$34<=H$4)*(CapEx!$J$5:$J$34+CapEx!$K$5:$K$34>H$4)*CapEx!$L$5:$L$34)*(1+Assumptions!$H$10))*Assumptions!$H$8,0) | I55: =IF(MOD(I$3,12)=0,MAX(0,SUMIF($D$4:$DS$4,I$4,$D$48:$DS$48)-SUMPRODUCT((CapEx!$J$5:$J$34<=I$4)*(CapEx!$J$5:$J$34+CapEx!$K$5:$K$34>I$4)*CapEx!$L$5:$L$34)*(1+Assumptions!$H$10))*Assumptions!$H$8,0) | J55: =IF(MOD(J$3,12)=0,MAX(0,SUMIF($D$4:$DS$4,J$4,$D$48:$DS$48)-SUMPRODUCT((CapEx!$J$5:$J$34<=J$4)*(CapEx!$J$5:$J$34+CapEx!$K$5:$K$34>J$4)*CapEx!$L$5:$L$34)*(1+Assumptions!$H$10))*Assumptions!$H$8,0) | K55: =IF(MOD(K$3,12)=0,MAX(0,SUMIF($D$4:$DS$4,K$4,$D$48:$DS$48)-SUMPRODUCT((CapEx!$J$5:$J$34<=K$4)*(CapEx!$J$5:$J$34+CapEx!$K$5:$K$34>K$4)*CapEx!$L$5:$L$34)*(1+Assumptions!$H$10))*Assumptions!$H$8,0) | ... DS55: =IF(MOD(DS$3,12)=0,MAX(0,SUMIF($D$4:$DS$4,DS$4,$D$48:$DS$48)-SUMPRODUCT((CapEx!$J$5:$J$34<=DS$4)*(CapEx!$J$5:$J$34+CapEx!$K$5:$K$34>DS$4)*CapEx!$L$5:$L$34)*(1+Assumptions!$H$10))*Assumptions!$H$8,0)
A57: CF_NET | B57: NET CASH FLOW (pre-financing) | C57: RWF | D57: =D25-D46-D53-D55 | E57: =E25-E46-E53-E55 | F57: =F25-F46-F53-F55 | G57: =G25-G46-G53-G55 | H57: =H25-H46-H53-H55 | I57: =I25-I46-I53-I55 | J57: =J25-J46-J53-J55 | K57: =K25-K46-K53-K55 | ... DS57: =DS25-DS46-DS53-DS55
A58: CF_CUM | B58: Cumulative net cash flow | C58: RWF | D58: =0+D57 | E58: =D58+E57 | F58: =E58+F57 | G58: =F58+G57 | H58: =G58+H57 | I58: =H58+I57 | J58: =I58+J57 | K58: =J58+K57 | L58: =K58+L57 | ... DS58: =DR58+DS57
A59: CF_BAL | B59: Cash balance with founder capital | C59: RWF | D59: =Control!$C$8+D58 | E59: =Control!$C$8+E58 | F59: =Control!$C$8+F58 | G59: =Control!$C$8+G58 | H59: =Control!$C$8+H58 | I59: =Control!$C$8+I58 | J59: =Control!$C$8+J58 | K59: =Control!$C$8+K58 | ... DS59: =Control!$C$8+DS58
A60: CF_SHORT | B60: Shortfall flag (1 = capital exhausted) | C60: flag | D60: =IF(D59<0,1,0) | E60: =IF(E59<0,1,0) | F60: =IF(F59<0,1,0) | G60: =IF(G59<0,1,0) | H60: =IF(H59<0,1,0) | I60: =IF(I59<0,1,0) | J60: =IF(J59<0,1,0) | K60: =IF(K59<0,1,0) | ... DS60: =IF(DS59<0,1,0)

Sheet Annual
A1: Annual
A2: Ten farm years: profit and loss (accrual) and cash flow (pre-financing). Real RWF.
B3: Farm year | D3: 1 | E3: 2 | F3: 3 | G3: 4 | H3: 5 | I3: 6 | J3: 7 | K3: 8 | L3: 9 | M3: 10
B5: Revenue
A6: AN_CF_AVO | B6: Fruit: Avocado (grafted) | C6: RWF | D6: =SUMIF(CashFlow!$D$4:$DS$4,D$3,CashFlow!$D$9:$DS$9) | E6: =SUMIF(CashFlow!$D$4:$DS$4,E$3,CashFlow!$D$9:$DS$9) | F6: =SUMIF(CashFlow!$D$4:$DS$4,F$3,CashFlow!$D$9:$DS$9) | G6: =SUMIF(CashFlow!$D$4:$DS$4,G$3,CashFlow!$D$9:$DS$9) | H6: =SUMIF(CashFlow!$D$4:$DS$4,H$3,CashFlow!$D$9:$DS$9) | I6: =SUMIF(CashFlow!$D$4:$DS$4,I$3,CashFlow!$D$9:$DS$9) | J6: =SUMIF(CashFlow!$D$4:$DS$4,J$3,CashFlow!$D$9:$DS$9) | K6: =SUMIF(CashFlow!$D$4:$DS$4,K$3,CashFlow!$D$9:$DS$9) | ... M6: =SUMIF(CashFlow!$D$4:$DS$4,M$3,CashFlow!$D$9:$DS$9)
A7: AN_CF_MAN | B7: Fruit: Mango (grafted) | C7: RWF | D7: =SUMIF(CashFlow!$D$4:$DS$4,D$3,CashFlow!$D$10:$DS$10) | E7: =SUMIF(CashFlow!$D$4:$DS$4,E$3,CashFlow!$D$10:$DS$10) | F7: =SUMIF(CashFlow!$D$4:$DS$4,F$3,CashFlow!$D$10:$DS$10) | G7: =SUMIF(CashFlow!$D$4:$DS$4,G$3,CashFlow!$D$10:$DS$10) | H7: =SUMIF(CashFlow!$D$4:$DS$4,H$3,CashFlow!$D$10:$DS$10) | I7: =SUMIF(CashFlow!$D$4:$DS$4,I$3,CashFlow!$D$10:$DS$10) | J7: =SUMIF(CashFlow!$D$4:$DS$4,J$3,CashFlow!$D$10:$DS$10) | K7: =SUMIF(CashFlow!$D$4:$DS$4,K$3,CashFlow!$D$10:$DS$10) | ... M7: =SUMIF(CashFlow!$D$4:$DS$4,M$3,CashFlow!$D$10:$DS$10)
A8: AN_CF_PAS | B8: Fruit: Passion fruit | C8: RWF | D8: =SUMIF(CashFlow!$D$4:$DS$4,D$3,CashFlow!$D$11:$DS$11) | E8: =SUMIF(CashFlow!$D$4:$DS$4,E$3,CashFlow!$D$11:$DS$11) | F8: =SUMIF(CashFlow!$D$4:$DS$4,F$3,CashFlow!$D$11:$DS$11) | G8: =SUMIF(CashFlow!$D$4:$DS$4,G$3,CashFlow!$D$11:$DS$11) | H8: =SUMIF(CashFlow!$D$4:$DS$4,H$3,CashFlow!$D$11:$DS$11) | I8: =SUMIF(CashFlow!$D$4:$DS$4,I$3,CashFlow!$D$11:$DS$11) | J8: =SUMIF(CashFlow!$D$4:$DS$4,J$3,CashFlow!$D$11:$DS$11) | K8: =SUMIF(CashFlow!$D$4:$DS$4,K$3,CashFlow!$D$11:$DS$11) | ... M8: =SUMIF(CashFlow!$D$4:$DS$4,M$3,CashFlow!$D$11:$DS$11)
A9: AN_CF_PAP | B9: Fruit: Papaya | C9: RWF | D9: =SUMIF(CashFlow!$D$4:$DS$4,D$3,CashFlow!$D$12:$DS$12) | E9: =SUMIF(CashFlow!$D$4:$DS$4,E$3,CashFlow!$D$12:$DS$12) | F9: =SUMIF(CashFlow!$D$4:$DS$4,F$3,CashFlow!$D$12:$DS$12) | G9: =SUMIF(CashFlow!$D$4:$DS$4,G$3,CashFlow!$D$12:$DS$12) | H9: =SUMIF(CashFlow!$D$4:$DS$4,H$3,CashFlow!$D$12:$DS$12) | I9: =SUMIF(CashFlow!$D$4:$DS$4,I$3,CashFlow!$D$12:$DS$12) | J9: =SUMIF(CashFlow!$D$4:$DS$4,J$3,CashFlow!$D$12:$DS$12) | K9: =SUMIF(CashFlow!$D$4:$DS$4,K$3,CashFlow!$D$12:$DS$12) | ... M9: =SUMIF(CashFlow!$D$4:$DS$4,M$3,CashFlow!$D$12:$DS$12)
A10: AN_CF_TTO | B10: Fruit: Tree tomato | C10: RWF | D10: =SUMIF(CashFlow!$D$4:$DS$4,D$3,CashFlow!$D$13:$DS$13) | E10: =SUMIF(CashFlow!$D$4:$DS$4,E$3,CashFlow!$D$13:$DS$13) | F10: =SUMIF(CashFlow!$D$4:$DS$4,F$3,CashFlow!$D$13:$DS$13) | G10: =SUMIF(CashFlow!$D$4:$DS$4,G$3,CashFlow!$D$13:$DS$13) | H10: =SUMIF(CashFlow!$D$4:$DS$4,H$3,CashFlow!$D$13:$DS$13) | I10: =SUMIF(CashFlow!$D$4:$DS$4,I$3,CashFlow!$D$13:$DS$13) | J10: =SUMIF(CashFlow!$D$4:$DS$4,J$3,CashFlow!$D$13:$DS$13) | K10: =SUMIF(CashFlow!$D$4:$DS$4,K$3,CashFlow!$D$13:$DS$13) | ... M10: =SUMIF(CashFlow!$D$4:$DS$4,M$3,CashFlow!$D$13:$DS$13)
A11: AN_CF_CIT | B11: Fruit: Citrus | C11: RWF | D11: =SUMIF(CashFlow!$D$4:$DS$4,D$3,CashFlow!$D$14:$DS$14) | E11: =SUMIF(CashFlow!$D$4:$DS$4,E$3,CashFlow!$D$14:$DS$14) | F11: =SUMIF(CashFlow!$D$4:$DS$4,F$3,CashFlow!$D$14:$DS$14) | G11: =SUMIF(CashFlow!$D$4:$DS$4,G$3,CashFlow!$D$14:$DS$14) | H11: =SUMIF(CashFlow!$D$4:$DS$4,H$3,CashFlow!$D$14:$DS$14) | I11: =SUMIF(CashFlow!$D$4:$DS$4,I$3,CashFlow!$D$14:$DS$14) | J11: =SUMIF(CashFlow!$D$4:$DS$4,J$3,CashFlow!$D$14:$DS$14) | K11: =SUMIF(CashFlow!$D$4:$DS$4,K$3,CashFlow!$D$14:$DS$14) | ... M11: =SUMIF(CashFlow!$D$4:$DS$4,M$3,CashFlow!$D$14:$DS$14)
A12: AN_CF_MAC | B12: Fruit: Macadamia (nut in shell) | C12: RWF | D12: =SUMIF(CashFlow!$D$4:$DS$4,D$3,CashFlow!$D$15:$DS$15) | E12: =SUMIF(CashFlow!$D$4:$DS$4,E$3,CashFlow!$D$15:$DS$15) | F12: =SUMIF(CashFlow!$D$4:$DS$4,F$3,CashFlow!$D$15:$DS$15) | G12: =SUMIF(CashFlow!$D$4:$DS$4,G$3,CashFlow!$D$15:$DS$15) | H12: =SUMIF(CashFlow!$D$4:$DS$4,H$3,CashFlow!$D$15:$DS$15) | I12: =SUMIF(CashFlow!$D$4:$DS$4,I$3,CashFlow!$D$15:$DS$15) | J12: =SUMIF(CashFlow!$D$4:$DS$4,J$3,CashFlow!$D$15:$DS$15) | K12: =SUMIF(CashFlow!$D$4:$DS$4,K$3,CashFlow!$D$15:$DS$15) | ... M12: =SUMIF(CashFlow!$D$4:$DS$4,M$3,CashFlow!$D$15:$DS$15)
A13: AN_CF_TIM | B13: Boundary poles | C13: RWF | D13: =SUMIF(CashFlow!$D$4:$DS$4,D$3,CashFlow!$D$16:$DS$16) | E13: =SUMIF(CashFlow!$D$4:$DS$4,E$3,CashFlow!$D$16:$DS$16) | F13: =SUMIF(CashFlow!$D$4:$DS$4,F$3,CashFlow!$D$16:$DS$16) | G13: =SUMIF(CashFlow!$D$4:$DS$4,G$3,CashFlow!$D$16:$DS$16) | H13: =SUMIF(CashFlow!$D$4:$DS$4,H$3,CashFlow!$D$16:$DS$16) | I13: =SUMIF(CashFlow!$D$4:$DS$4,I$3,CashFlow!$D$16:$DS$16) | J13: =SUMIF(CashFlow!$D$4:$DS$4,J$3,CashFlow!$D$16:$DS$16) | K13: =SUMIF(CashFlow!$D$4:$DS$4,K$3,CashFlow!$D$16:$DS$16) | ... M13: =SUMIF(CashFlow!$D$4:$DS$4,M$3,CashFlow!$D$16:$DS$16)
A14: AN_CF_GT_Y | B14: Goats: young stock | C14: RWF | D14: =SUMIF(CashFlow!$D$4:$DS$4,D$3,CashFlow!$D$17:$DS$17) | E14: =SUMIF(CashFlow!$D$4:$DS$4,E$3,CashFlow!$D$17:$DS$17) | F14: =SUMIF(CashFlow!$D$4:$DS$4,F$3,CashFlow!$D$17:$DS$17) | G14: =SUMIF(CashFlow!$D$4:$DS$4,G$3,CashFlow!$D$17:$DS$17) | H14: =SUMIF(CashFlow!$D$4:$DS$4,H$3,CashFlow!$D$17:$DS$17) | I14: =SUMIF(CashFlow!$D$4:$DS$4,I$3,CashFlow!$D$17:$DS$17) | J14: =SUMIF(CashFlow!$D$4:$DS$4,J$3,CashFlow!$D$17:$DS$17) | K14: =SUMIF(CashFlow!$D$4:$DS$4,K$3,CashFlow!$D$17:$DS$17) | ... M14: =SUMIF(CashFlow!$D$4:$DS$4,M$3,CashFlow!$D$17:$DS$17)
A15: AN_CF_GT_C | B15: Goats: culled adults | C15: RWF | D15: =SUMIF(CashFlow!$D$4:$DS$4,D$3,CashFlow!$D$18:$DS$18) | E15: =SUMIF(CashFlow!$D$4:$DS$4,E$3,CashFlow!$D$18:$DS$18) | F15: =SUMIF(CashFlow!$D$4:$DS$4,F$3,CashFlow!$D$18:$DS$18) | G15: =SUMIF(CashFlow!$D$4:$DS$4,G$3,CashFlow!$D$18:$DS$18) | H15: =SUMIF(CashFlow!$D$4:$DS$4,H$3,CashFlow!$D$18:$DS$18) | I15: =SUMIF(CashFlow!$D$4:$DS$4,I$3,CashFlow!$D$18:$DS$18) | J15: =SUMIF(CashFlow!$D$4:$DS$4,J$3,CashFlow!$D$18:$DS$18) | K15: =SUMIF(CashFlow!$D$4:$DS$4,K$3,CashFlow!$D$18:$DS$18) | ... M15: =SUMIF(CashFlow!$D$4:$DS$4,M$3,CashFlow!$D$18:$DS$18)
A16: AN_CF_SH_Y | B16: Sheep: young stock | C16: RWF | D16: =SUMIF(CashFlow!$D$4:$DS$4,D$3,CashFlow!$D$19:$DS$19) | E16: =SUMIF(CashFlow!$D$4:$DS$4,E$3,CashFlow!$D$19:$DS$19) | F16: =SUMIF(CashFlow!$D$4:$DS$4,F$3,CashFlow!$D$19:$DS$19) | G16: =SUMIF(CashFlow!$D$4:$DS$4,G$3,CashFlow!$D$19:$DS$19) | H16: =SUMIF(CashFlow!$D$4:$DS$4,H$3,CashFlow!$D$19:$DS$19) | I16: =SUMIF(CashFlow!$D$4:$DS$4,I$3,CashFlow!$D$19:$DS$19) | J16: =SUMIF(CashFlow!$D$4:$DS$4,J$3,CashFlow!$D$19:$DS$19) | K16: =SUMIF(CashFlow!$D$4:$DS$4,K$3,CashFlow!$D$19:$DS$19) | ... M16: =SUMIF(CashFlow!$D$4:$DS$4,M$3,CashFlow!$D$19:$DS$19)
A17: AN_CF_SH_C | B17: Sheep: culled adults | C17: RWF | D17: =SUMIF(CashFlow!$D$4:$DS$4,D$3,CashFlow!$D$20:$DS$20) | E17: =SUMIF(CashFlow!$D$4:$DS$4,E$3,CashFlow!$D$20:$DS$20) | F17: =SUMIF(CashFlow!$D$4:$DS$4,F$3,CashFlow!$D$20:$DS$20) | G17: =SUMIF(CashFlow!$D$4:$DS$4,G$3,CashFlow!$D$20:$DS$20) | H17: =SUMIF(CashFlow!$D$4:$DS$4,H$3,CashFlow!$D$20:$DS$20) | I17: =SUMIF(CashFlow!$D$4:$DS$4,I$3,CashFlow!$D$20:$DS$20) | J17: =SUMIF(CashFlow!$D$4:$DS$4,J$3,CashFlow!$D$20:$DS$20) | K17: =SUMIF(CashFlow!$D$4:$DS$4,K$3,CashFlow!$D$20:$DS$20) | ... M17: =SUMIF(CashFlow!$D$4:$DS$4,M$3,CashFlow!$D$20:$DS$20)
A18: AN_REV | B18: Total revenue | C18: RWF | D18: =SUM(D6:D17) | E18: =SUM(E6:E17) | F18: =SUM(F6:F17) | G18: =SUM(G6:G17) | H18: =SUM(H6:H17) | I18: =SUM(I6:I17) | J18: =SUM(J6:J17) | K18: =SUM(K6:K17) | ... M18: =SUM(M6:M17)
B20: Direct costs
A21: AN_CF_FEED | B21: Feed bought | C21: RWF | D21: =SUMIF(CashFlow!$D$4:$DS$4,D$3,CashFlow!$D$31:$DS$31) | E21: =SUMIF(CashFlow!$D$4:$DS$4,E$3,CashFlow!$D$31:$DS$31) | F21: =SUMIF(CashFlow!$D$4:$DS$4,F$3,CashFlow!$D$31:$DS$31) | G21: =SUMIF(CashFlow!$D$4:$DS$4,G$3,CashFlow!$D$31:$DS$31) | H21: =SUMIF(CashFlow!$D$4:$DS$4,H$3,CashFlow!$D$31:$DS$31) | I21: =SUMIF(CashFlow!$D$4:$DS$4,I$3,CashFlow!$D$31:$DS$31) | J21: =SUMIF(CashFlow!$D$4:$DS$4,J$3,CashFlow!$D$31:$DS$31) | K21: =SUMIF(CashFlow!$D$4:$DS$4,K$3,CashFlow!$D$31:$DS$31) | ... M21: =SUMIF(CashFlow!$D$4:$DS$4,M$3,CashFlow!$D$31:$DS$31)
A22: AN_CF_CONS | B22: Hay/silage conservation | C22: RWF | D22: =SUMIF(CashFlow!$D$4:$DS$4,D$3,CashFlow!$D$32:$DS$32) | E22: =SUMIF(CashFlow!$D$4:$DS$4,E$3,CashFlow!$D$32:$DS$32) | F22: =SUMIF(CashFlow!$D$4:$DS$4,F$3,CashFlow!$D$32:$DS$32) | G22: =SUMIF(CashFlow!$D$4:$DS$4,G$3,CashFlow!$D$32:$DS$32) | H22: =SUMIF(CashFlow!$D$4:$DS$4,H$3,CashFlow!$D$32:$DS$32) | I22: =SUMIF(CashFlow!$D$4:$DS$4,I$3,CashFlow!$D$32:$DS$32) | J22: =SUMIF(CashFlow!$D$4:$DS$4,J$3,CashFlow!$D$32:$DS$32) | K22: =SUMIF(CashFlow!$D$4:$DS$4,K$3,CashFlow!$D$32:$DS$32) | ... M22: =SUMIF(CashFlow!$D$4:$DS$4,M$3,CashFlow!$D$32:$DS$32)
A23: AN_CF_VET | B23: Veterinary care, medicines, minerals | C23: RWF | D23: =SUMIF(CashFlow!$D$4:$DS$4,D$3,CashFlow!$D$30:$DS$30) | E23: =SUMIF(CashFlow!$D$4:$DS$4,E$3,CashFlow!$D$30:$DS$30) | F23: =SUMIF(CashFlow!$D$4:$DS$4,F$3,CashFlow!$D$30:$DS$30) | G23: =SUMIF(CashFlow!$D$4:$DS$4,G$3,CashFlow!$D$30:$DS$30) | H23: =SUMIF(CashFlow!$D$4:$DS$4,H$3,CashFlow!$D$30:$DS$30) | I23: =SUMIF(CashFlow!$D$4:$DS$4,I$3,CashFlow!$D$30:$DS$30) | J23: =SUMIF(CashFlow!$D$4:$DS$4,J$3,CashFlow!$D$30:$DS$30) | K23: =SUMIF(CashFlow!$D$4:$DS$4,K$3,CashFlow!$D$30:$DS$30) | ... M23: =SUMIF(CashFlow!$D$4:$DS$4,M$3,CashFlow!$D$30:$DS$30)
A24: AN_CF_FERT | B24: Orchard inputs | C24: RWF | D24: =SUMIF(CashFlow!$D$4:$DS$4,D$3,CashFlow!$D$33:$DS$33) | E24: =SUMIF(CashFlow!$D$4:$DS$4,E$3,CashFlow!$D$33:$DS$33) | F24: =SUMIF(CashFlow!$D$4:$DS$4,F$3,CashFlow!$D$33:$DS$33) | G24: =SUMIF(CashFlow!$D$4:$DS$4,G$3,CashFlow!$D$33:$DS$33) | H24: =SUMIF(CashFlow!$D$4:$DS$4,H$3,CashFlow!$D$33:$DS$33) | I24: =SUMIF(CashFlow!$D$4:$DS$4,I$3,CashFlow!$D$33:$DS$33) | J24: =SUMIF(CashFlow!$D$4:$DS$4,J$3,CashFlow!$D$33:$DS$33) | K24: =SUMIF(CashFlow!$D$4:$DS$4,K$3,CashFlow!$D$33:$DS$33) | ... M24: =SUMIF(CashFlow!$D$4:$DS$4,M$3,CashFlow!$D$33:$DS$33)
A25: AN_CF_PASTM | B25: Pasture and fodder upkeep | C25: RWF | D25: =SUMIF(CashFlow!$D$4:$DS$4,D$3,CashFlow!$D$34:$DS$34) | E25: =SUMIF(CashFlow!$D$4:$DS$4,E$3,CashFlow!$D$34:$DS$34) | F25: =SUMIF(CashFlow!$D$4:$DS$4,F$3,CashFlow!$D$34:$DS$34) | G25: =SUMIF(CashFlow!$D$4:$DS$4,G$3,CashFlow!$D$34:$DS$34) | H25: =SUMIF(CashFlow!$D$4:$DS$4,H$3,CashFlow!$D$34:$DS$34) | I25: =SUMIF(CashFlow!$D$4:$DS$4,I$3,CashFlow!$D$34:$DS$34) | J25: =SUMIF(CashFlow!$D$4:$DS$4,J$3,CashFlow!$D$34:$DS$34) | K25: =SUMIF(CashFlow!$D$4:$DS$4,K$3,CashFlow!$D$34:$DS$34) | ... M25: =SUMIF(CashFlow!$D$4:$DS$4,M$3,CashFlow!$D$34:$DS$34)
A26: AN_CF_CASUAL | B26: Casual labour | C26: RWF | D26: =SUMIF(CashFlow!$D$4:$DS$4,D$3,CashFlow!$D$29:$DS$29) | E26: =SUMIF(CashFlow!$D$4:$DS$4,E$3,CashFlow!$D$29:$DS$29) | F26: =SUMIF(CashFlow!$D$4:$DS$4,F$3,CashFlow!$D$29:$DS$29) | G26: =SUMIF(CashFlow!$D$4:$DS$4,G$3,CashFlow!$D$29:$DS$29) | H26: =SUMIF(CashFlow!$D$4:$DS$4,H$3,CashFlow!$D$29:$DS$29) | I26: =SUMIF(CashFlow!$D$4:$DS$4,I$3,CashFlow!$D$29:$DS$29) | J26: =SUMIF(CashFlow!$D$4:$DS$4,J$3,CashFlow!$D$29:$DS$29) | K26: =SUMIF(CashFlow!$D$4:$DS$4,K$3,CashFlow!$D$29:$DS$29) | ... M26: =SUMIF(CashFlow!$D$4:$DS$4,M$3,CashFlow!$D$29:$DS$29)
A27: AN_CF_REPL | B27: Replanting short-cycle crops | C27: RWF | D27: =SUMIF(CashFlow!$D$4:$DS$4,D$3,CashFlow!$D$35:$DS$35) | E27: =SUMIF(CashFlow!$D$4:$DS$4,E$3,CashFlow!$D$35:$DS$35) | F27: =SUMIF(CashFlow!$D$4:$DS$4,F$3,CashFlow!$D$35:$DS$35) | G27: =SUMIF(CashFlow!$D$4:$DS$4,G$3,CashFlow!$D$35:$DS$35) | H27: =SUMIF(CashFlow!$D$4:$DS$4,H$3,CashFlow!$D$35:$DS$35) | I27: =SUMIF(CashFlow!$D$4:$DS$4,I$3,CashFlow!$D$35:$DS$35) | J27: =SUMIF(CashFlow!$D$4:$DS$4,J$3,CashFlow!$D$35:$DS$35) | K27: =SUMIF(CashFlow!$D$4:$DS$4,K$3,CashFlow!$D$35:$DS$35) | ... M27: =SUMIF(CashFlow!$D$4:$DS$4,M$3,CashFlow!$D$35:$DS$35)
A28: AN_CF_TRANSF | B28: Transport: fruit | C28: RWF | D28: =SUMIF(CashFlow!$D$4:$DS$4,D$3,CashFlow!$D$36:$DS$36) | E28: =SUMIF(CashFlow!$D$4:$DS$4,E$3,CashFlow!$D$36:$DS$36) | F28: =SUMIF(CashFlow!$D$4:$DS$4,F$3,CashFlow!$D$36:$DS$36) | G28: =SUMIF(CashFlow!$D$4:$DS$4,G$3,CashFlow!$D$36:$DS$36) | H28: =SUMIF(CashFlow!$D$4:$DS$4,H$3,CashFlow!$D$36:$DS$36) | I28: =SUMIF(CashFlow!$D$4:$DS$4,I$3,CashFlow!$D$36:$DS$36) | J28: =SUMIF(CashFlow!$D$4:$DS$4,J$3,CashFlow!$D$36:$DS$36) | K28: =SUMIF(CashFlow!$D$4:$DS$4,K$3,CashFlow!$D$36:$DS$36) | ... M28: =SUMIF(CashFlow!$D$4:$DS$4,M$3,CashFlow!$D$36:$DS$36)
A29: AN_CF_TRANSL | B29: Transport: livestock | C29: RWF | D29: =SUMIF(CashFlow!$D$4:$DS$4,D$3,CashFlow!$D$37:$DS$37) | E29: =SUMIF(CashFlow!$D$4:$DS$4,E$3,CashFlow!$D$37:$DS$37) | F29: =SUMIF(CashFlow!$D$4:$DS$4,F$3,CashFlow!$D$37:$DS$37) | G29: =SUMIF(CashFlow!$D$4:$DS$4,G$3,CashFlow!$D$37:$DS$37) | H29: =SUMIF(CashFlow!$D$4:$DS$4,H$3,CashFlow!$D$37:$DS$37) | I29: =SUMIF(CashFlow!$D$4:$DS$4,I$3,CashFlow!$D$37:$DS$37) | J29: =SUMIF(CashFlow!$D$4:$DS$4,J$3,CashFlow!$D$37:$DS$37) | K29: =SUMIF(CashFlow!$D$4:$DS$4,K$3,CashFlow!$D$37:$DS$37) | ... M29: =SUMIF(CashFlow!$D$4:$DS$4,M$3,CashFlow!$D$37:$DS$37)
A30: AN_CF_PACK | B30: Packaging | C30: RWF | D30: =SUMIF(CashFlow!$D$4:$DS$4,D$3,CashFlow!$D$38:$DS$38) | E30: =SUMIF(CashFlow!$D$4:$DS$4,E$3,CashFlow!$D$38:$DS$38) | F30: =SUMIF(CashFlow!$D$4:$DS$4,F$3,CashFlow!$D$38:$DS$38) | G30: =SUMIF(CashFlow!$D$4:$DS$4,G$3,CashFlow!$D$38:$DS$38) | H30: =SUMIF(CashFlow!$D$4:$DS$4,H$3,CashFlow!$D$38:$DS$38) | I30: =SUMIF(CashFlow!$D$4:$DS$4,I$3,CashFlow!$D$38:$DS$38) | J30: =SUMIF(CashFlow!$D$4:$DS$4,J$3,CashFlow!$D$38:$DS$38) | K30: =SUMIF(CashFlow!$D$4:$DS$4,K$3,CashFlow!$D$38:$DS$38) | ... M30: =SUMIF(CashFlow!$D$4:$DS$4,M$3,CashFlow!$D$38:$DS$38)
A31: AN_DIRECT | B31: Total direct costs | C31: RWF | D31: =SUM(D21:D30) | E31: =SUM(E21:E30) | F31: =SUM(F21:F30) | G31: =SUM(G21:G30) | H31: =SUM(H21:H30) | I31: =SUM(I21:I30) | J31: =SUM(J21:J30) | K31: =SUM(K21:K30) | ... M31: =SUM(M21:M30)
A32: AN_GM | B32: Gross margin | C32: RWF | D32: =D18-D31 | E32: =E18-E31 | F32: =F18-F31 | G32: =G18-G31 | H32: =H18-H31 | I32: =I18-I31 | J32: =J18-J31 | K32: =K18-K31 | ... M32: =M18-M31
A33: AN_GMPCT | B33: Gross margin % | C33: share | D33: =IF(D18>0,D32/D18,0) | E33: =IF(E18>0,E32/E18,0) | F33: =IF(F18>0,F32/F18,0) | G33: =IF(G18>0,G32/G18,0) | H33: =IF(H18>0,H32/H18,0) | I33: =IF(I18>0,I32/I18,0) | J33: =IF(J18>0,J32/J18,0) | K33: =IF(K18>0,K32/K18,0) | ... M33: =IF(M18>0,M32/M18,0)
B35: Overheads
A36: AN_CF_PERM | B36: Permanent labour | C36: RWF | D36: =SUMIF(CashFlow!$D$4:$DS$4,D$3,CashFlow!$D$28:$DS$28) | E36: =SUMIF(CashFlow!$D$4:$DS$4,E$3,CashFlow!$D$28:$DS$28) | F36: =SUMIF(CashFlow!$D$4:$DS$4,F$3,CashFlow!$D$28:$DS$28) | G36: =SUMIF(CashFlow!$D$4:$DS$4,G$3,CashFlow!$D$28:$DS$28) | H36: =SUMIF(CashFlow!$D$4:$DS$4,H$3,CashFlow!$D$28:$DS$28) | I36: =SUMIF(CashFlow!$D$4:$DS$4,I$3,CashFlow!$D$28:$DS$28) | J36: =SUMIF(CashFlow!$D$4:$DS$4,J$3,CashFlow!$D$28:$DS$28) | K36: =SUMIF(CashFlow!$D$4:$DS$4,K$3,CashFlow!$D$28:$DS$28) | ... M36: =SUMIF(CashFlow!$D$4:$DS$4,M$3,CashFlow!$D$28:$DS$28)
A37: AN_CF_MKTG | B37: Marketing and sales | C37: RWF | D37: =SUMIF(CashFlow!$D$4:$DS$4,D$3,CashFlow!$D$39:$DS$39) | E37: =SUMIF(CashFlow!$D$4:$DS$4,E$3,CashFlow!$D$39:$DS$39) | F37: =SUMIF(CashFlow!$D$4:$DS$4,F$3,CashFlow!$D$39:$DS$39) | G37: =SUMIF(CashFlow!$D$4:$DS$4,G$3,CashFlow!$D$39:$DS$39) | H37: =SUMIF(CashFlow!$D$4:$DS$4,H$3,CashFlow!$D$39:$DS$39) | I37: =SUMIF(CashFlow!$D$4:$DS$4,I$3,CashFlow!$D$39:$DS$39) | J37: =SUMIF(CashFlow!$D$4:$DS$4,J$3,CashFlow!$D$39:$DS$39) | K37: =SUMIF(CashFlow!$D$4:$DS$4,K$3,CashFlow!$D$39:$DS$39) | ... M37: =SUMIF(CashFlow!$D$4:$DS$4,M$3,CashFlow!$D$39:$DS$39)
A38: AN_CF_COMMS | B38: Communications and software | C38: RWF | D38: =SUMIF(CashFlow!$D$4:$DS$4,D$3,CashFlow!$D$40:$DS$40) | E38: =SUMIF(CashFlow!$D$4:$DS$4,E$3,CashFlow!$D$40:$DS$40) | F38: =SUMIF(CashFlow!$D$4:$DS$4,F$3,CashFlow!$D$40:$DS$40) | G38: =SUMIF(CashFlow!$D$4:$DS$4,G$3,CashFlow!$D$40:$DS$40) | H38: =SUMIF(CashFlow!$D$4:$DS$4,H$3,CashFlow!$D$40:$DS$40) | I38: =SUMIF(CashFlow!$D$4:$DS$4,I$3,CashFlow!$D$40:$DS$40) | J38: =SUMIF(CashFlow!$D$4:$DS$4,J$3,CashFlow!$D$40:$DS$40) | K38: =SUMIF(CashFlow!$D$4:$DS$4,K$3,CashFlow!$D$40:$DS$40) | ... M38: =SUMIF(CashFlow!$D$4:$DS$4,M$3,CashFlow!$D$40:$DS$40)
A39: AN_CF_UTIL | B39: Utilities and fuel | C39: RWF | D39: =SUMIF(CashFlow!$D$4:$DS$4,D$3,CashFlow!$D$41:$DS$41) | E39: =SUMIF(CashFlow!$D$4:$DS$4,E$3,CashFlow!$D$41:$DS$41) | F39: =SUMIF(CashFlow!$D$4:$DS$4,F$3,CashFlow!$D$41:$DS$41) | G39: =SUMIF(CashFlow!$D$4:$DS$4,G$3,CashFlow!$D$41:$DS$41) | H39: =SUMIF(CashFlow!$D$4:$DS$4,H$3,CashFlow!$D$41:$DS$41) | I39: =SUMIF(CashFlow!$D$4:$DS$4,I$3,CashFlow!$D$41:$DS$41) | J39: =SUMIF(CashFlow!$D$4:$DS$4,J$3,CashFlow!$D$41:$DS$41) | K39: =SUMIF(CashFlow!$D$4:$DS$4,K$3,CashFlow!$D$41:$DS$41) | ... M39: =SUMIF(CashFlow!$D$4:$DS$4,M$3,CashFlow!$D$41:$DS$41)
A40: AN_CF_ADMIN | B40: Administration and accounting | C40: RWF | D40: =SUMIF(CashFlow!$D$4:$DS$4,D$3,CashFlow!$D$42:$DS$42) | E40: =SUMIF(CashFlow!$D$4:$DS$4,E$3,CashFlow!$D$42:$DS$42) | F40: =SUMIF(CashFlow!$D$4:$DS$4,F$3,CashFlow!$D$42:$DS$42) | G40: =SUMIF(CashFlow!$D$4:$DS$4,G$3,CashFlow!$D$42:$DS$42) | H40: =SUMIF(CashFlow!$D$4:$DS$4,H$3,CashFlow!$D$42:$DS$42) | I40: =SUMIF(CashFlow!$D$4:$DS$4,I$3,CashFlow!$D$42:$DS$42) | J40: =SUMIF(CashFlow!$D$4:$DS$4,J$3,CashFlow!$D$42:$DS$42) | K40: =SUMIF(CashFlow!$D$4:$DS$4,K$3,CashFlow!$D$42:$DS$42) | ... M40: =SUMIF(CashFlow!$D$4:$DS$4,M$3,CashFlow!$D$42:$DS$42)
A41: AN_CF_INS | B41: Livestock insurance | C41: RWF | D41: =SUMIF(CashFlow!$D$4:$DS$4,D$3,CashFlow!$D$43:$DS$43) | E41: =SUMIF(CashFlow!$D$4:$DS$4,E$3,CashFlow!$D$43:$DS$43) | F41: =SUMIF(CashFlow!$D$4:$DS$4,F$3,CashFlow!$D$43:$DS$43) | G41: =SUMIF(CashFlow!$D$4:$DS$4,G$3,CashFlow!$D$43:$DS$43) | H41: =SUMIF(CashFlow!$D$4:$DS$4,H$3,CashFlow!$D$43:$DS$43) | I41: =SUMIF(CashFlow!$D$4:$DS$4,I$3,CashFlow!$D$43:$DS$43) | J41: =SUMIF(CashFlow!$D$4:$DS$4,J$3,CashFlow!$D$43:$DS$43) | K41: =SUMIF(CashFlow!$D$4:$DS$4,K$3,CashFlow!$D$43:$DS$43) | ... M41: =SUMIF(CashFlow!$D$4:$DS$4,M$3,CashFlow!$D$43:$DS$43)
A42: AN_CF_RM | B42: Repairs and maintenance | C42: RWF | D42: =SUMIF(CashFlow!$D$4:$DS$4,D$3,CashFlow!$D$44:$DS$44) | E42: =SUMIF(CashFlow!$D$4:$DS$4,E$3,CashFlow!$D$44:$DS$44) | F42: =SUMIF(CashFlow!$D$4:$DS$4,F$3,CashFlow!$D$44:$DS$44) | G42: =SUMIF(CashFlow!$D$4:$DS$4,G$3,CashFlow!$D$44:$DS$44) | H42: =SUMIF(CashFlow!$D$4:$DS$4,H$3,CashFlow!$D$44:$DS$44) | I42: =SUMIF(CashFlow!$D$4:$DS$4,I$3,CashFlow!$D$44:$DS$44) | J42: =SUMIF(CashFlow!$D$4:$DS$4,J$3,CashFlow!$D$44:$DS$44) | K42: =SUMIF(CashFlow!$D$4:$DS$4,K$3,CashFlow!$D$44:$DS$44) | ... M42: =SUMIF(CashFlow!$D$4:$DS$4,M$3,CashFlow!$D$44:$DS$44)
A43: AN_CF_LAND | B43: Land fees and taxes | C43: RWF | D43: =SUMIF(CashFlow!$D$4:$DS$4,D$3,CashFlow!$D$45:$DS$45) | E43: =SUMIF(CashFlow!$D$4:$DS$4,E$3,CashFlow!$D$45:$DS$45) | F43: =SUMIF(CashFlow!$D$4:$DS$4,F$3,CashFlow!$D$45:$DS$45) | G43: =SUMIF(CashFlow!$D$4:$DS$4,G$3,CashFlow!$D$45:$DS$45) | H43: =SUMIF(CashFlow!$D$4:$DS$4,H$3,CashFlow!$D$45:$DS$45) | I43: =SUMIF(CashFlow!$D$4:$DS$4,I$3,CashFlow!$D$45:$DS$45) | J43: =SUMIF(CashFlow!$D$4:$DS$4,J$3,CashFlow!$D$45:$DS$45) | K43: =SUMIF(CashFlow!$D$4:$DS$4,K$3,CashFlow!$D$45:$DS$45) | ... M43: =SUMIF(CashFlow!$D$4:$DS$4,M$3,CashFlow!$D$45:$DS$45)
A44: AN_OVER | B44: Total overheads | C44: RWF | D44: =SUM(D36:D43) | E44: =SUM(E36:E43) | F44: =SUM(F36:F43) | G44: =SUM(G36:G43) | H44: =SUM(H36:H43) | I44: =SUM(I36:I43) | J44: =SUM(J36:J43) | K44: =SUM(K36:K43) | ... M44: =SUM(M36:M43)
A46: AN_EBITDA | B46: EBITDA | C46: RWF | D46: =D32-D44 | E46: =E32-E44 | F46: =F32-F44 | G46: =G32-G44 | H46: =H32-H44 | I46: =I32-I44 | J46: =J32-J44 | K46: =K32-K44 | ... M46: =M32-M44
A47: AN_DEP | B47: Depreciation (incl. contingency) | C47: RWF | D47: =SUMPRODUCT((CapEx!$J$5:$J$34<=D$3)*(CapEx!$J$5:$J$34+CapEx!$K$5:$K$34>D$3)*CapEx!$L$5:$L$34)*(1+Assumptions!$H$10) | E47: =SUMPRODUCT((CapEx!$J$5:$J$34<=E$3)*(CapEx!$J$5:$J$34+CapEx!$K$5:$K$34>E$3)*CapEx!$L$5:$L$34)*(1+Assumptions!$H$10) | F47: =SUMPRODUCT((CapEx!$J$5:$J$34<=F$3)*(CapEx!$J$5:$J$34+CapEx!$K$5:$K$34>F$3)*CapEx!$L$5:$L$34)*(1+Assumptions!$H$10) | G47: =SUMPRODUCT((CapEx!$J$5:$J$34<=G$3)*(CapEx!$J$5:$J$34+CapEx!$K$5:$K$34>G$3)*CapEx!$L$5:$L$34)*(1+Assumptions!$H$10) | H47: =SUMPRODUCT((CapEx!$J$5:$J$34<=H$3)*(CapEx!$J$5:$J$34+CapEx!$K$5:$K$34>H$3)*CapEx!$L$5:$L$34)*(1+Assumptions!$H$10) | I47: =SUMPRODUCT((CapEx!$J$5:$J$34<=I$3)*(CapEx!$J$5:$J$34+CapEx!$K$5:$K$34>I$3)*CapEx!$L$5:$L$34)*(1+Assumptions!$H$10) | J47: =SUMPRODUCT((CapEx!$J$5:$J$34<=J$3)*(CapEx!$J$5:$J$34+CapEx!$K$5:$K$34>J$3)*CapEx!$L$5:$L$34)*(1+Assumptions!$H$10) | K47: =SUMPRODUCT((CapEx!$J$5:$J$34<=K$3)*(CapEx!$J$5:$J$34+CapEx!$K$5:$K$34>K$3)*CapEx!$L$5:$L$34)*(1+Assumptions!$H$10) | ... M47: =SUMPRODUCT((CapEx!$J$5:$J$34<=M$3)*(CapEx!$J$5:$J$34+CapEx!$K$5:$K$34>M$3)*CapEx!$L$5:$L$34)*(1+Assumptions!$H$10)
A48: AN_EBIT | B48: EBIT | C48: RWF | D48: =D46-D47 | E48: =E46-E47 | F48: =F46-F47 | G48: =G46-G47 | H48: =H46-H47 | I48: =I46-I47 | J48: =J46-J47 | K48: =K46-K47 | ... M48: =M46-M47
A49: AN_TAX | B49: Income tax (no loss carry-forward modelled) | C49: RWF | D49: =MAX(0,D48)*Assumptions!$H$8 | E49: =MAX(0,E48)*Assumptions!$H$8 | F49: =MAX(0,F48)*Assumptions!$H$8 | G49: =MAX(0,G48)*Assumptions!$H$8 | H49: =MAX(0,H48)*Assumptions!$H$8 | I49: =MAX(0,I48)*Assumptions!$H$8 | J49: =MAX(0,J48)*Assumptions!$H$8 | K49: =MAX(0,K48)*Assumptions!$H$8 | ... M49: =MAX(0,M48)*Assumptions!$H$8
A50: AN_NP | B50: Net profit | C50: RWF | D50: =D48-D49 | E50: =E48-E49 | F50: =F48-F49 | G50: =G48-G49 | H50: =H48-H49 | I50: =I48-I49 | J50: =J48-J49 | K50: =K48-K49 | ... M50: =M48-M49
B52: Cash flow (pre-financing)
A53: AN_COLLECT | B53: Collections | C53: RWF | D53: =SUMIF(CashFlow!$D$4:$DS$4,D$3,CashFlow!$D$25:$DS$25) | E53: =SUMIF(CashFlow!$D$4:$DS$4,E$3,CashFlow!$D$25:$DS$25) | F53: =SUMIF(CashFlow!$D$4:$DS$4,F$3,CashFlow!$D$25:$DS$25) | G53: =SUMIF(CashFlow!$D$4:$DS$4,G$3,CashFlow!$D$25:$DS$25) | H53: =SUMIF(CashFlow!$D$4:$DS$4,H$3,CashFlow!$D$25:$DS$25) | I53: =SUMIF(CashFlow!$D$4:$DS$4,I$3,CashFlow!$D$25:$DS$25) | J53: =SUMIF(CashFlow!$D$4:$DS$4,J$3,CashFlow!$D$25:$DS$25) | K53: =SUMIF(CashFlow!$D$4:$DS$4,K$3,CashFlow!$D$25:$DS$25) | ... M53: =SUMIF(CashFlow!$D$4:$DS$4,M$3,CashFlow!$D$25:$DS$25)
A54: AN_OPEX | B54: Operating costs | C54: RWF | D54: =SUMIF(CashFlow!$D$4:$DS$4,D$3,CashFlow!$D$46:$DS$46) | E54: =SUMIF(CashFlow!$D$4:$DS$4,E$3,CashFlow!$D$46:$DS$46) | F54: =SUMIF(CashFlow!$D$4:$DS$4,F$3,CashFlow!$D$46:$DS$46) | G54: =SUMIF(CashFlow!$D$4:$DS$4,G$3,CashFlow!$D$46:$DS$46) | H54: =SUMIF(CashFlow!$D$4:$DS$4,H$3,CashFlow!$D$46:$DS$46) | I54: =SUMIF(CashFlow!$D$4:$DS$4,I$3,CashFlow!$D$46:$DS$46) | J54: =SUMIF(CashFlow!$D$4:$DS$4,J$3,CashFlow!$D$46:$DS$46) | K54: =SUMIF(CashFlow!$D$4:$DS$4,K$3,CashFlow!$D$46:$DS$46) | ... M54: =SUMIF(CashFlow!$D$4:$DS$4,M$3,CashFlow!$D$46:$DS$46)
A55: AN_CAPEX | B55: Capital items incl. contingency | C55: RWF | D55: =SUMIF(CashFlow!$D$4:$DS$4,D$3,CashFlow!$D$51:$DS$51) | E55: =SUMIF(CashFlow!$D$4:$DS$4,E$3,CashFlow!$D$51:$DS$51) | F55: =SUMIF(CashFlow!$D$4:$DS$4,F$3,CashFlow!$D$51:$DS$51) | G55: =SUMIF(CashFlow!$D$4:$DS$4,G$3,CashFlow!$D$51:$DS$51) | H55: =SUMIF(CashFlow!$D$4:$DS$4,H$3,CashFlow!$D$51:$DS$51) | I55: =SUMIF(CashFlow!$D$4:$DS$4,I$3,CashFlow!$D$51:$DS$51) | J55: =SUMIF(CashFlow!$D$4:$DS$4,J$3,CashFlow!$D$51:$DS$51) | K55: =SUMIF(CashFlow!$D$4:$DS$4,K$3,CashFlow!$D$51:$DS$51) | ... M55: =SUMIF(CashFlow!$D$4:$DS$4,M$3,CashFlow!$D$51:$DS$51)
A56: AN_ANIMALS | B56: Animal purchases | C56: RWF | D56: =SUMIF(CashFlow!$D$4:$DS$4,D$3,CashFlow!$D$52:$DS$52) | E56: =SUMIF(CashFlow!$D$4:$DS$4,E$3,CashFlow!$D$52:$DS$52) | F56: =SUMIF(CashFlow!$D$4:$DS$4,F$3,CashFlow!$D$52:$DS$52) | G56: =SUMIF(CashFlow!$D$4:$DS$4,G$3,CashFlow!$D$52:$DS$52) | H56: =SUMIF(CashFlow!$D$4:$DS$4,H$3,CashFlow!$D$52:$DS$52) | I56: =SUMIF(CashFlow!$D$4:$DS$4,I$3,CashFlow!$D$52:$DS$52) | J56: =SUMIF(CashFlow!$D$4:$DS$4,J$3,CashFlow!$D$52:$DS$52) | K56: =SUMIF(CashFlow!$D$4:$DS$4,K$3,CashFlow!$D$52:$DS$52) | ... M56: =SUMIF(CashFlow!$D$4:$DS$4,M$3,CashFlow!$D$52:$DS$52)
A57: AN_TAXPAID | B57: Income tax paid | C57: RWF | D57: =SUMIF(CashFlow!$D$4:$DS$4,D$3,CashFlow!$D$55:$DS$55) | E57: =SUMIF(CashFlow!$D$4:$DS$4,E$3,CashFlow!$D$55:$DS$55) | F57: =SUMIF(CashFlow!$D$4:$DS$4,F$3,CashFlow!$D$55:$DS$55) | G57: =SUMIF(CashFlow!$D$4:$DS$4,G$3,CashFlow!$D$55:$DS$55) | H57: =SUMIF(CashFlow!$D$4:$DS$4,H$3,CashFlow!$D$55:$DS$55) | I57: =SUMIF(CashFlow!$D$4:$DS$4,I$3,CashFlow!$D$55:$DS$55) | J57: =SUMIF(CashFlow!$D$4:$DS$4,J$3,CashFlow!$D$55:$DS$55) | K57: =SUMIF(CashFlow!$D$4:$DS$4,K$3,CashFlow!$D$55:$DS$55) | ... M57: =SUMIF(CashFlow!$D$4:$DS$4,M$3,CashFlow!$D$55:$DS$55)
A58: AN_NET | B58: Net cash flow | C58: RWF | D58: =D53-D54-D55-D56-D57 | E58: =E53-E54-E55-E56-E57 | F58: =F53-F54-F55-F56-F57 | G58: =G53-G54-G55-G56-G57 | H58: =H53-H54-H55-H56-H57 | I58: =I53-I54-I55-I56-I57 | J58: =J53-J54-J55-J56-J57 | K58: =K53-K54-K55-K56-K57 | ... M58: =M53-M54-M55-M56-M57
A59: AN_CUM | B59: Cumulative net cash flow | C59: RWF | D59: =0+D58 | E59: =D59+E58 | F59: =E59+F58 | G59: =F59+G58 | H59: =G59+H58 | I59: =H59+I58 | J59: =I59+J58 | K59: =J59+K58 | L59: =K59+L58 | M59: =L59+M58
A60: AN_DF | B60: Discount factor (end of year) | C60: factor | D60: =1/(1+Assumptions!$H$7)^D$3 | E60: =1/(1+Assumptions!$H$7)^E$3 | F60: =1/(1+Assumptions!$H$7)^F$3 | G60: =1/(1+Assumptions!$H$7)^G$3 | H60: =1/(1+Assumptions!$H$7)^H$3 | I60: =1/(1+Assumptions!$H$7)^I$3 | J60: =1/(1+Assumptions!$H$7)^J$3 | K60: =1/(1+Assumptions!$H$7)^K$3 | ... M60: =1/(1+Assumptions!$H$7)^M$3
A61: AN_PV | B61: Present value of net cash flow | C61: RWF | D61: =D58*D60 | E61: =E58*E60 | F61: =F58*F60 | G61: =G58*G60 | H61: =H58*H60 | I61: =I58*I60 | J61: =J58*J60 | K61: =K58*K60 | ... M61: =M58*M60
A62: AN_PAYBACK | B62: Payback marker | C62: year | D62: =IF(D59>=0,D$3,"") | E62: =IF(AND(E59>=0,D59<0),E$3,"") | F62: =IF(AND(F59>=0,E59<0),F$3,"") | G62: =IF(AND(G59>=0,F59<0),G$3,"") | H62: =IF(AND(H59>=0,G59<0),H$3,"") | I62: =IF(AND(I59>=0,H59<0),I$3,"") | J62: =IF(AND(J59>=0,I59<0),J$3,"") | K62: =IF(AND(K59>=0,J59<0),K$3,"") | L62: =IF(AND(L59>=0,K59<0),L$3,"") | M62: =IF(AND(M59>=0,L59<0),M$3,"")
A63: AN_BE | B63: Operating break-even marker (EBITDA > 0) | C63: year | D63: =IF(D46>0,D$3,"") | E63: =IF(E46>0,E$3,"") | F63: =IF(F46>0,F$3,"") | G63: =IF(G46>0,G$3,"") | H63: =IF(H46>0,H$3,"") | I63: =IF(I46>0,I$3,"") | J63: =IF(J46>0,J$3,"") | K63: =IF(K46>0,K$3,"") | ... M63: =IF(M46>0,M$3,"")
B65: Operating indicators
A66: AN_KG | B66: Fruit marketed | C66: kg | D66: =SUMIF(CashFlow!$D$4:$DS$4,D$3,CashFlow!$D$22:$DS$22) | E66: =SUMIF(CashFlow!$D$4:$DS$4,E$3,CashFlow!$D$22:$DS$22) | F66: =SUMIF(CashFlow!$D$4:$DS$4,F$3,CashFlow!$D$22:$DS$22) | G66: =SUMIF(CashFlow!$D$4:$DS$4,G$3,CashFlow!$D$22:$DS$22) | H66: =SUMIF(CashFlow!$D$4:$DS$4,H$3,CashFlow!$D$22:$DS$22) | I66: =SUMIF(CashFlow!$D$4:$DS$4,I$3,CashFlow!$D$22:$DS$22) | J66: =SUMIF(CashFlow!$D$4:$DS$4,J$3,CashFlow!$D$22:$DS$22) | K66: =SUMIF(CashFlow!$D$4:$DS$4,K$3,CashFlow!$D$22:$DS$22) | ... M66: =SUMIF(CashFlow!$D$4:$DS$4,M$3,CashFlow!$D$22:$DS$22)
A67: AN_GT_F | B67: Goats: breeding females at year end | C67: head | D67: =INDEX(Livestock!$D$18:$DS$18,1,12*D$3) | E67: =INDEX(Livestock!$D$18:$DS$18,1,12*E$3) | F67: =INDEX(Livestock!$D$18:$DS$18,1,12*F$3) | G67: =INDEX(Livestock!$D$18:$DS$18,1,12*G$3) | H67: =INDEX(Livestock!$D$18:$DS$18,1,12*H$3) | I67: =INDEX(Livestock!$D$18:$DS$18,1,12*I$3) | J67: =INDEX(Livestock!$D$18:$DS$18,1,12*J$3) | K67: =INDEX(Livestock!$D$18:$DS$18,1,12*K$3) | ... M67: =INDEX(Livestock!$D$18:$DS$18,1,12*M$3)
A68: AN_SH_F | B68: Sheep: breeding females at year end | C68: head | D68: =INDEX(Livestock!$D$42:$DS$42,1,12*D$3) | E68: =INDEX(Livestock!$D$42:$DS$42,1,12*E$3) | F68: =INDEX(Livestock!$D$42:$DS$42,1,12*F$3) | G68: =INDEX(Livestock!$D$42:$DS$42,1,12*G$3) | H68: =INDEX(Livestock!$D$42:$DS$42,1,12*H$3) | I68: =INDEX(Livestock!$D$42:$DS$42,1,12*I$3) | J68: =INDEX(Livestock!$D$42:$DS$42,1,12*J$3) | K68: =INDEX(Livestock!$D$42:$DS$42,1,12*K$3) | ... M68: =INDEX(Livestock!$D$42:$DS$42,1,12*M$3)
A69: AN_FDEM | B69: Feed demand | C69: kg DM | D69: =SUMIF(CashFlow!$D$4:$DS$4,D$3,Feed!$D$8:$DS$8) | E69: =SUMIF(CashFlow!$D$4:$DS$4,E$3,Feed!$D$8:$DS$8) | F69: =SUMIF(CashFlow!$D$4:$DS$4,F$3,Feed!$D$8:$DS$8) | G69: =SUMIF(CashFlow!$D$4:$DS$4,G$3,Feed!$D$8:$DS$8) | H69: =SUMIF(CashFlow!$D$4:$DS$4,H$3,Feed!$D$8:$DS$8) | I69: =SUMIF(CashFlow!$D$4:$DS$4,I$3,Feed!$D$8:$DS$8) | J69: =SUMIF(CashFlow!$D$4:$DS$4,J$3,Feed!$D$8:$DS$8) | K69: =SUMIF(CashFlow!$D$4:$DS$4,K$3,Feed!$D$8:$DS$8) | ... M69: =SUMIF(CashFlow!$D$4:$DS$4,M$3,Feed!$D$8:$DS$8)
A70: AN_FBUY | B70: Feed bought | C70: kg DM | D70: =SUMIF(CashFlow!$D$4:$DS$4,D$3,Feed!$D$17:$DS$17) | E70: =SUMIF(CashFlow!$D$4:$DS$4,E$3,Feed!$D$17:$DS$17) | F70: =SUMIF(CashFlow!$D$4:$DS$4,F$3,Feed!$D$17:$DS$17) | G70: =SUMIF(CashFlow!$D$4:$DS$4,G$3,Feed!$D$17:$DS$17) | H70: =SUMIF(CashFlow!$D$4:$DS$4,H$3,Feed!$D$17:$DS$17) | I70: =SUMIF(CashFlow!$D$4:$DS$4,I$3,Feed!$D$17:$DS$17) | J70: =SUMIF(CashFlow!$D$4:$DS$4,J$3,Feed!$D$17:$DS$17) | K70: =SUMIF(CashFlow!$D$4:$DS$4,K$3,Feed!$D$17:$DS$17) | ... M70: =SUMIF(CashFlow!$D$4:$DS$4,M$3,Feed!$D$17:$DS$17)
A71: AN_FSELF | B71: Feed self-sufficiency | C71: share | D71: =IF(D69>0,1-D70/D69,1) | E71: =IF(E69>0,1-E70/E69,1) | F71: =IF(F69>0,1-F70/F69,1) | G71: =IF(G69>0,1-G70/G69,1) | H71: =IF(H69>0,1-H70/H69,1) | I71: =IF(I69>0,1-I70/I69,1) | J71: =IF(J69>0,1-J70/J69,1) | K71: =IF(K69>0,1-K70/K69,1) | ... M71: =IF(M69>0,1-M70/M69,1)

Sheet Metrics
A1: Metrics
A2: Headline results for the selected scenario and model. Placeholder inputs make these illustrative only.
A4: Key | B4: Metric | C4: Value | D4: Unit / note
A5: MX_SCEN | B5: Scenario | C5: =Control!$C$14
A6: MX_MODEL | B6: Farm model | C6: =Control!$C$15
A7: MX_CAP | B7: Capital available, years 1–2 | C7: =Control!$C$8 | D7: RWF
A8: MX_INV10 | B8: Total investment over 10 years (capital items + animals) | C8: =SUM(Annual!$D$55:$M$55)+SUM(Annual!$D$56:$M$56) | D8: RWF
A9: MX_INV24 | B9: Investment in months 1–24 | C9: =SUM(CashFlow!$D$53:$AA$53) | D9: RWF
A10: MX_PEAK | B10: Peak funding need (lowest cumulative cash) | C10: =MAX(0,-MIN(CashFlow!$D$58:$DS$58)) | D10: RWF
A11: MX_PEAKM | B11: Month of peak funding need | C11: =MATCH(MIN(CashFlow!$D$58:$DS$58),CashFlow!$D$58:$DS$58,0) | D11: model month
A12: MX_GAP | B12: FUNDING GAP (peak need less capital available) | C12: =MAX(0,C10-C7) | D12: RWF
A13: MX_GAPUSD | B13: Funding gap in USD | C13: =C12/Assumptions!$H$6 | D13: USD at the Assumptions rate
A14: MX_NPV | B14: NPV, 10 years, real, no terminal value | C14: =NPV(Assumptions!$H$7,Annual!$D$58:$M$58) | D14: RWF
A15: MX_IRR | B15: IRR, 10 years | C15: =IFERROR(IRR(Annual!$D$58:$M$58),"n/a") | D15: share
A16: MX_PAYBACK | B16: Payback year (cumulative cash turns positive) | C16: =IF(COUNT(Annual!$D$62:$M$62)=0,"beyond Y10",MIN(Annual!$D$62:$M$62)) | D16: farm year
A17: MX_BE | B17: First year with positive EBITDA | C17: =IF(COUNT(Annual!$D$63:$M$63)=0,"beyond Y10",MIN(Annual!$D$63:$M$63)) | D17: farm year
A18: MX_REV5 | B18: Revenue, year 5 | C18: =Annual!H18 | D18: RWF
A19: MX_REV10 | B19: Revenue, year 10 | C19: =Annual!M18 | D19: RWF
A20: MX_EBITDA5 | B20: EBITDA, year 5 | C20: =Annual!H46 | D20: RWF
A21: MX_EBITDA10 | B21: EBITDA, year 10 | C21: =Annual!M46 | D21: RWF
A22: MX_ROIC | B22: Return on invested capital, average Y6–Y10 (after tax) | C22: =IFERROR(AVERAGE(Annual!I48:M48)*(1-Assumptions!$H$8)/C8,"n/a") | D22: share
A23: MX_FSELF5 | B23: Feed self-sufficiency, year 5 | C23: =Annual!H71 | D23: share
A24: MX_TIMBER | B24: Memo: standing boundary-timber value at Y10 (not in NPV) | C24: =Trees!$C$93 | D24: RWF
B26: Checks (all should read OK)
B27: Land shares sum to 100% | C27: =IF(ABS(Land!$C$25-1)<0.0001,"OK","CHECK")
B28: Orchard mix sums to 100% | C28: =IF(ABS(Land!$C$26-1)<0.0001,"OK","CHECK")
B29: Monthly sales tie to annual revenue | C29: =IF(ABS(SUM(CashFlow!$D$21:$DS$21)-SUM(Annual!$D$18:$M$18))<1,"OK","CHECK")
B30: Monthly net cash ties to annual net cash | C30: =IF(ABS(SUM(CashFlow!$D$57:$DS$57)-SUM(Annual!$D$58:$M$58))<1,"OK","CHECK")
B31: Monthly tax ties to annual tax | C31: =IF(ABS(SUM(CashFlow!$D$55:$DS$55)-SUM(Annual!$D$49:$M$49))<1,"OK","CHECK")
B32: Herd never negative | C32: =IF(MIN(MIN(Livestock!$D$18:$DS$18),MIN(Livestock!$D$42:$DS$42))>=-0.0001,"OK","CHECK")
B33: Harvest seasonality sums to 1 for every crop | C33: =IF(AND(ABS(Curves!$P$15-1)<0.001,ABS(Curves!$P$16-1)<0.001,ABS(Curves!$P$17-1)<0.001,ABS(Curves!$P$18-1)<0.001,ABS(Curves!$P$19-1)<0.001,ABS(Curves!$P$20-1)<0.001,ABS(Curves!$P$21-1)<0.001),"OK","CHECK")
B34: Pasture growth averages 1 | C34: =IF(ABS(Curves!$P$25-1)<0.001,"OK","CHECK")
